Workbook
Name Bancos: OFFSET(#REF!,0,0,COUNTA(#REF!)-1)
Name FromOrganiz_1: _xlfn.ANCHORARRAY('Para Inf Web'!$A$5)
Name SegmentaciónDeDatos_Año: #N/A
Name SegmentaciónDeDatos_CtaCtbl: #N/A
Name SegmentaciónDeDatos_CtaCtbl2: #N/A
Name SegmentaciónDeDatos_Descripción: #N/A
Name SegmentaciónDeDatos_Mes: #N/A
Name UF: #REF!

Sheet Top 5
A1: Top 5 - Ingresos | D1: Top 5 - Egresos
A2: Año | B2: 2025 | D2: Año | E2: 2025
A3: Mes | B3: Noviembre | D3: Mes | E3: Noviembre
A5: Etiquetas de fila | D5: Etiquetas de fila | E5: Cargos
A6: Cuota Ordinaria | D6: Cuota Ordinaria | E6: 0
A7: Pago Comisiones | D7: Pago Comisiones | E7: 23569
A8: Sitio corporativo web | D8: Sitio corporativo web | E8: 207152
A9: Taxi, Uber o Similar | D9: Taxi, Uber o Similar | E9: 6294
A10: Total general | D10: Total general | E10: 237015

Sheet Para Inf Web
A1: Año | B1: 2025 | D1: =UPPER("Finanzas "&B2&" del "&B1) -> FINANZAS DICIEMBRE DEL 2025
A2: Mes | B2: Diciembre | D2: =UPPER("Distribución de los Egresos a "&B2&" del "&B1) -> DISTRIBUCIÓN DE LOS EGRESOS A DICIEMBRE DEL 2025 | G2: Saldo | I2: =G3+I3 -> 17877600
G3: =SUBTOTAL(9,G5:G1000) -> 17877600 | H3: =SUBTOTAL(9,H5:H1000) -> 0 | I3: =SUBTOTAL(9,I5:I1000) -> 0
A5: {=_xlfn.LET( _xlpm.Filtrados, _xlfn.LET( _xlpm.datos,_xlfn.CHOOSECOLS(Banco[],1,2,8,9,13), _xlfn._xlws.FILTER(_xlpm.datos,(_xlfn.CHOOSECOLS(_xlpm.datos,1)=B1)*(_xlfn.CHOOSECOLS(_xlpm.datos,2)=B2),"Sin Datos") ), _xlfn.GROUPBY( _xlpm.Filtrados,_xlfn.CHOOSECOLS(_xlpm.Filtrados,3,4),_xleta.SUM ) )} -> 2025 | B5: Diciembre | C5: 0 | D5: 8938800 | E5: Cuota Ordinaria | F5: 0 | G5: 8938800
A6: 2025 | B6: Diciembre | C6: 23588 | D6: 0 | E6: Pago Comisiones | F6: 23588 | G6: 0
A7: 2025 | B7: Diciembre | C7: 39500 | D7: 0 | E7: Coronas de Caridad Condolencias | F7: 39500 | G7: 0
A8: 2025 | B8: Diciembre | C8: 350000 | D8: 0 | E8: Asesoria Legal - Convenio Fijo Mensual | F8: 1400000 | G8: 0
A9: 2025 | B9: Diciembre | C9: 500000 | D9: 0 | E9: Regalo Corportivo (Aniversario) | F9: 500000 | G9: 0
A10: 2025 | B10: Diciembre | C10: 1457600 | D10: 0 | E10: Regalo Corportivo (Aniversario) | F10: 1457600 | G10: 0
A11: 2025 | B11: Diciembre | C11: 5000000 | D11: 0 | E11: Regalo Corportivo (Aniversario) | F11: 15000000 | G11: 0
A12: Total | F12: 18420688 | G12: 8938800
B32: {=_xludf.UNIQUE(_xlfn._xlws.FILTER(Banco[Nombre Cuenta],(Banco[Año]=B1)*(Banco[Mes]=B2)))} -> #NAME?

Sheet Hoja1
T1: Año | U1: Mes
T2: 2021 | U2: Enero
T3: 2022 | U3: Febrero
T4: 2023 | U4: Marzo
T5: 2024 | U5: Abril
T6: 2025 | U6: Mayo
T7: 2026 | U7: Junio
U8: Julio
U9: Agosto
U10: Septiembre
U11: Octubre
U12: Noviembre
U13: Diciembre

Sheet Banco
G9: Saldo | I9: =I11+G11 -> 8361633
F11: =SUBTOTAL(9,F231:F10064) -> 0 | G11: =SUBTOTAL(9,G13:G1028) -> -18824299 | I11: =SUBTOTAL(9,I13:I1028) -> 27185932 | J11: =SUBTOTAL(9,J13:J10064) -> 0 | K11: =SUBTOTAL(9,(K12:K1028)) -> 8361633
A12: Año | B12: Mes | C12: Periodo Contable | D12: Fecha | E12: Descripción | F12: N° Doc. | G12: cargos | H12: Egresos | I12: Ingresos | J12: Saldo | K12: Monto | L12: CtaCtbl | M12: Nombre Cuenta | N12: Observacion del Gasto o Abono / Link a Document0o Respaldo | O12: Cartola
A13: =YEAR(Banco[[#This Row],[Fecha]]) -> 2021 | B13: =PROPER(TEXT(Banco[[#This Row],[Fecha]],"MMMM")) -> Septiembre | C13: =TEXT(Banco[[#This Row],[Fecha]],"mmm-yyyy") -> sept-2021 | D13: 44440 | E13: APERTURA CUENTA CORRIENTE | F13: ------- | G13: 0 | H13: =Banco[[#This Row],[cargos]]*-1 -> 0 | I13: 0 | J13: 0 | K13: =+Banco[[#This Row],[cargos]]+Banco[[#This Row],[Ingresos]] -> 0 | L13: 3.03.03 - Otros Pagos | M13: =MID(Banco[[#This Row],[CtaCtbl]],FIND(" - ",Banco[[#This Row],[CtaCtbl]])+3,40) -> Otros Pagos
A14: =YEAR(Banco[[#This Row],[Fecha]]) -> 2021 | B14: =PROPER(TEXT(Banco[[#This Row],[Fecha]],"MMMM")) -> Octubre | C14: =TEXT(Banco[[#This Row],[Fecha]],"mmm-yyyy") -> oct-2021 | D14: 44496 | E14: PROVEEDORE 96505760-9 COLBUN M | G14: 0 | H14: =Banco[[#This Row],[cargos]]*-1 -> 0 | I14: 2349346 | K14: =+Banco[[#This Row],[cargos]]+Banco[[#This Row],[Ingresos]] -> 2349346 | L14: 1.01.02 - Cuota Extraordinaria | M14: =MID(Banco[[#This Row],[CtaCtbl]],FIND(" - ",Banco[[#This Row],[CtaCtbl]])+3,40) -> Cuota Extraordinaria
A15: =YEAR(Banco[[#This Row],[Fecha]]) -> 2021 | B15: =PROPER(TEXT(Banco[[#This Row],[Fecha]],"MMMM")) -> Octubre | C15: =TEXT(Banco[[#This Row],[Fecha]],"mmm-yyyy") -> oct-2021 | D15: 44496 | E15: PROVEEDORE 96505760-9 COLBUN M | G15: 0 | H15: =Banco[[#This Row],[cargos]]*-1 -> 0 | I15: 4445566 | J15: 6794912 | K15: =+Banco[[#This Row],[cargos]]+Banco[[#This Row],[Ingresos]] -> 4445566 | L15: 1.01.01 - Cuota Ordinaria | M15: =MID(Banco[[#This Row],[CtaCtbl]],FIND(" - ",Banco[[#This Row],[CtaCtbl]])+3,40) -> Cuota Ordinaria
A16: =YEAR(Banco[[#This Row],[Fecha]]) -> 2021 | B16: =PROPER(TEXT(Banco[[#This Row],[Fecha]],"MMMM")) -> Noviembre | C16: =TEXT(Banco[[#This Row],[Fecha]],"mmm-yyyy") -> nov-2021 | D16: 44509 | E16: TEF 14082906-4 Alejandra Saldi | G16: -234341 | H16: =Banco[[#This Row],[cargos]]*-1 -> 234341 | I16: 0 | J16: 6560571 | K16: =+Banco[[#This Row],[cargos]]+Banco[[#This Row],[Ingresos]] -> -234341 | L16: 2.01.03.03.1.9 - Traslado Terrestre Van/Taxi,etc | M16: =MID(Banco[[#This Row],[CtaCtbl]],FIND(" - ",Banco[[#This Row],[CtaCtbl]])+3,40) -> Traslado Terrestre Van/Taxi,etc
A17: =YEAR(Banco[[#This Row],[Fecha]]) -> 2021 | B17: =PROPER(TEXT(Banco[[#This Row],[Fecha]],"MMMM")) -> Noviembre | C17: =TEXT(Banco[[#This Row],[Fecha]],"mmm-yyyy") -> nov-2021 | D17: 44509 | E17: TEF 17412336-5 Robinson Cornej | G17: -380230 | H17: =Banco[[#This Row],[cargos]]*-1 -> 380230 | I17: 0 | J17: 6180341 | K17: =+Banco[[#This Row],[cargos]]+Banco[[#This Row],[Ingresos]] -> -380230 | L17: 2.01.03.03.1.9 - Traslado Terrestre Van/Taxi,etc | M17: =MID(Banco[[#This Row],[CtaCtbl]],FIND(" - ",Banco[[#This Row],[CtaCtbl]])+3,40) -> Traslado Terrestre Van/Taxi,etc
A18: =YEAR(Banco[[#This Row],[Fecha]]) -> 2021 | B18: =PROPER(TEXT(Banco[[#This Row],[Fecha]],"MMMM")) -> Noviembre | C18: =TEXT(Banco[[#This Row],[Fecha]],"mmm-yyyy") -> nov-2021 | D18: 44509 | E18: TEF 76194207-7 Estudio Juridic | G18: -108500 | H18: =Banco[[#This Row],[cargos]]*-1 -> 108500 | I18: 0 | J18: 6071841 | K18: =+Banco[[#This Row],[cargos]]+Banco[[#This Row],[Ingresos]] -> -108500 | L18: 2.01.01.01.1 - Asesoria Legal - Convenio Fijo Mensual | M18: =MID(Banco[[#This Row],[CtaCtbl]],FIND(" - ",Banco[[#This Row],[CtaCtbl]])+3,40) -> Asesoria Legal - Convenio Fijo Mensual
A19: =YEAR(Banco[[#This Row],[Fecha]]) -> 2021 | B19: =PROPER(TEXT(Banco[[#This Row],[Fecha]],"MMMM")) -> Noviembre | C19: =TEXT(Banco[[#This Row],[Fecha]],"mmm-yyyy") -> nov-2021 | D19: 44526 | E19: PROVEEDORE 96505760-9 COLBUN M | G19: 0 | H19: =Banco[[#This Row],[cargos]]*-1 -> 0 | I19: 107667 | K19: =+Banco[[#This Row],[cargos]]+Banco[[#This Row],[Ingresos]] -> 107667 | L19: 1.01.02 - Cuota Extraordinaria | M19: =MID(Banco[[#This Row],[CtaCtbl]],FIND(" - ",Banco[[#This Row],[CtaCtbl]])+3,40) -> Cuota Extraordinaria
A20: =YEAR(Banco[[#This Row],[Fecha]]) -> 2021 | B20: =PROPER(TEXT(Banco[[#This Row],[Fecha]],"MMMM")) -> Noviembre | C20: =TEXT(Banco[[#This Row],[Fecha]],"mmm-yyyy") -> nov-2021 | D20: 44526 | E20: PROVEEDORE 96505760-9 COLBUN M | G20: 0 | H20: =Banco[[#This Row],[cargos]]*-1 -> 0 | I20: 2476341 | J20: 8655849 | K20: =+Banco[[#This Row],[cargos]]+Banco[[#This Row],[Ingresos]] -> 2476341 | L20: 1.01.01 - Cuota Ordinaria | M20: =MID(Banco[[#This Row],[CtaCtbl]],FIND(" - ",Banco[[#This Row],[CtaCtbl]])+3,40) -> Cuota Ordinaria
A21: =YEAR(Banco[[#This Row],[Fecha]]) -> 2021 | B21: =PROPER(TEXT(Banco[[#This Row],[Fecha]],"MMMM")) -> Diciembre | C21: =TEXT(Banco[[#This Row],[Fecha]],"mmm-yyyy") -> dic-2021 | D21: 44531 | E21: COBRO COMISION SCOTIAWEB | G21: -18312 | H21: =Banco[[#This Row],[cargos]]*-1 -> 18312 | I21: 0 | J21: 8637537 | K21: =+Banco[[#This Row],[cargos]]+Banco[[#This Row],[Ingresos]] -> -18312 | L21: 3.03.01 - Pago Comisiones | M21: =MID(Banco[[#This Row],[CtaCtbl]],FIND(" - ",Banco[[#This Row],[CtaCtbl]])+3,40) -> Pago Comisiones
A22: =YEAR(Banco[[#This Row],[Fecha]]) -> 2021 | B22: =PROPER(TEXT(Banco[[#This Row],[Fecha]],"MMMM")) -> Diciembre | C22: =TEXT(Banco[[#This Row],[Fecha]],"mmm-yyyy") -> dic-2021 | D22: 44537 | E22: TEF 76194207-7 Estudio Juridic | G22: -113400 | H22: =Banco[[#This Row],[cargos]]*-1 -> 113400 | I22: 0 | J22: 8524137 | K22: =+Banco[[#This Row],[cargos]]+Banco[[#This Row],[Ingresos]] -> -113400 | L22: 2.01.01.01.1 - Asesoria Legal - Convenio Fijo Mensual | M22: =MID(Banco[[#This Row],[CtaCtbl]],FIND(" - ",Banco[[#This Row],[CtaCtbl]])+3,40) -> Asesoria Legal - Convenio Fijo Mensual
A23: =YEAR(Banco[[#This Row],[Fecha]]) -> 2021 | B23: =PROPER(TEXT(Banco[[#This Row],[Fecha]],"MMMM")) -> Diciembre | C23: =TEXT(Banco[[#This Row],[Fecha]],"mmm-yyyy") -> dic-2021 | D23: 44558 | E23: PROVEEDORE 96505760-9 COLBUN M | G23: 0 | H23: =Banco[[#This Row],[cargos]]*-1 -> 0 | I23: 216944 | K23: =+Banco[[#This Row],[cargos]]+Banco[[#This Row],[Ingresos]] -> 216944 | L23: 1.01.02 - Cuota Extraordinaria | M23: =MID(Banco[[#This Row],[CtaCtbl]],FIND(" - ",Banco[[#This Row],[CtaCtbl]])+3,40) -> Cuota Extraordinaria
A24: =YEAR(Banco[[#This Row],[Fecha]]) -> 2021 | B24: =PROPER(TEXT(Banco[[#This Row],[Fecha]],"MMMM")) -> Diciembre | C24: =TEXT(Banco[[#This Row],[Fecha]],"mmm-yyyy") -> dic-2021 | D24: 44558 | E24: PROVEEDORE 96505760-9 COLBUN M | G24: 0 | H24: =Banco[[#This Row],[cargos]]*-1 -> 0 | I24: 2665312 | J24: 11406393 | K24: =+Banco[[#This Row],[cargos]]+Banco[[#This Row],[Ingresos]] -> 2665312 | L24: 1.01.01 - Cuota Ordinaria | M24: =MID(Banco[[#This Row],[CtaCtbl]],FIND(" - ",Banco[[#This Row],[CtaCtbl]])+3,40) -> Cuota Ordinaria
A25: =YEAR(Banco[[#This Row],[Fecha]]) -> 2022 | B25: =PROPER(TEXT(Banco[[#This Row],[Fecha]],"MMMM")) -> Enero | C25: =TEXT(Banco[[#This Row],[Fecha]],"mmm-yyyy") -> ene-2022 | D25: 44564 | E25: COBRO COMISION SCOTIAWEB | G25: -18449 | H25: =Banco[[#This Row],[cargos]]*-1 -> 18449 | I25: 0 | J25: 11387944 | K25: =+Banco[[#This Row],[cargos]]+Banco[[#This Row],[Ingresos]] -> -18449 | L25: 3.03.01 - Pago Comisiones | M25: =MID(Banco[[#This Row],[CtaCtbl]],FIND(" - ",Banco[[#This Row],[CtaCtbl]])+3,40) -> Pago Comisiones
A26: =YEAR(Banco[[#This Row],[Fecha]]) -> 2022 | B26: =PROPER(TEXT(Banco[[#This Row],[Fecha]],"MMMM")) -> Enero | C26: =TEXT(Banco[[#This Row],[Fecha]],"mmm-yyyy") -> ene-2022 | D26: 44572 | E26: TEF 76194207-7 Estudio Juridic | G26: -121100 | H26: =Banco[[#This Row],[cargos]]*-1 -> 121100 | I26: 0 | J26: 11266844 | K26: =+Banco[[#This Row],[cargos]]+Banco[[#This Row],[Ingresos]] -> -121100 | L26: 2.01.01.01.1 - Asesoria Legal - Convenio Fijo Mensual | M26: =MID(Banco[[#This Row],[CtaCtbl]],FIND(" - ",Banco[[#This Row],[CtaCtbl]])+3,40) -> Asesoria Legal - Convenio Fijo Mensual | N26: EJ Mes Dic 2021 - Factura N° 0249
A27: 2022 | B27: Enero | C27: ene-2022 | D27: 44588 | E27: PROVEEDORE 96505760-9 COLBUN M | G27: 0 | H27: =Banco[[#This Row],[cargos]]*-1 -> 0 | I27: 109242 | J27: 2840292 | K27: =+Banco[[#This Row],[cargos]]+Banco[[#This Row],[Ingresos]] -> 109242 | L27: 1.01.02 - Cuota Extraordinaria | M27: =MID(Banco[[#This Row],[CtaCtbl]],FIND(" - ",Banco[[#This Row],[CtaCtbl]])+3,40) -> Cuota Extraordinaria
A28: 2022 | B28: Enero | C28: ene-2022 | D28: 44588 | E28: PROVEEDORE 96505760-9 COLBUN M | G28: 0 | H28: =Banco[[#This Row],[cargos]]*-1 -> 0 | I28: 2731050 | J28: 2840292 | K28: =+Banco[[#This Row],[cargos]]+Banco[[#This Row],[Ingresos]] -> 2731050 | L28: 1.01.01 - Cuota Ordinaria | M28: =MID(Banco[[#This Row],[CtaCtbl]],FIND(" - ",Banco[[#This Row],[CtaCtbl]])+3,40) -> Cuota Ordinaria
A29: =YEAR(Banco[[#This Row],[Fecha]]) -> 2022 | B29: =PROPER(TEXT(Banco[[#This Row],[Fecha]],"MMMM")) -> Enero | C29: =TEXT(Banco[[#This Row],[Fecha]],"mmm-yyyy") -> ene-2022 | D29: 44589 | E29: TEF 12379484-2 Abdel Karim Aza | G29: -34560 | H29: =Banco[[#This Row],[cargos]]*-1 -> 34560 | I29: 0 | J29: 13972576 | K29: =+Banco[[#This Row],[cargos]]+Banco[[#This Row],[Ingresos]] -> -34560 | L29: 2.01.04.01.2 - Almuerzo | M29: =MID(Banco[[#This Row],[CtaCtbl]],FIND(" - ",Banco[[#This Row],[CtaCtbl]])+3,40) -> Almuerzo
A30: =YEAR(Banco[[#This Row],[Fecha]]) -> 2022 | B30: =PROPER(TEXT(Banco[[#This Row],[Fecha]],"MMMM")) -> Enero | C30: =TEXT(Banco[[#This Row],[Fecha]],"mmm-yyyy") -> ene-2022 | D30: 44589 | E30: TEF 17412336-5 Robinson Cornej | G30: -233827 | H30: =Banco[[#This Row],[cargos]]*-1 -> 233827 | I30: 0 | J30: 13738749 | K30: =+Banco[[#This Row],[cargos]]+Banco[[#This Row],[Ingresos]] -> -233827 | L30: 2.01.03.03.1.9 - Traslado Terrestre Van/Taxi,etc | M30: =MID(Banco[[#This Row],[CtaCtbl]],FIND(" - ",Banco[[#This Row],[CtaCtbl]])+3,40) -> Traslado Terrestre Van/Taxi,etc
A31: =YEAR(Banco[[#This Row],[Fecha]]) -> 2022 | B31: =PROPER(TEXT(Banco[[#This Row],[Fecha]],"MMMM")) -> Enero | C31: =TEXT(Banco[[#This Row],[Fecha]],"mmm-yyyy") -> ene-2022 | D31: 44589 | E31: TEF 76197051-8 RED HOTELERA CH | G31: -100000 | H31: =Banco[[#This Row],[cargos]]*-1 -> 100000 | I31: 0 | J31: 14007136 | K31: =+Banco[[#This Row],[cargos]]+Banco[[#This Row],[Ingresos]] -> -100000 | L31: 2.01.04.02 - Alojamiento | M31: =MID(Banco[[#This Row],[CtaCtbl]],FIND(" - ",Banco[[#This Row],[CtaCtbl]])+3,40) -> Alojamiento
A32: =YEAR(Banco[[#This Row],[Fecha]]) -> 2022 | B32: =PROPER(TEXT(Banco[[#This Row],[Fecha]],"MMMM")) -> Enero | C32: =TEXT(Banco[[#This Row],[Fecha]],"mmm-yyyy") -> ene-2022 | D32: 44592 | E32: TEF 76016422-4 Hotel Avellano | G32: -65450 | H32: =Banco[[#This Row],[cargos]]*-1 -> 65450 | I32: 0 | J32: 13673299 | K32: =+Banco[[#This Row],[cargos]]+Banco[[#This Row],[Ingresos]] -> -65450 | L32: 2.01.04.02 - Alojamiento | M32: =MID(Banco[[#This Row],[CtaCtbl]],FIND(" - ",Banco[[#This Row],[CtaCtbl]])+3,40) -> Alojamiento
A33: =YEAR(Banco[[#This Row],[Fecha]]) -> 2022 | B33: =PROPER(TEXT(Banco[[#This Row],[Fecha]],"MMMM")) -> Febrero | C33: =TEXT(Banco[[#This Row],[Fecha]],"mmm-yyyy") -> feb-2022 | D33: 44593 | E33: COBRO COMISION SCOTIAWEB | G33: -18576 | H33: =Banco[[#This Row],[cargos]]*-1 -> 18576 | I33: 0 | J33: 13654723 | K33: =+Banco[[#This Row],[cargos]]+Banco[[#This Row],[Ingresos]] -> -18576 | L33: 3.03.01 - Pago Comisiones | M33: =MID(Banco[[#This Row],[CtaCtbl]],FIND(" - ",Banco[[#This Row],[CtaCtbl]])+3,40) -> Pago Comisiones
A34: =YEAR(Banco[[#This Row],[Fecha]]) -> 2022 | B34: =PROPER(TEXT(Banco[[#This Row],[Fecha]],"MMMM")) -> Febrero | C34: =TEXT(Banco[[#This Row],[Fecha]],"mmm-yyyy") -> feb-2022 | D34: 44602 | E34: TEF 12379484-2 Abdel Karim Aza | G34: -119949 | H34: =Banco[[#This Row],[cargos]]*-1 -> 119949 | I34: 0 | J34: 13446574 | K34: =+Banco[[#This Row],[cargos]]+Banco[[#This Row],[Ingresos]] -> -119949 | L34: 2.01.03.03.1.9 - Traslado Terrestre Van/Taxi,etc | M34: =MID(Banco[[#This Row],[CtaCtbl]],FIND(" - ",Banco[[#This Row],[CtaCtbl]])+3,40) -> Traslado Terrestre Van/Taxi,etc
A35: =YEAR(Banco[[#This Row],[Fecha]]) -> 2022 | B35: =PROPER(TEXT(Banco[[#This Row],[Fecha]],"MMMM")) -> Febrero | C35: =TEXT(Banco[[#This Row],[Fecha]],"mmm-yyyy") -> feb-2022 | D35: 44602 | E35: TEF 76194207-7 Estudio Juridic | G35: -88200 | H35: =Banco[[#This Row],[cargos]]*-1 -> 88200 | I35: 0 | J35: 13566523 | K35: =+Banco[[#This Row],[cargos]]+Banco[[#This Row],[Ingresos]] -> -88200 | L35: 2.01.01.01.1 - Asesoria Legal - Convenio Fijo Mensual | M35: =MID(Banco[[#This Row],[CtaCtbl]],FIND(" - ",Banco[[#This Row],[CtaCtbl]])+3,40) -> Asesoria Legal - Convenio Fijo Mensual | N35: EJ Mes Ene 2022 - Factura N°0250
A36: =YEAR(Banco[[#This Row],[Fecha]]) -> 2022 | B36: =PROPER(TEXT(Banco[[#This Row],[Fecha]],"MMMM")) -> Febrero | C36: =TEXT(Banco[[#This Row],[Fecha]],"mmm-yyyy") -> feb-2022 | D36: 44617 | E36: PROVEEDORE 96505760-9 COLBUN M | G36: 0 | H36: =Banco[[#This Row],[cargos]]*-1 -> 0 | I36: 282712 | K36: =+Banco[[#This Row],[cargos]]+Banco[[#This Row],[Ingresos]] -> 282712 | L36: 1.01.02 - Cuota Extraordinaria | M36: =MID(Banco[[#This Row],[CtaCtbl]],FIND(" - ",Banco[[#This Row],[CtaCtbl]])+3,40) -> Cuota Extraordinaria
A37: =YEAR(Banco[[#This Row],[Fecha]]) -> 2022 | B37: =PROPER(TEXT(Banco[[#This Row],[Fecha]],"MMMM")) -> Febrero | C37: =TEXT(Banco[[#This Row],[Fecha]],"mmm-yyyy") -> feb-2022 | D37: 44617 | E37: PROVEEDORE 96505760-9 COLBUN M | G37: 0 | H37: =Banco[[#This Row],[cargos]]*-1 -> 0 | I37: 2917450 | J37: 16646736 | K37: =+Banco[[#This Row],[cargos]]+Banco[[#This Row],[Ingresos]] -> 2917450 | L37: 1.01.01 - Cuota Ordinaria | M37: =MID(Banco[[#This Row],[CtaCtbl]],FIND(" - ",Banco[[#This Row],[CtaCtbl]])+3,40) -> Cuota Ordinaria
A38: =YEAR(Banco[[#This Row],[Fecha]]) -> 2022 | B38: =PROPER(TEXT(Banco[[#This Row],[Fecha]],"MMMM")) -> Marzo | C38: =TEXT(Banco[[#This Row],[Fecha]],"mmm-yyyy") -> mar-2022 | D38: 44621 | E38: COBRO COMISION SCOTIAWEB | G38: -18773 | H38: =Banco[[#This Row],[cargos]]*-1 -> 18773 | I38: 0 | J38: 16627963 | K38: =+Banco[[#This Row],[cargos]]+Banco[[#This Row],[Ingresos]] -> -18773 | L38: 3.03.01 - Pago Comisiones | M38: =MID(Banco[[#This Row],[CtaCtbl]],FIND(" - ",Banco[[#This Row],[CtaCtbl]])+3,40) -> Pago Comisiones
A39: =YEAR(Banco[[#This Row],[Fecha]]) -> 2022 | B39: =PROPER(TEXT(Banco[[#This Row],[Fecha]],"MMMM")) -> Marzo | C39: =TEXT(Banco[[#This Row],[Fecha]],"mmm-yyyy") -> mar-2022 | D39: 44628 | E39: TEF 12379484-2 Abdel Karim Aza | G39: -2300 | H39: =Banco[[#This Row],[cargos]]*-1 -> 2300 | I39: 0 | J39: 16609847 | K39: =+Banco[[#This Row],[cargos]]+Banco[[#This Row],[Ingresos]] -> -2300 | L39: 2.01.03.03.1.9 - Traslado Terrestre Van/Taxi,etc | M39: =MID(Banco[[#This Row],[CtaCtbl]],FIND(" - ",Banco[[#This Row],[CtaCtbl]])+3,40) -> Traslado Terrestre Van/Taxi,etc
A40: =YEAR(Banco[[#This Row],[Fecha]]) -> 2022 | B40: =PROPER(TEXT(Banco[[#This Row],[Fecha]],"MMMM")) -> Marzo | C40: =TEXT(Banco[[#This Row],[Fecha]],"mmm-yyyy") -> mar-2022 | D40: 44628 | E40: TEF 13790679-1 Paula Paredes | G40: -15816 | H40: =Banco[[#This Row],[cargos]]*-1 -> 15816 | I40: 0 | J40: 16612147 | K40: =+Banco[[#This Row],[cargos]]+Banco[[#This Row],[Ingresos]] -> -15816 | L40: 2.02.08 - Aporte Extraordinario al Socio | M40: =MID(Banco[[#This Row],[CtaCtbl]],FIND(" - ",Banco[[#This Row],[CtaCtbl]])+3,40) -> Aporte Extraordinario al Socio
A41: =YEAR(Banco[[#This Row],[Fecha]]) -> 2022 | B41: =PROPER(TEXT(Banco[[#This Row],[Fecha]],"MMMM")) -> Marzo | C41: =TEXT(Banco[[#This Row],[Fecha]],"mmm-yyyy") -> mar-2022 | D41: 44628 | E41: TEF 76194207-7 Estudio Juridic | G41: -107800 | H41: =Banco[[#This Row],[cargos]]*-1 -> 107800 | I41: 0 | J41: 16502047 | K41: =+Banco[[#This Row],[cargos]]+Banco[[#This Row],[Ingresos]] -> -107800 | L41: 2.01.01.01.1 - Asesoria Legal - Convenio Fijo Mensual | M41: =MID(Banco[[#This Row],[CtaCtbl]],FIND(" - ",Banco[[#This Row],[CtaCtbl]])+3,40) -> Asesoria Legal - Convenio Fijo Mensual | N41: EJ Mes Feb 2022 - Factura N°0254
A42: =YEAR(Banco[[#This Row],[Fecha]]) -> 2022 | B42: =PROPER(TEXT(Banco[[#This Row],[Fecha]],"MMMM")) -> Marzo | C42: =TEXT(Banco[[#This Row],[Fecha]],"mmm-yyyy") -> mar-2022 | D42: 44631 | E42: TEF 76194207-7 Estudio Juridic | G42: -2000000 | H42: =Banco[[#This Row],[cargos]]*-1 -> 2000000 | I42: 0 | J42: 14502047 | K42: =+Banco[[#This Row],[cargos]]+Banco[[#This Row],[Ingresos]] -> -2000000 | L42: 2.01.01.01.2 - Asesoria Legal - Proyectos Negociacion | M42: =MID(Banco[[#This Row],[CtaCtbl]],FIND(" - ",Banco[[#This Row],[CtaCtbl]])+3,40) -> Asesoria Legal - Proyectos Negociacion | N42: EJ Negociacion Colectiva 1er Pago 2022 - Factura N°0251
A43: =YEAR(Banco[[#This Row],[Fecha]]) -> 2022 | B43: =PROPER(TEXT(Banco[[#This Row],[Fecha]],"MMMM")) -> Marzo | C43: =TEXT(Banco[[#This Row],[Fecha]],"mmm-yyyy") -> mar-2022 | D43: 44645 | E43: PROVEEDORE 96505760-9 COLBUN M | G43: 0 | H43: =Banco[[#This Row],[cargos]]*-1 -> 0 | I43: 523512 | K43: =+Banco[[#This Row],[cargos]]+Banco[[#This Row],[Ingresos]] -> 523512 | L43: 1.01.02 - Cuota Extraordinaria | M43: =MID(Banco[[#This Row],[CtaCtbl]],FIND(" - ",Banco[[#This Row],[CtaCtbl]])+3,40) -> Cuota Extraordinaria
A44: =YEAR(Banco[[#This Row],[Fecha]]) -> 2022 | B44: =PROPER(TEXT(Banco[[#This Row],[Fecha]],"MMMM")) -> Marzo | C44: =TEXT(Banco[[#This Row],[Fecha]],"mmm-yyyy") -> mar-2022 | D44: 44645 | E44: PROVEEDORE 96505760-9 COLBUN M | G44: 0 | H44: =Banco[[#This Row],[cargos]]*-1 -> 0 | I44: 3410760 | J44: 18436319 | K44: =+Banco[[#This Row],[cargos]]+Banco[[#This Row],[Ingresos]] -> 3410760 | L44: 1.01.01 - Cuota Ordinaria | M44: =MID(Banco[[#This Row],[CtaCtbl]],FIND(" - ",Banco[[#This Row],[CtaCtbl]])+3,40) -> Cuota Ordinaria
A45: =YEAR(Banco[[#This Row],[Fecha]]) -> 2022 | B45: =PROPER(TEXT(Banco[[#This Row],[Fecha]],"MMMM")) -> Abril | C45: =TEXT(Banco[[#This Row],[Fecha]],"mmm-yyyy") -> abr-2022 | D45: 44652 | E45: COBRO COMISION SCOTIAWEB | G45: -18879 | H45: =Banco[[#This Row],[cargos]]*-1 -> 18879 | I45: 0 | J45: 18417440 | K45: =+Banco[[#This Row],[cargos]]+Banco[[#This Row],[Ingresos]] -> -18879 | L45: 3.03.01 - Pago Comisiones | M45: =MID(Banco[[#This Row],[CtaCtbl]],FIND(" - ",Banco[[#This Row],[CtaCtbl]])+3,40) -> Pago Comisiones
A46: =YEAR(Banco[[#This Row],[Fecha]]) -> 2022 | B46: =PROPER(TEXT(Banco[[#This Row],[Fecha]],"MMMM")) -> Abril | C46: =TEXT(Banco[[#This Row],[Fecha]],"mmm-yyyy") -> abr-2022 | D46: 44655 | E46: TEF 76330590-2 TRANSPORTES JOS | G46: -380572 | H46: =Banco[[#This Row],[cargos]]*-1 -> 380572 | I46: 0 | J46: 18036868 | K46: =+Banco[[#This Row],[cargos]]+Banco[[#This Row],[Ingresos]] -> -380572 | L46: 2.01.03.03.1.7 - Taxi, Uber o Similar | M46: =MID(Banco[[#This Row],[CtaCtbl]],FIND(" - ",Banco[[#This Row],[CtaCtbl]])+3,40) -> Taxi, Uber o Similar
A47: =YEAR(Banco[[#This Row],[Fecha]]) -> 2022 | B47: =PROPER(TEXT(Banco[[#This Row],[Fecha]],"MMMM")) -> Abril | C47: =TEXT(Banco[[#This Row],[Fecha]],"mmm-yyyy") -> abr-2022 | D47: 44677 | E47: PROVEEDORE 96505760-9 COLBUN M | G47: 0 | H47: =Banco[[#This Row],[cargos]]*-1 -> 0 | I47: 3442832 | J47: 21479700 | K47: =+Banco[[#This Row],[cargos]]+Banco[[#This Row],[Ingresos]] -> 3442832 | L47: 1.01.01 - Cuota Ordinaria | M47: =MID(Banco[[#This Row],[CtaCtbl]],FIND(" - ",Banco[[#This Row],[CtaCtbl]])+3,40) -> Cuota Ordinaria
A48: =YEAR(Banco[[#This Row],[Fecha]]) -> 2022 | B48: =PROPER(TEXT(Banco[[#This Row],[Fecha]],"MMMM")) -> Abril | C48: =TEXT(Banco[[#This Row],[Fecha]],"mmm-yyyy") -> abr-2022 | D48: 44677 | E48: TEF 12379484-2 Abdel Karim Aza | G48: -63463 | H48: =Banco[[#This Row],[cargos]]*-1 -> 63463 | I48: 0 | J48: 18016379 | K48: =+Banco[[#This Row],[cargos]]+Banco[[#This Row],[Ingresos]] -> -63463 | L48: 2.01.04.03 - Otros gastos varios | M48: =MID(Banco[[#This Row],[CtaCtbl]],FIND(" - ",Banco[[#This Row],[CtaCtbl]])+3,40) -> Otros gastos varios
A49: =YEAR(Banco[[#This Row],[Fecha]]) -> 2022 | B49: =PROPER(TEXT(Banco[[#This Row],[Fecha]],"MMMM")) -> Abril | C49: =TEXT(Banco[[#This Row],[Fecha]],"mmm-yyyy") -> abr-2022 | D49: 44677 | E49: TEF 12846913-3 Mitchell Zuniga | G49: -15606 | H49: =Banco[[#This Row],[cargos]]*-1 -> 15606 | I49: 0 | J49: 18242494 | K49: =+Banco[[#This Row],[cargos]]+Banco[[#This Row],[Ingresos]] -> -15606 | L49: 2.02.05 - Restitución Fondos Socios | M49: =MID(Banco[[#This Row],[CtaCtbl]],FIND(" - ",Banco[[#This Row],[CtaCtbl]])+3,40) -> Restitución Fondos Socios
A50: =YEAR(Banco[[#This Row],[Fecha]]) -> 2022 | B50: =PROPER(TEXT(Banco[[#This Row],[Fecha]],"MMMM")) -> Abril | C50: =TEXT(Banco[[#This Row],[Fecha]],"mmm-yyyy") -> abr-2022 | D50: 44677 | E50: TEF 14082906-4 Alejandra Saldi | G50: -132356 | H50: =Banco[[#This Row],[cargos]]*-1 -> 132356 | I50: 0 | J50: 17884023 | K50: =+Banco[[#This Row],[cargos]]+Banco[[#This Row],[Ingresos]] -> -132356 | L50: 2.01.04.03 - Otros gastos varios | M50: =MID(Banco[[#This Row],[CtaCtbl]],FIND(" - ",Banco[[#This Row],[CtaCtbl]])+3,40) -> Otros gastos varios
A51: =YEAR(Banco[[#This Row],[Fecha]]) -> 2022 | B51: =PROPER(TEXT(Banco[[#This Row],[Fecha]],"MMMM")) -> Abril | C51: =TEXT(Banco[[#This Row],[Fecha]],"mmm-yyyy") -> abr-2022 | D51: 44677 | E51: TEF 17412336-5 Robinson Cornej | G51: -162652 | H51: =Banco[[#This Row],[cargos]]*-1 -> 162652 | I51: 0 | J51: 18079842 | K51: =+Banco[[#This Row],[cargos]]+Banco[[#This Row],[Ingresos]] -> -162652 | L51: 2.01.04.03 - Otros gastos varios | M51: =MID(Banco[[#This Row],[CtaCtbl]],FIND(" - ",Banco[[#This Row],[CtaCtbl]])+3,40) -> Otros gastos varios
A52: =YEAR(Banco[[#This Row],[Fecha]]) -> 2022 | B52: =PROPER(TEXT(Banco[[#This Row],[Fecha]],"MMMM")) -> Abril | C52: =TEXT(Banco[[#This Row],[Fecha]],"mmm-yyyy") -> abr-2022 | D52: 44677 | E52: TEF 76194207-7 Estudio Juridic | G52: -149800 | H52: =Banco[[#This Row],[cargos]]*-1 -> 149800 | I52: 0 | J52: 21329900 | K52: =+Banco[[#This Row],[cargos]]+Banco[[#This Row],[Ingresos]] -> -149800 | L52: 2.01.01.01.1 - Asesoria Legal - Convenio Fijo Mensual | M52: =MID(Banco[[#This Row],[CtaCtbl]],FIND(" - ",Banco[[#This Row],[CtaCtbl]])+3,40) -> Asesoria Legal - Convenio Fijo Mensual | N52: 2022-03 - Mensualidad EJ - Factura N°0259
A53: =YEAR(Banco[[#This Row],[Fecha]]) -> 2022 | B53: =PROPER(TEXT(Banco[[#This Row],[Fecha]],"MMMM")) -> Abril | C53: =TEXT(Banco[[#This Row],[Fecha]],"mmm-yyyy") -> abr-2022 | D53: 44677 | E53: TEF 76194207-7 Estudio Juridic | G53: -3071800 | H53: =Banco[[#This Row],[cargos]]*-1 -> 3071800 | I53: 0 | J53: 18258100 | K53: =+Banco[[#This Row],[cargos]]+Banco[[#This Row],[Ingresos]] -> -3071800 | L53: 2.01.01.01.2 - Asesoria Legal - Proyectos Negociacion | M53: =MID(Banco[[#This Row],[CtaCtbl]],FIND(" - ",Banco[[#This Row],[CtaCtbl]])+3,40) -> Asesoria Legal - Proyectos Negociacion | N53: EJ Negociacion Colectiva 2er Pago 2022 - Factura N°0258
A54: =YEAR(Banco[[#This Row],[Fecha]]) -> 2022 | B54: =PROPER(TEXT(Banco[[#This Row],[Fecha]],"MMMM")) -> Mayo | C54: =TEXT(Banco[[#This Row],[Fecha]],"mmm-yyyy") -> may-2022 | D54: 44683 | E54: COBRO COMISION SCOTIAWEB | G54: -19169 | H54: =Banco[[#This Row],[cargos]]*-1 -> 19169 | I54: 0 | J54: 17864854 | K54: =+Banco[[#This Row],[cargos]]+Banco[[#This Row],[Ingresos]] -> -19169 | L54: 3.03.01 - Pago Comisiones | M54: =MID(Banco[[#This Row],[CtaCtbl]],FIND(" - ",Banco[[#This Row],[CtaCtbl]])+3,40) -> Pago Comisiones
A55: =YEAR(Banco[[#This Row],[Fecha]]) -> 2022 | B55: =PROPER(TEXT(Banco[[#This Row],[Fecha]],"MMMM")) -> Mayo | C55: =TEXT(Banco[[#This Row],[Fecha]],"mmm-yyyy") -> may-2022 | D55: 44707 | E55: PROVEEDORE 96505760-9 COLBUN M | G55: 0 | H55: =Banco[[#This Row],[cargos]]*-1 -> 0 | I55: 107000000 | J55: 128361614 | K55: =+Banco[[#This Row],[cargos]]+Banco[[#This Row],[Ingresos]] -> 107000000 | L55: 1.03.04 - Aporte Colbun | M55: =MID(Banco[[#This Row],[CtaCtbl]],FIND(" - ",Banco[[#This Row],[CtaCtbl]])+3,40) -> Aporte Colbun
A56: =YEAR(Banco[[#This Row],[Fecha]]) -> 2022 | B56: =PROPER(TEXT(Banco[[#This Row],[Fecha]],"MMMM")) -> Mayo | C56: =TEXT(Banco[[#This Row],[Fecha]],"mmm-yyyy") -> may-2022 | D56: 44707 | E56: PROVEEDORE 96505760-9 COLBUN M | G56: 0 | H56: =Banco[[#This Row],[cargos]]*-1 -> 0 | I56: 3496760 | K56: =+Banco[[#This Row],[cargos]]+Banco[[#This Row],[Ingresos]] -> 3496760 | L56: 1.01.01 - Cuota Ordinaria | M56: =MID(Banco[[#This Row],[CtaCtbl]],FIND(" - ",Banco[[#This Row],[CtaCtbl]])+3,40) -> Cuota Ordinaria
A57: =YEAR(Banco[[#This Row],[Fecha]]) -> 2022 | B57: =PROPER(TEXT(Banco[[#This Row],[Fecha]],"MMMM")) -> Mayo | C57: =TEXT(Banco[[#This Row],[Fecha]],"mmm-yyyy") -> may-2022 | D57: 44711 | E57: TEF 76194207-7 Estudio Juridic | G57: -149800 | H57: =Banco[[#This Row],[cargos]]*-1 -> 149800 | I57: 0 | J57: 128211814 | K57: =+Banco[[#This Row],[cargos]]+Banco[[#This Row],[Ingresos]] -> -149800 | L57: 2.01.01.01.1 - Asesoria Legal - Convenio Fijo Mensual | M57: =MID(Banco[[#This Row],[CtaCtbl]],FIND(" - ",Banco[[#This Row],[CtaCtbl]])+3,40) -> Asesoria Legal - Convenio Fijo Mensual | N57: Ej Mes Abril 2022 - Factura N°0268
A58: =YEAR(Banco[[#This Row],[Fecha]]) -> 2022 | B58: =PROPER(TEXT(Banco[[#This Row],[Fecha]],"MMMM")) -> Mayo | C58: =TEXT(Banco[[#This Row],[Fecha]],"mmm-yyyy") -> may-2022 | D58: 44711 | E58: TEF 76194207-7 Estudio Juridic | G58: -149800 | H58: =Banco[[#This Row],[cargos]]*-1 -> 149800 | I58: 0 | J58: 128062014 | K58: =+Banco[[#This Row],[cargos]]+Banco[[#This Row],[Ingresos]] -> -149800 | L58: 2.01.01.01.1 - Asesoria Legal - Convenio Fijo Mensual | M58: =MID(Banco[[#This Row],[CtaCtbl]],FIND(" - ",Banco[[#This Row],[CtaCtbl]])+3,40) -> Asesoria Legal - Convenio Fijo Mensual | N58: 2022-05 Mensualidad EJ - Factura N°0269
A59: =YEAR(Banco[[#This Row],[Fecha]]) -> 2022 | B59: =PROPER(TEXT(Banco[[#This Row],[Fecha]],"MMMM")) -> Mayo | C59: =TEXT(Banco[[#This Row],[Fecha]],"mmm-yyyy") -> may-2022 | D59: 44711 | E59: TEF 76330590-2 TRANSPORTES JOS | G59: -380572 | H59: =Banco[[#This Row],[cargos]]*-1 -> 380572 | I59: 0 | J59: 127681442 | K59: =+Banco[[#This Row],[cargos]]+Banco[[#This Row],[Ingresos]] -> -380572 | L59: 2.01.03.03.1.7 - Taxi, Uber o Similar | M59: =MID(Banco[[#This Row],[CtaCtbl]],FIND(" - ",Banco[[#This Row],[CtaCtbl]])+3,40) -> Taxi, Uber o Similar
A60: =YEAR(Banco[[#This Row],[Fecha]]) -> 2022 | B60: =PROPER(TEXT(Banco[[#This Row],[Fecha]],"MMMM")) -> Junio | C60: =TEXT(Banco[[#This Row],[Fecha]],"mmm-yyyy") -> jun-2022 | D60: 44713 | E60: COBRO COMISION SCOTIAWEB | G60: -19453 | H60: =Banco[[#This Row],[cargos]]*-1 -> 19453 | I60: 0 | J60: 127661989 | K60: =+Banco[[#This Row],[cargos]]+Banco[[#This Row],[Ingresos]] -> -19453 | L60: 3.03.01 - Pago Comisiones | M60: =MID(Banco[[#This Row],[CtaCtbl]],FIND(" - ",Banco[[#This Row],[CtaCtbl]])+3,40) -> Pago Comisiones
A61: =YEAR(Banco[[#This Row],[Fecha]]) -> 2022 | B61: =PROPER(TEXT(Banco[[#This Row],[Fecha]],"MMMM")) -> Junio | C61: =TEXT(Banco[[#This Row],[Fecha]],"mmm-yyyy") -> jun-2022 | D61: 44726 | E61: PROVEEDORES 20220614153633263 | G61: -106000000 | H61: =Banco[[#This Row],[cargos]]*-1 -> 106000000 | I61: 0 | J61: 21661989 | K61: =+Banco[[#This Row],[cargos]]+Banco[[#This Row],[Ingresos]] -> -106000000 | L61: 2.02.06 - Pago Bonos a Socios | M61: =MID(Banco[[#This Row],[CtaCtbl]],FIND(" - ",Banco[[#This Row],[CtaCtbl]])+3,40) -> Pago Bonos a Socios
A62: =YEAR(Banco[[#This Row],[Fecha]]) -> 2022 | B62: =PROPER(TEXT(Banco[[#This Row],[Fecha]],"MMMM")) -> Junio | C62: =TEXT(Banco[[#This Row],[Fecha]],"mmm-yyyy") -> jun-2022 | D62: 44727 | E62: RECH PROVEEDO20220614153633263 | G62: 0 | H62: =Banco[[#This Row],[cargos]]*-1 -> 0 | I62: 500000 | J62: 22161989 | K62: =+Banco[[#This Row],[cargos]]+Banco[[#This Row],[Ingresos]] -> 500000 | L62: 1.03.03 - Otros Aportes | M62: =MID(Banco[[#This Row],[CtaCtbl]],FIND(" - ",Banco[[#This Row],[CtaCtbl]])+3,40) -> Otros Aportes
A63: =YEAR(Banco[[#This Row],[Fecha]]) -> 2022 | B63: =PROPER(TEXT(Banco[[#This Row],[Fecha]],"MMMM")) -> Junio | C63: =TEXT(Banco[[#This Row],[Fecha]],"mmm-yyyy") -> jun-2022 | D63: 44727 | E63: RECH PROVEEDO20220614153633263 | G63: 0 | H63: =Banco[[#This Row],[cargos]]*-1 -> 0 | I63: 500000 | J63: 22661989 | K63: =+Banco[[#This Row],[cargos]]+Banco[[#This Row],[Ingresos]] -> 500000 | L63: 1.03.03 - Otros Aportes | M63: =MID(Banco[[#This Row],[CtaCtbl]],FIND(" - ",Banco[[#This Row],[CtaCtbl]])+3,40) -> Otros Aportes
A64: =YEAR(Banco[[#This Row],[Fecha]]) -> 2022 | B64: =PROPER(TEXT(Banco[[#This Row],[Fecha]],"MMMM")) -> Junio | C64: =TEXT(Banco[[#This Row],[Fecha]],"mmm-yyyy") -> jun-2022 | D64: 44727 | E64: RECH PROVEEDO20220614153633263 | G64: 0 | H64: =Banco[[#This Row],[cargos]]*-1 -> 0 | I64: 500000 | J64: 23161989 | K64: =+Banco[[#This Row],[cargos]]+Banco[[#This Row],[Ingresos]] -> 500000 | L64: 1.03.03 - Otros Aportes | M64: =MID(Banco[[#This Row],[CtaCtbl]],FIND(" - ",Banco[[#This Row],[CtaCtbl]])+3,40) -> Otros Aportes
A65: =YEAR(Banco[[#This Row],[Fecha]]) -> 2022 | B65: =PROPER(TEXT(Banco[[#This Row],[Fecha]],"MMMM")) -> Junio | C65: =TEXT(Banco[[#This Row],[Fecha]],"mmm-yyyy") -> jun-2022 | D65: 44727 | E65: RECH PROVEEDO20220614153633263 | G65: 0 | H65: =Banco[[#This Row],[cargos]]*-1 -> 0 | I65: 500000 | J65: 23661989 | K65: =+Banco[[#This Row],[cargos]]+Banco[[#This Row],[Ingresos]] -> 500000 | L65: 1.03.03 - Otros Aportes | M65: =MID(Banco[[#This Row],[CtaCtbl]],FIND(" - ",Banco[[#This Row],[CtaCtbl]])+3,40) -> Otros Aportes
A66: =YEAR(Banco[[#This Row],[Fecha]]) -> 2022 | B66: =PROPER(TEXT(Banco[[#This Row],[Fecha]],"MMMM")) -> Junio | C66: =TEXT(Banco[[#This Row],[Fecha]],"mmm-yyyy") -> jun-2022 | D66: 44727 | E66: RECH PROVEEDO20220614153633263 | G66: 0 | H66: =Banco[[#This Row],[cargos]]*-1 -> 0 | I66: 500000 | J66: 24161989 | K66: =+Banco[[#This Row],[cargos]]+Banco[[#This Row],[Ingresos]] -> 500000 | L66: 1.03.03 - Otros Aportes | M66: =MID(Banco[[#This Row],[CtaCtbl]],FIND(" - ",Banco[[#This Row],[CtaCtbl]])+3,40) -> Otros Aportes
A67: =YEAR(Banco[[#This Row],[Fecha]]) -> 2022 | B67: =PROPER(TEXT(Banco[[#This Row],[Fecha]],"MMMM")) -> Junio | C67: =TEXT(Banco[[#This Row],[Fecha]],"mmm-yyyy") -> jun-2022 | D67: 44727 | E67: RECH PROVEEDO20220614153633263 | G67: 0 | H67: =Banco[[#This Row],[cargos]]*-1 -> 0 | I67: 500000 | J67: 24661989 | K67: =+Banco[[#This Row],[cargos]]+Banco[[#This Row],[Ingresos]] -> 500000 | L67: 1.03.03 - Otros Aportes | M67: =MID(Banco[[#This Row],[CtaCtbl]],FIND(" - ",Banco[[#This Row],[CtaCtbl]])+3,40) -> Otros Aportes
A68: =YEAR(Banco[[#This Row],[Fecha]]) -> 2022 | B68: =PROPER(TEXT(Banco[[#This Row],[Fecha]],"MMMM")) -> Junio | C68: =TEXT(Banco[[#This Row],[Fecha]],"mmm-yyyy") -> jun-2022 | D68: 44735 | E68: TEF 16094319-K VICTOR ANDRES N | G68: 0 | H68: =Banco[[#This Row],[cargos]]*-1 -> 0 | I68: 82487 | J68: 24744476 | K68: =+Banco[[#This Row],[cargos]]+Banco[[#This Row],[Ingresos]] -> 82487 | L68: 1.01.02 - Cuota Extraordinaria | M68: =MID(Banco[[#This Row],[CtaCtbl]],FIND(" - ",Banco[[#This Row],[CtaCtbl]])+3,40) -> Cuota Extraordinaria | N68: Pago Multas o Cuotas no cobradas
A69: =YEAR(Banco[[#This Row],[Fecha]]) -> 2022 | B69: =PROPER(TEXT(Banco[[#This Row],[Fecha]],"MMMM")) -> Junio | C69: =TEXT(Banco[[#This Row],[Fecha]],"mmm-yyyy") -> jun-2022 | D69: 44736 | E69: PROVEEDORE 96505760-9 COLBUN M | G69: 0 | H69: =Banco[[#This Row],[cargos]]*-1 -> 0 | I69: 3507116 | J69: 28251592 | K69: =+Banco[[#This Row],[cargos]]+Banco[[#This Row],[Ingresos]] -> 3507116 | L69: 1.01.01 - Cuota Ordinaria | M69: =MID(Banco[[#This Row],[CtaCtbl]],FIND(" - ",Banco[[#This Row],[CtaCtbl]])+3,40) -> Cuota Ordinaria
A70: =YEAR(Banco[[#This Row],[Fecha]]) -> 2022 | B70: =PROPER(TEXT(Banco[[#This Row],[Fecha]],"MMMM")) -> Junio | C70: =TEXT(Banco[[#This Row],[Fecha]],"mmm-yyyy") -> jun-2022 | D70: 44736 | E70: TEF 12014424-3 Alejandro Gutie | G70: -500000 | H70: =Banco[[#This Row],[cargos]]*-1 -> 500000 | I70: 0 | J70: 26251592 | K70: =+Banco[[#This Row],[cargos]]+Banco[[#This Row],[Ingresos]] -> -500000 | L70: 2.02.06 - Pago Bonos a Socios | M70: =MID(Banco[[#This Row],[CtaCtbl]],FIND(" - ",Banco[[#This Row],[CtaCtbl]])+3,40) -> Pago Bonos a Socios
A71: =YEAR(Banco[[#This Row],[Fecha]]) -> 2022 | B71: =PROPER(TEXT(Banco[[#This Row],[Fecha]],"MMMM")) -> Junio | C71: =TEXT(Banco[[#This Row],[Fecha]],"mmm-yyyy") -> jun-2022 | D71: 44736 | E71: TEF 12566461-K Juan Vallejos | G71: -500000 | H71: =Banco[[#This Row],[cargos]]*-1 -> 500000 | I71: 0 | J71: 25751592 | K71: =+Banco[[#This Row],[cargos]]+Banco[[#This Row],[Ingresos]] -> -500000 | L71: 2.02.06 - Pago Bonos a Socios | M71: =MID(Banco[[#This Row],[CtaCtbl]],FIND(" - ",Banco[[#This Row],[CtaCtbl]])+3,40) -> Pago Bonos a Socios
A72: =YEAR(Banco[[#This Row],[Fecha]]) -> 2022 | B72: =PROPER(TEXT(Banco[[#This Row],[Fecha]],"MMMM")) -> Junio | C72: =TEXT(Banco[[#This Row],[Fecha]],"mmm-yyyy") -> jun-2022 | D72: 44736 | E72: TEF 12978344-3 Juan Godoy | G72: -500000 | H72: =Banco[[#This Row],[cargos]]*-1 -> 500000 | I72: 0 | J72: 27751592 | K72: =+Banco[[#This Row],[cargos]]+Banco[[#This Row],[Ingresos]] -> -500000 | L72: 2.02.06 - Pago Bonos a Socios | M72: =MID(Banco[[#This Row],[CtaCtbl]],FIND(" - ",Banco[[#This Row],[CtaCtbl]])+3,40) -> Pago Bonos a Socios
A73: =YEAR(Banco[[#This Row],[Fecha]]) -> 2022 | B73: =PROPER(TEXT(Banco[[#This Row],[Fecha]],"MMMM")) -> Junio | C73: =TEXT(Banco[[#This Row],[Fecha]],"mmm-yyyy") -> jun-2022 | D73: 44736 | E73: TEF 14121779-8 Mauricio Santib | G73: -500000 | H73: =Banco[[#This Row],[cargos]]*-1 -> 500000 | I73: 0 | J73: 26751592 | K73: =+Banco[[#This Row],[cargos]]+Banco[[#This Row],[Ingresos]] -> -500000 | L73: 2.02.06 - Pago Bonos a Socios | M73: =MID(Banco[[#This Row],[CtaCtbl]],FIND(" - ",Banco[[#This Row],[CtaCtbl]])+3,40) -> Pago Bonos a Socios
A74: =YEAR(Banco[[#This Row],[Fecha]]) -> 2022 | B74: =PROPER(TEXT(Banco[[#This Row],[Fecha]],"MMMM")) -> Junio | C74: =TEXT(Banco[[#This Row],[Fecha]],"mmm-yyyy") -> jun-2022 | D74: 44736 | E74: TEF 15453079-7 Gloria Hidalgo | G74: -500000 | H74: =Banco[[#This Row],[cargos]]*-1 -> 500000 | I74: 0 | J74: 27251592 | K74: =+Banco[[#This Row],[cargos]]+Banco[[#This Row],[Ingresos]] -> -500000 | L74: 2.02.06 - Pago Bonos a Socios | M74: =MID(Banco[[#This Row],[CtaCtbl]],FIND(" - ",Banco[[#This Row],[CtaCtbl]])+3,40) -> Pago Bonos a Socios
A75: =YEAR(Banco[[#This Row],[Fecha]]) -> 2022 | B75: =PROPER(TEXT(Banco[[#This Row],[Fecha]],"MMMM")) -> Junio | C75: =TEXT(Banco[[#This Row],[Fecha]],"mmm-yyyy") -> jun-2022 | D75: 44740 | E75: TEF 15954691-8 Felipe Puente | G75: -500000 | H75: =Banco[[#This Row],[cargos]]*-1 -> 500000 | I75: 0 | J75: 24751592 | K75: =+Banco[[#This Row],[cargos]]+Banco[[#This Row],[Ingresos]] -> -500000 | L75: 2.02.06 - Pago Bonos a Socios | M75: =MID(Banco[[#This Row],[CtaCtbl]],FIND(" - ",Banco[[#This Row],[CtaCtbl]])+3,40) -> Pago Bonos a Socios
A76: =YEAR(Banco[[#This Row],[Fecha]]) -> 2022 | B76: =PROPER(TEXT(Banco[[#This Row],[Fecha]],"MMMM")) -> Junio | C76: =TEXT(Banco[[#This Row],[Fecha]],"mmm-yyyy") -> jun-2022 | D76: 44740 | E76: TEF 16398217-K Elias Dominguez | G76: -500000 | H76: =Banco[[#This Row],[cargos]]*-1 -> 500000 | I76: 0 | J76: 25251592 | K76: =+Banco[[#This Row],[cargos]]+Banco[[#This Row],[Ingresos]] -> -500000 | L76: 2.02.06 - Pago Bonos a Socios | M76: =MID(Banco[[#This Row],[CtaCtbl]],FIND(" - ",Banco[[#This Row],[CtaCtbl]])+3,40) -> Pago Bonos a Socios
A77: =YEAR(Banco[[#This Row],[Fecha]]) -> 2022 | B77: =PROPER(TEXT(Banco[[#This Row],[Fecha]],"MMMM")) -> Julio | C77: =TEXT(Banco[[#This Row],[Fecha]],"mmm-yyyy") -> jul-2022 | D77: 44743 | E77: COBRO COMISION SCOTIAWEB | G77: -19695 | H77: =Banco[[#This Row],[cargos]]*-1 -> 19695 | I77: 0 | J77: 24731897 | K77: =+Banco[[#This Row],[cargos]]+Banco[[#This Row],[Ingresos]] -> -19695 | L77: 3.03.01 - Pago Comisiones | M77: =MID(Banco[[#This Row],[CtaCtbl]],FIND(" - ",Banco[[#This Row],[CtaCtbl]])+3,40) -> Pago Comisiones
A78: =YEAR(Banco[[#This Row],[Fecha]]) -> 2022 | B78: =PROPER(TEXT(Banco[[#This Row],[Fecha]],"MMMM")) -> Julio | C78: =TEXT(Banco[[#This Row],[Fecha]],"mmm-yyyy") -> jul-2022 | D78: 44769 | E78: PROVEEDORE 96505760-9 COLBUN M | G78: 0 | H78: =Banco[[#This Row],[cargos]]*-1 -> 0 | I78: 3592435 | J78: 28324332 | K78: =+Banco[[#This Row],[cargos]]+Banco[[#This Row],[Ingresos]] -> 3592435 | L78: 1.01.01 - Cuota Ordinaria | M78: =MID(Banco[[#This Row],[CtaCtbl]],FIND(" - ",Banco[[#This Row],[CtaCtbl]])+3,40) -> Cuota Ordinaria
A79: =YEAR(Banco[[#This Row],[Fecha]]) -> 2022 | B79: =PROPER(TEXT(Banco[[#This Row],[Fecha]],"MMMM")) -> Agosto | C79: =TEXT(Banco[[#This Row],[Fecha]],"mmm-yyyy") -> ago-2022 | D79: 44774 | E79: COBRO COMISION SCOTIAWEB | G79: -19888 | H79: =Banco[[#This Row],[cargos]]*-1 -> 19888 | I79: 0 | J79: 28304444 | K79: =+Banco[[#This Row],[cargos]]+Banco[[#This Row],[Ingresos]] -> -19888 | L79: 3.03.01 - Pago Comisiones | M79: =MID(Banco[[#This Row],[CtaCtbl]],FIND(" - ",Banco[[#This Row],[CtaCtbl]])+3,40) -> Pago Comisiones
A80: =YEAR(Banco[[#This Row],[Fecha]]) -> 2022 | B80: =PROPER(TEXT(Banco[[#This Row],[Fecha]],"MMMM")) -> Agosto | C80: =TEXT(Banco[[#This Row],[Fecha]],"mmm-yyyy") -> ago-2022 | D80: 44782 | E80: TEF 76194207-7 Estudio Juridic | G80: -149800 | H80: =Banco[[#This Row],[cargos]]*-1 -> 149800 | I80: 0 | J80: 28154644 | K80: =+Banco[[#This Row],[cargos]]+Banco[[#This Row],[Ingresos]] -> -149800 | L80: 2.01.01.01.1 - Asesoria Legal - Convenio Fijo Mensual | M80: =MID(Banco[[#This Row],[CtaCtbl]],FIND(" - ",Banco[[#This Row],[CtaCtbl]])+3,40) -> Asesoria Legal - Convenio Fijo Mensual | N80: 202-06 Mensualidad EJ - Factura N°0299
A81: =YEAR(Banco[[#This Row],[Fecha]]) -> 2022 | B81: =PROPER(TEXT(Banco[[#This Row],[Fecha]],"MMMM")) -> Agosto | C81: =TEXT(Banco[[#This Row],[Fecha]],"mmm-yyyy") -> ago-2022 | D81: 44783 | E81: TEF 12379484-2 Abdel Karim Aza | G81: -61230 | H81: =Banco[[#This Row],[cargos]]*-1 -> 61230 | I81: 0 | J81: 28093414 | K81: =+Banco[[#This Row],[cargos]]+Banco[[#This Row],[Ingresos]] -> -61230 | L81: 2.01.04.03 - Otros gastos varios | M81: =MID(Banco[[#This Row],[CtaCtbl]],FIND(" - ",Banco[[#This Row],[CtaCtbl]])+3,40) -> Otros gastos varios
A82: =YEAR(Banco[[#This Row],[Fecha]]) -> 2022 | B82: =PROPER(TEXT(Banco[[#This Row],[Fecha]],"MMMM")) -> Agosto | C82: =TEXT(Banco[[#This Row],[Fecha]],"mmm-yyyy") -> ago-2022 | D82: 44784 | E82: TEF 76194207-7 Estudio Juridic | G82: -149800 | H82: =Banco[[#This Row],[cargos]]*-1 -> 149800 | I82: 0 | J82: 27943614 | K82: =+Banco[[#This Row],[cargos]]+Banco[[#This Row],[Ingresos]] -> -149800 | L82: 2.01.01.01.1 - Asesoria Legal - Convenio Fijo Mensual | M82: =MID(Banco[[#This Row],[CtaCtbl]],FIND(" - ",Banco[[#This Row],[CtaCtbl]])+3,40) -> Asesoria Legal - Convenio Fijo Mensual | N82: EJ Mes Jul2022 - Factura N°300
A83: =YEAR(Banco[[#This Row],[Fecha]]) -> 2022 | B83: =PROPER(TEXT(Banco[[#This Row],[Fecha]],"MMMM")) -> Agosto | C83: =TEXT(Banco[[#This Row],[Fecha]],"mmm-yyyy") -> ago-2022 | D83: 44784 | E83: TEF 76194207-7 Estudio Juridic | G83: -149800 | H83: =Banco[[#This Row],[cargos]]*-1 -> 149800 | I83: 0 | J83: 27793814 | K83: =+Banco[[#This Row],[cargos]]+Banco[[#This Row],[Ingresos]] -> -149800 | L83: 2.01.01.01.1 - Asesoria Legal - Convenio Fijo Mensual | M83: =MID(Banco[[#This Row],[CtaCtbl]],FIND(" - ",Banco[[#This Row],[CtaCtbl]])+3,40) -> Asesoria Legal - Convenio Fijo Mensual | N83: EJ Mes 2022-08- Factura N°0301
A84: =YEAR(Banco[[#This Row],[Fecha]]) -> 2022 | B84: =PROPER(TEXT(Banco[[#This Row],[Fecha]],"MMMM")) -> Agosto | C84: =TEXT(Banco[[#This Row],[Fecha]],"mmm-yyyy") -> ago-2022 | D84: 44799 | E84: PROVEEDORE 96505760-9 COLBUN M | G84: 0 | H84: =Banco[[#This Row],[cargos]]*-1 -> 0 | I84: 3603534 | J84: 31397348 | K84: =+Banco[[#This Row],[cargos]]+Banco[[#This Row],[Ingresos]] -> 3603534 | L84: 1.01.01 - Cuota Ordinaria | M84: =MID(Banco[[#This Row],[CtaCtbl]],FIND(" - ",Banco[[#This Row],[CtaCtbl]])+3,40) -> Cuota Ordinaria
A85: =YEAR(Banco[[#This Row],[Fecha]]) -> 2022 | B85: =PROPER(TEXT(Banco[[#This Row],[Fecha]],"MMMM")) -> Septiembre | C85: =TEXT(Banco[[#This Row],[Fecha]],"mmm-yyyy") -> sept-2022 | D85: 44805 | E85: COBRO COMISION SCOTIAWEB | G85: -20142 | H85: =Banco[[#This Row],[cargos]]*-1 -> 20142 | I85: 0 | J85: 31377206 | K85: =+Banco[[#This Row],[cargos]]+Banco[[#This Row],[Ingresos]] -> -20142 | L85: 3.03.01 - Pago Comisiones | M85: =MID(Banco[[#This Row],[CtaCtbl]],FIND(" - ",Banco[[#This Row],[CtaCtbl]])+3,40) -> Pago Comisiones
A86: =YEAR(Banco[[#This Row],[Fecha]]) -> 2022 | B86: =PROPER(TEXT(Banco[[#This Row],[Fecha]],"MMMM")) -> Septiembre | C86: =TEXT(Banco[[#This Row],[Fecha]],"mmm-yyyy") -> sept-2022 | D86: 44826 | E86: TEF 76405371-0 Green Glass SPA | G86: -211701 | H86: =Banco[[#This Row],[cargos]]*-1 -> 211701 | I86: 0 | J86: 31165505 | K86: =+Banco[[#This Row],[cargos]]+Banco[[#This Row],[Ingresos]] -> -211701 | L86: 2.02.10.1 - Regalo Corportivo (Aniversario) | M86: =MID(Banco[[#This Row],[CtaCtbl]],FIND(" - ",Banco[[#This Row],[CtaCtbl]])+3,40) -> Regalo Corportivo (Aniversario) | N86: Comprobante de Pago
A87: =YEAR(Banco[[#This Row],[Fecha]]) -> 2022 | B87: =PROPER(TEXT(Banco[[#This Row],[Fecha]],"MMMM")) -> Septiembre | C87: =TEXT(Banco[[#This Row],[Fecha]],"mmm-yyyy") -> sept-2022 | D87: 44827 | E87: TEF 76405371-0 Green Glass SPA | G87: -5000000 | H87: =Banco[[#This Row],[cargos]]*-1 -> 5000000 | I87: 0 | J87: 26165505 | K87: =+Banco[[#This Row],[cargos]]+Banco[[#This Row],[Ingresos]] -> -5000000 | L87: 2.02.10.1 - Regalo Corportivo (Aniversario) | M87: =MID(Banco[[#This Row],[CtaCtbl]],FIND(" - ",Banco[[#This Row],[CtaCtbl]])+3,40) -> Regalo Corportivo (Aniversario) | N87: Comprobante Transferencia
A88: =YEAR(Banco[[#This Row],[Fecha]]) -> 2022 | B88: =PROPER(TEXT(Banco[[#This Row],[Fecha]],"MMMM")) -> Septiembre | C88: =TEXT(Banco[[#This Row],[Fecha]],"mmm-yyyy") -> sept-2022 | D88: 44830 | E88: PROVEEDORE 96505760-9 COLBUN M | G88: 0 | H88: =Banco[[#This Row],[cargos]]*-1 -> 0 | I88: 3648477 | J88: 29813982 | K88: =+Banco[[#This Row],[cargos]]+Banco[[#This Row],[Ingresos]] -> 3648477 | L88: 1.01.01 - Cuota Ordinaria | M88: =MID(Banco[[#This Row],[CtaCtbl]],FIND(" - ",Banco[[#This Row],[CtaCtbl]])+3,40) -> Cuota Ordinaria
A89: =YEAR(Banco[[#This Row],[Fecha]]) -> 2022 | B89: =PROPER(TEXT(Banco[[#This Row],[Fecha]],"MMMM")) -> Septiembre | C89: =TEXT(Banco[[#This Row],[Fecha]],"mmm-yyyy") -> sept-2022 | D89: 44831 | E89: TEF 76405371-0 Green Glass SPA | G89: -164000 | H89: =Banco[[#This Row],[cargos]]*-1 -> 164000 | I89: 0 | J89: 29649982 | K89: =+Banco[[#This Row],[cargos]]+Banco[[#This Row],[Ingresos]] -> -164000 | L89: 2.02.10.1 - Regalo Corportivo (Aniversario) | M89: =MID(Banco[[#This Row],[CtaCtbl]],FIND(" - ",Banco[[#This Row],[CtaCtbl]])+3,40) -> Regalo Corportivo (Aniversario) | N89: Tranferencia
A90: =YEAR(Banco[[#This Row],[Fecha]]) -> 2022 | B90: =PROPER(TEXT(Banco[[#This Row],[Fecha]],"MMMM")) -> Octubre | C90: =TEXT(Banco[[#This Row],[Fecha]],"mmm-yyyy") -> oct-2022 | D90: 44837 | E90: COBRO COMISION SCOTIAWEB | G90: -20409 | H90: =Banco[[#This Row],[cargos]]*-1 -> 20409 | I90: 0 | J90: 29629573 | K90: =+Banco[[#This Row],[cargos]]+Banco[[#This Row],[Ingresos]] -> -20409 | L90: 3.03.01 - Pago Comisiones | M90: =MID(Banco[[#This Row],[CtaCtbl]],FIND(" - ",Banco[[#This Row],[CtaCtbl]])+3,40) -> Pago Comisiones
A91: =YEAR(Banco[[#This Row],[Fecha]]) -> 2022 | B91: =PROPER(TEXT(Banco[[#This Row],[Fecha]],"MMMM")) -> Octubre | C91: =TEXT(Banco[[#This Row],[Fecha]],"mmm-yyyy") -> oct-2022 | D91: 44860 | E91: PROVEEDORE 96505760-9 COLBUN M | G91: 0 | H91: =Banco[[#This Row],[cargos]]*-1 -> 0 | I91: 3598400 | J91: 33227973 | K91: =+Banco[[#This Row],[cargos]]+Banco[[#This Row],[Ingresos]] -> 3598400 | L91: 1.01.01 - Cuota Ordinaria | M91: =MID(Banco[[#This Row],[CtaCtbl]],FIND(" - ",Banco[[#This Row],[CtaCtbl]])+3,40) -> Cuota Ordinaria
A92: =YEAR(Banco[[#This Row],[Fecha]]) -> 2022 | B92: =PROPER(TEXT(Banco[[#This Row],[Fecha]],"MMMM")) -> Noviembre | C92: =TEXT(Banco[[#This Row],[Fecha]],"mmm-yyyy") -> nov-2022 | D92: 44867 | E92: COBRO COMISION SCOTIAWEB | G92: -20599 | H92: =Banco[[#This Row],[cargos]]*-1 -> 20599 | I92: 0 | J92: 33207374 | K92: =+Banco[[#This Row],[cargos]]+Banco[[#This Row],[Ingresos]] -> -20599 | L92: 3.03.01 - Pago Comisiones | M92: =MID(Banco[[#This Row],[CtaCtbl]],FIND(" - ",Banco[[#This Row],[CtaCtbl]])+3,40) -> Pago Comisiones
A93: =YEAR(Banco[[#This Row],[Fecha]]) -> 2022 | B93: =PROPER(TEXT(Banco[[#This Row],[Fecha]],"MMMM")) -> Noviembre | C93: =TEXT(Banco[[#This Row],[Fecha]],"mmm-yyyy") -> nov-2022 | D93: 44872 | E93: TEF 76194207-7 Estudio Juridic | G93: -149800 | H93: =Banco[[#This Row],[cargos]]*-1 -> 149800 | I93: 0 | J93: 33057574 | K93: =+Banco[[#This Row],[cargos]]+Banco[[#This Row],[Ingresos]] -> -149800 | L93: 2.01.01.01.1 - Asesoria Legal - Convenio Fijo Mensual | M93: =MID(Banco[[#This Row],[CtaCtbl]],FIND(" - ",Banco[[#This Row],[CtaCtbl]])+3,40) -> Asesoria Legal - Convenio Fijo Mensual | N93: EJ Mes Sep2022 - Factura N°0331
A94: =YEAR(Banco[[#This Row],[Fecha]]) -> 2022 | B94: =PROPER(TEXT(Banco[[#This Row],[Fecha]],"MMMM")) -> Noviembre | C94: =TEXT(Banco[[#This Row],[Fecha]],"mmm-yyyy") -> nov-2022 | D94: 44872 | E94: TEF 76194207-7 Estudio Juridic | G94: -149800 | H94: =Banco[[#This Row],[cargos]]*-1 -> 149800 | I94: 0 | J94: 32907774 | K94: =+Banco[[#This Row],[cargos]]+Banco[[#This Row],[Ingresos]] -> -149800 | L94: 2.01.01.01.1 - Asesoria Legal - Convenio Fijo Mensual | M94: =MID(Banco[[#This Row],[CtaCtbl]],FIND(" - ",Banco[[#This Row],[CtaCtbl]])+3,40) -> Asesoria Legal - Convenio Fijo Mensual | N94: EJ Mes Oct2022 - Factura N°0331
A95: =YEAR(Banco[[#This Row],[Fecha]]) -> 2022 | B95: =PROPER(TEXT(Banco[[#This Row],[Fecha]],"MMMM")) -> Noviembre | C95: =TEXT(Banco[[#This Row],[Fecha]],"mmm-yyyy") -> nov-2022 | D95: 44872 | E95: TEF 76194207-7 Estudio Juridic | G95: -149800 | H95: =Banco[[#This Row],[cargos]]*-1 -> 149800 | I95: 0 | J95: 32757974 | K95: =+Banco[[#This Row],[cargos]]+Banco[[#This Row],[Ingresos]] -> -149800 | L95: 2.01.01.01.1 - Asesoria Legal - Convenio Fijo Mensual | M95: =MID(Banco[[#This Row],[CtaCtbl]],FIND(" - ",Banco[[#This Row],[CtaCtbl]])+3,40) -> Asesoria Legal - Convenio Fijo Mensual | N95: EJ Mes Nov2022 - Factura N°0331
A96: =YEAR(Banco[[#This Row],[Fecha]]) -> 2022 | B96: =PROPER(TEXT(Banco[[#This Row],[Fecha]],"MMMM")) -> Noviembre | C96: =TEXT(Banco[[#This Row],[Fecha]],"mmm-yyyy") -> nov-2022 | D96: 44890 | E96: PROVEEDORE 96505760-9 COLBUN M | G96: 0 | H96: =Banco[[#This Row],[cargos]]*-1 -> 0 | I96: 3620448 | J96: 36378422 | K96: =+Banco[[#This Row],[cargos]]+Banco[[#This Row],[Ingresos]] -> 3620448 | L96: 1.01.01 - Cuota Ordinaria | M96: =MID(Banco[[#This Row],[CtaCtbl]],FIND(" - ",Banco[[#This Row],[CtaCtbl]])+3,40) -> Cuota Ordinaria
A97: =YEAR(Banco[[#This Row],[Fecha]]) -> 2022 | B97: =PROPER(TEXT(Banco[[#This Row],[Fecha]],"MMMM")) -> Diciembre | C97: =TEXT(Banco[[#This Row],[Fecha]],"mmm-yyyy") -> dic-2022 | D97: 44896 | E97: COBRO COMISION SCOTIAWEB | G97: -20717 | H97: =Banco[[#This Row],[cargos]]*-1 -> 20717 | I97: 0 | J97: 36357705 | K97: =+Banco[[#This Row],[cargos]]+Banco[[#This Row],[Ingresos]] -> -20717 | L97: 3.03.01 - Pago Comisiones | M97: =MID(Banco[[#This Row],[CtaCtbl]],FIND(" - ",Banco[[#This Row],[CtaCtbl]])+3,40) -> Pago Comisiones
A98: =YEAR(Banco[[#This Row],[Fecha]]) -> 2022 | B98: =PROPER(TEXT(Banco[[#This Row],[Fecha]],"MMMM")) -> Diciembre | C98: =TEXT(Banco[[#This Row],[Fecha]],"mmm-yyyy") -> dic-2022 | D98: 44907 | E98: TEF 12379484-2 Abdel Karim Aza | G98: -16000 | H98: =Banco[[#This Row],[cargos]]*-1 -> 16000 | I98: 0 | J98: 36319535 | K98: =+Banco[[#This Row],[cargos]]+Banco[[#This Row],[Ingresos]] -> -16000 | L98: 2.01.04.03 - Otros gastos varios | M98: =MID(Banco[[#This Row],[CtaCtbl]],FIND(" - ",Banco[[#This Row],[CtaCtbl]])+3,40) -> Otros gastos varios
A99: =YEAR(Banco[[#This Row],[Fecha]]) -> 2022 | B99: =PROPER(TEXT(Banco[[#This Row],[Fecha]],"MMMM")) -> Diciembre | C99: =TEXT(Banco[[#This Row],[Fecha]],"mmm-yyyy") -> dic-2022 | D99: 44907 | E99: TEF 14082906-4 Alejandra Saldi | G99: -22170 | H99: =Banco[[#This Row],[cargos]]*-1 -> 22170 | I99: 0 | J99: 36335535 | K99: =+Banco[[#This Row],[cargos]]+Banco[[#This Row],[Ingresos]] -> -22170 | L99: 2.01.04.03 - Otros gastos varios | M99: =MID(Banco[[#This Row],[CtaCtbl]],FIND(" - ",Banco[[#This Row],[CtaCtbl]])+3,40) -> Otros gastos varios
A100: =YEAR(Banco[[#This Row],[Fecha]]) -> 2022 | B100: =PROPER(TEXT(Banco[[#This Row],[Fecha]],"MMMM")) -> Diciembre | C100: =TEXT(Banco[[#This Row],[Fecha]],"mmm-yyyy") -> dic-2022 | D100: 44907 | E100: TEF 17412336-5 Robinson Cornej | G100: -166969 | H100: =Banco[[#This Row],[cargos]]*-1 -> 166969 | I100: 0 | J100: 36152566 | K100: =+Banco[[#This Row],[cargos]]+Banco[[#This Row],[Ingresos]] -> -166969 | L100: 2.01.04.03 - Otros gastos varios | M100: =MID(Banco[[#This Row],[CtaCtbl]],FIND(" - ",Banco[[#This Row],[CtaCtbl]])+3,40) -> Otros gastos varios
A101: =YEAR(Banco[[#This Row],[Fecha]]) -> 2022 | B101: =PROPER(TEXT(Banco[[#This Row],[Fecha]],"MMMM")) -> Diciembre | C101: =TEXT(Banco[[#This Row],[Fecha]],"mmm-yyyy") -> dic-2022 | D101: 44908 | E101: TEF 12379484-2 Abdel Karim Aza | G101: -138902 | H101: =Banco[[#This Row],[cargos]]*-1 -> 138902 | I101: 0 | J101: 36013664 | K101: =+Banco[[#This Row],[cargos]]+Banco[[#This Row],[Ingresos]] -> -138902 | L101: 2.01.04.03 - Otros gastos varios | M101: =MID(Banco[[#This Row],[CtaCtbl]],FIND(" - ",Banco[[#This Row],[CtaCtbl]])+3,40) -> Otros gastos varios
A102: =YEAR(Banco[[#This Row],[Fecha]]) -> 2022 | B102: =PROPER(TEXT(Banco[[#This Row],[Fecha]],"MMMM")) -> Diciembre | C102: =TEXT(Banco[[#This Row],[Fecha]],"mmm-yyyy") -> dic-2022 | D102: 44918 | E102: PROVEEDORE 96505760-9 COLBUN M | G102: 0 | H102: =Banco[[#This Row],[cargos]]*-1 -> 0 | I102: 3633885 | J102: 39647549 | K102: =+Banco[[#This Row],[cargos]]+Banco[[#This Row],[Ingresos]] -> 3633885 | L102: 1.01.01 - Cuota Ordinaria | M102: =MID(Banco[[#This Row],[CtaCtbl]],FIND(" - ",Banco[[#This Row],[CtaCtbl]])+3,40) -> Cuota Ordinaria
A103: =YEAR(Banco[[#This Row],[Fecha]]) -> 2022 | B103: =PROPER(TEXT(Banco[[#This Row],[Fecha]],"MMMM")) -> Diciembre | C103: =TEXT(Banco[[#This Row],[Fecha]],"mmm-yyyy") -> dic-2022 | D103: 44923 | E103: TEF 18626785-0 Soraya Abigail | G103: 0 | H103: =Banco[[#This Row],[cargos]]*-1 -> 0 | I103: 138362 | J103: 39785911 | K103: =+Banco[[#This Row],[cargos]]+Banco[[#This Row],[Ingresos]] -> 138362 | L103: 1.03.03 - Otros Aportes | M103: =MID(Banco[[#This Row],[CtaCtbl]],FIND(" - ",Banco[[#This Row],[CtaCtbl]])+3,40) -> Otros Aportes | N103: Pago de Cuotas 2022 pedientes. Ya que socia estaba con Sin Goze de Sueldo
A104: =YEAR(Banco[[#This Row],[Fecha]]) -> 2023 | B104: =PROPER(TEXT(Banco[[#This Row],[Fecha]],"MMMM")) -> Enero | C104: =TEXT(Banco[[#This Row],[Fecha]],"mmm-yyyy") -> ene-2023 | D104: 44929 | E104: COBRO COMISION SCOTIAWEB | G104: -20911 | H104: =Banco[[#This Row],[cargos]]*-1 -> 20911 | I104: 0 | J104: 0 | K104: =+Banco[[#This Row],[cargos]]+Banco[[#This Row],[Ingresos]] -> -20911 | L104: 3.03.01 - Pago Comisiones | M104: =MID(Banco[[#This Row],[CtaCtbl]],FIND(" - ",Banco[[#This Row],[CtaCtbl]])+3,40) -> Pago Comisiones
A105: =YEAR(Banco[[#This Row],[Fecha]]) -> 2023 | B105: =PROPER(TEXT(Banco[[#This Row],[Fecha]],"MMMM")) -> Enero | C105: =TEXT(Banco[[#This Row],[Fecha]],"mmm-yyyy") -> ene-2023 | D105: 44952 | E105: PROVEEDORE 96505760-9 COLBUN M | G105: 0 | H105: =Banco[[#This Row],[cargos]]*-1 -> 0 | I105: 3617020 | K105: =+Banco[[#This Row],[cargos]]+Banco[[#This Row],[Ingresos]] -> 3617020 | L105: 1.01.01 - Cuota Ordinaria | M105: =MID(Banco[[#This Row],[CtaCtbl]],FIND(" - ",Banco[[#This Row],[CtaCtbl]])+3,40) -> Cuota Ordinaria
A106: =YEAR(Banco[[#This Row],[Fecha]]) -> 2023 | B106: =PROPER(TEXT(Banco[[#This Row],[Fecha]],"MMMM")) -> Febrero | C106: =TEXT(Banco[[#This Row],[Fecha]],"mmm-yyyy") -> feb-2023 | D106: 44958 | E106: COBRO COMISION SCOTIAWEB | G106: -20998 | H106: =Banco[[#This Row],[cargos]]*-1 -> 20998 | I106: 0 | K106: =+Banco[[#This Row],[cargos]]+Banco[[#This Row],[Ingresos]] -> -20998 | L106: 3.03.01 - Pago Comisiones | M106: =MID(Banco[[#This Row],[CtaCtbl]],FIND(" - ",Banco[[#This Row],[CtaCtbl]])+3,40) -> Pago Comisiones
A107: =YEAR(Banco[[#This Row],[Fecha]]) -> 2023 | B107: =PROPER(TEXT(Banco[[#This Row],[Fecha]],"MMMM")) -> Febrero | C107: =TEXT(Banco[[#This Row],[Fecha]],"mmm-yyyy") -> feb-2023 | D107: 44958 | E107: Transferencia Estudio Juridico | G107: -218440 | H107: =Banco[[#This Row],[cargos]]*-1 -> 218440 | I107: 0 | K107: =+Banco[[#This Row],[cargos]]+Banco[[#This Row],[Ingresos]] -> -218440 | L107: 2.01.01.01.1 - Asesoria Legal - Convenio Fijo Mensual | M107: =MID(Banco[[#This Row],[CtaCtbl]],FIND(" - ",Banco[[#This Row],[CtaCtbl]])+3,40) -> Asesoria Legal - Convenio Fijo Mensual
A108: =YEAR(Banco[[#This Row],[Fecha]]) -> 2023 | B108: =PROPER(TEXT(Banco[[#This Row],[Fecha]],"MMMM")) -> Febrero | C108: =TEXT(Banco[[#This Row],[Fecha]],"mmm-yyyy") -> feb-2023 | D108: 44984 | E108: PROVEEDORE 96505760-9 COLBUN M | G108: 0 | H108: =Banco[[#This Row],[cargos]]*-1 -> 0 | I108: 3622020 | K108: =+Banco[[#This Row],[cargos]]+Banco[[#This Row],[Ingresos]] -> 3622020 | L108: 1.01.01 - Cuota Ordinaria | M108: =MID(Banco[[#This Row],[CtaCtbl]],FIND(" - ",Banco[[#This Row],[CtaCtbl]])+3,40) -> Cuota Ordinaria
A109: =YEAR(Banco[[#This Row],[Fecha]]) -> 2023 | B109: =PROPER(TEXT(Banco[[#This Row],[Fecha]],"MMMM")) -> Marzo | C109: =TEXT(Banco[[#This Row],[Fecha]],"mmm-yyyy") -> mar-2023 | D109: 44986 | E109: COBRO COMISION SCOTIAWEB | G109: -21134 | H109: =Banco[[#This Row],[cargos]]*-1 -> 21134 | I109: 0 | J109: 0 | K109: =+Banco[[#This Row],[cargos]]+Banco[[#This Row],[Ingresos]] -> -21134 | L109: 3.03.01 - Pago Comisiones | M109: =MID(Banco[[#This Row],[CtaCtbl]],FIND(" - ",Banco[[#This Row],[CtaCtbl]])+3,40) -> Pago Comisiones
...

Sheet Plan de Cuentas
E2: 2021 | J2: 2022 | W2: 2023 | AJ2: 2024 | AV2: 2024 | AW2: 2025 | BI2: 2025 | BW2: Resultado
A3: Cuenta | B3: Descripcion Cuenta | C3: Codigo Cta | D3: Observaciones | E3: sept-21 | F3: oct-21 | G3: nov-21 | H3: dic-21 | I3: Total 2021 | J3: ene-22 | K3: feb-22 | L3: mar-22 | M3: abr-22 | N3: may-22 | O3: jun-22 | P3: jul-22 | Q3: ago-22 | R3: sept-22 | S3: oct-22 | T3: nov-22 | U3: dic-22 | V3: Total 2022 | W3: ene-23 | X3: feb-23 | Y3: mar-23 | Z3: abr-23 | AA3: may-23 | AB3: jun-23 | AC3: jul-23 | AD3: ago-23 | AE3: sept-23 | AF3: oct-23 | AG3: nov-23 | AH3: dic-23 | AI3: Total 2023 | AJ3: ene-24 | AK3: feb-24 | AL3: mar-24 | AM3: abr-24 | AN3: may-24 | AO3: jun-24 | AP3: jul-24 | AQ3: ago-24 | AR3: sept-24 | AS3: oct-24 | AT3: nov-24 | AU3: dic-24 | AV3: Total 2024 | AW3: ene-25 | AX3: feb-25 | AY3: mar-25 | AZ3: abr-25 | BA3: may-25 | BB3: jun-25 | BC3: jul-25 | BD3: ago-25 | BE3: sept-25 | BF3: oct-25 | BG3: nov-25 | BH3: dic-25 | BI3: Total 2025 | BJ3: ene-26 | BK3: feb-26 | BL3: mar-26 | BM3: abr-26 | BN3: may-26 | BO3: jun-26 | BP3: jul-26 | BQ3: ago-26 | BR3: sept-26 | BS3: oct-26 | BT3: nov-26 | BU3: dic-26 | BV3: Total 2026 | BW3: Total
A4: 1 | B4: Ingresos | C4: =+Tabla17[[#This Row],[Cuenta]]&" - "&Tabla17[[#This Row],[Descripcion Cuenta]] -> 1 - Ingresos | E4: =SUBTOTAL(9,E5:E24) -> 0 | F4: =SUBTOTAL(9,F5:F24) -> 6794912 | G4: =SUBTOTAL(9,G5:G24) -> 2584008 | H4: =SUBTOTAL(9,H5:H24) -> 2882256 | I4: =SUM(Tabla17[[#This Row],[sept-21]:[dic-21]]) -> 12261176 | J4: =SUBTOTAL(9,J5:J24) -> 2840292 | K4: =SUBTOTAL(9,K5:K24) -> 3200162 | L4: =SUBTOTAL(9,L5:L24) -> 3934272 | M4: =SUBTOTAL(9,M5:M24) -> 3442832 | N4: =SUBTOTAL(9,N5:N24) -> 110496760 | O4: =SUBTOTAL(9,O5:O24) -> 6589603 | P4: =SUBTOTAL(9,P5:P24) -> 3592435 | Q4: =SUBTOTAL(9,Q5:Q24) -> 3603534 | ... BW4: =SUBTOTAL(9,BW5:BW24) -> 0
A5: 1.01 | B5: Cuotas Sindicales | C5: =+Tabla17[[#This Row],[Cuenta]]&" - "&Tabla17[[#This Row],[Descripcion Cuenta]] -> 1.01 - Cuotas Sindicales | E5: =SUBTOTAL(9,E6:E8) -> 0 | F5: =SUBTOTAL(9,F6:F8) -> 6794912 | G5: =SUBTOTAL(9,G6:G8) -> 2584008 | H5: =SUBTOTAL(9,H6:H8) -> 2882256 | I5: =SUM(Tabla17[[#This Row],[sept-21]:[dic-21]]) -> 12261176 | J5: =SUBTOTAL(9,J6:J8) -> 2840292 | K5: =SUBTOTAL(9,K6:K8) -> 3200162 | L5: =SUBTOTAL(9,L6:L8) -> 3934272 | M5: =SUBTOTAL(9,M6:M8) -> 3442832 | N5: =SUBTOTAL(9,N6:N8) -> 3496760 | O5: =SUBTOTAL(9,O6:O8) -> 3589603 | P5: =SUBTOTAL(9,P6:P8) -> 3592435 | Q5: =SUBTOTAL(9,Q6:Q8) -> 3603534 | ... BW5: =SUBTOTAL(9,BW6:BW8) -> 0
A6: 1.01.01 | B6: Cuota Ordinaria | C6: =+Tabla17[[#This Row],[Cuenta]]&" - "&Tabla17[[#This Row],[Descripcion Cuenta]] -> 1.01.01 - Cuota Ordinaria | E6: =SUMIFS(Banco[Monto],Banco[CtaCtbl],$C6,Banco[Periodo Contable],TEXT(E$3,"mmm-yyyy")) -> 0 | F6: =SUMIFS(Banco[Monto],Banco[CtaCtbl],$C6,Banco[Periodo Contable],TEXT(F$3,"mmm-yyyy")) -> 4445566 | G6: =SUMIFS(Banco[Monto],Banco[CtaCtbl],$C6,Banco[Periodo Contable],TEXT(G$3,"mmm-yyyy")) -> 2476341 | H6: =SUMIFS(Banco[Monto],Banco[CtaCtbl],$C6,Banco[Periodo Contable],TEXT(H$3,"mmm-yyyy")) -> 2665312 | I6: =SUM(Tabla17[[#This Row],[sept-21]:[dic-21]]) -> 9587219 | J6: =SUMIFS(Banco[Monto],Banco[CtaCtbl],$C6,Banco[Periodo Contable],TEXT(J$3,"mmm-yyyy")) -> 2731050 | K6: =SUMIFS(Banco[Monto],Banco[CtaCtbl],$C6,Banco[Periodo Contable],TEXT(K$3,"mmm-yyyy")) -> 2917450 | L6: =SUMIFS(Banco[Monto],Banco[CtaCtbl],$C6,Banco[Periodo Contable],TEXT(L$3,"mmm-yyyy")) -> 3410760 | M6: =SUMIFS(Banco[Monto],Banco[CtaCtbl],$C6,Banco[Periodo Contable],TEXT(M$3,"mmm-yyyy")) -> 3442832 | N6: =SUMIFS(Banco[Monto],Banco[CtaCtbl],$C6,Banco[Periodo Contable],TEXT(N$3,"mmm-yyyy")) -> 3496760 | O6: =SUMIFS(Banco[Monto],Banco[CtaCtbl],$C6,Banco[Periodo Contable],TEXT(O$3,"mmm-yyyy")) -> 3507116 | P6: =SUMIFS(Banco[Monto],Banco[CtaCtbl],$C6,Banco[Periodo Contable],TEXT(P$3,"mmm-yyyy")) -> 3592435 | Q6: =SUMIFS(Banco[Monto],Banco[CtaCtbl],$C6,Banco[Periodo Contable],TEXT(Q$3,"mmm-yyyy")) -> 3603534 | ... U6: =SUMIFS(Banco[Monto],Banco[CtaCtbl],$C6,Banco[Periodo Contable],TEXT(U$3,"mmm-yyyy")) -> 3633885 | V6: =SUM(Tabla17[[#This Row],[ene-22]:[dic-22]]) -> 41203147 | W6: =SUMIFS(Banco[Monto],Banco[CtaCtbl],$C6,Banco[Periodo Contable],TEXT(W$3,"mmm-yyyy")) -> 3617020 | X6: =SUMIFS(Banco[Monto],Banco[CtaCtbl],$C6,Banco[Periodo Contable],TEXT(X$3,"mmm-yyyy")) -> 3622020 | Y6: =SUMIFS(Banco[Monto],Banco[CtaCtbl],$C6,Banco[Periodo Contable],TEXT(Y$3,"mmm-yyyy")) -> 3610964 | Z6: =SUMIFS(Banco[Monto],Banco[CtaCtbl],$C6,Banco[Periodo Contable],TEXT(Z$3,"mmm-yyyy")) -> 3619638 | AA6: =SUMIFS(Banco[Monto],Banco[CtaCtbl],$C6,Banco[Periodo Contable],TEXT(AA$3,"mmm-yyyy")) -> 3603200 | AB6: =SUMIFS(Banco[Monto],Banco[CtaCtbl],$C6,Banco[Periodo Contable],TEXT(AB$3,"mmm-yyyy")) -> 3609000 | AC6: =SUMIFS(Banco[Monto],Banco[CtaCtbl],$C6,Banco[Periodo Contable],TEXT(AC$3,"mmm-yyyy")) -> 3623016 | AD6: =SUMIFS(Banco[Monto],Banco[CtaCtbl],$C6,Banco[Periodo Contable],TEXT(AD$3,"mmm-yyyy")) -> 3594935 | ... AH6: =SUMIFS(Banco[Monto],Banco[CtaCtbl],$C6,Banco[Periodo Contable],TEXT(AH$3,"mmm-yyyy")) -> 3605420 | AI6: =SUM(Tabla17[[#This Row],[ene-23]:[dic-23]]) -> 43310880 | AJ6: =SUMIFS(Banco[Monto],Banco[CtaCtbl],$C6,Banco[Periodo Contable],TEXT(AJ$3,"mmm-yyyy")) -> 3618299 | AK6: =SUMIFS(Banco[Monto],Banco[CtaCtbl],$C6,Banco[Periodo Contable],TEXT(AK$3,"mmm-yyyy")) -> 3611888 | AL6: =SUMIFS(Banco[Monto],Banco[CtaCtbl],$C6,Banco[Periodo Contable],TEXT(AL$3,"mmm-yyyy")) -> 3635212 | AM6: =SUMIFS(Banco[Monto],Banco[CtaCtbl],$C6,Banco[Periodo Contable],TEXT(AM$3,"mmm-yyyy")) -> 3688938 | AN6: =SUMIFS(Banco[Monto],Banco[CtaCtbl],$C6,Banco[Periodo Contable],TEXT(AN$3,"mmm-yyyy")) -> 3650205 | AO6: =SUMIFS(Banco[Monto],Banco[CtaCtbl],$C6,Banco[Periodo Contable],TEXT(AO$3,"mmm-yyyy")) -> 3644484 | AP6: =SUMIFS(Banco[Monto],Banco[CtaCtbl],$C6,Banco[Periodo Contable],TEXT(AP$3,"mmm-yyyy")) -> 3626277 | AQ6: =SUMIFS(Banco[Monto],Banco[CtaCtbl],$C6,Banco[Periodo Contable],TEXT(AQ$3,"mmm-yyyy")) -> 3643261 | ... AU6: =SUMIFS(Banco[Monto],Banco[CtaCtbl],$C6,Banco[Periodo Contable],TEXT(AU$3,"mmm-yyyy")) -> 5128536 | AV6: =SUM(Tabla17[[#This Row],[ene-24]:[dic-24]]) -> 45984735 | AW6: =SUMIFS(Banco[Monto],Banco[CtaCtbl],$C6,Banco[Periodo Contable],TEXT(AW$3,"mmm-yyyy")) -> 5047496 | AX6: =SUMIFS(Banco[Monto],Banco[CtaCtbl],$C6,Banco[Periodo Contable],TEXT(AX$3,"mmm-yyyy")) -> 8599180 | AY6: =SUMIFS(Banco[Monto],Banco[CtaCtbl],$C6,Banco[Periodo Contable],TEXT(AY$3,"mmm-yyyy")) -> 9373454 | AZ6: =SUMIFS(Banco[Monto],Banco[CtaCtbl],$C6,Banco[Periodo Contable],TEXT(AZ$3,"mmm-yyyy")) -> 9417316 | BA6: =SUMIFS(Banco[Monto],Banco[CtaCtbl],$C6,Banco[Periodo Contable],TEXT(BA$3,"mmm-yyyy")) -> 9366410 | BB6: =SUMIFS(Banco[Monto],Banco[CtaCtbl],$C6,Banco[Periodo Contable],TEXT(BB$3,"mmm-yyyy")) -> 9286882 | BC6: =SUMIFS(Banco[Monto],Banco[CtaCtbl],$C6,Banco[Periodo Contable],TEXT(BC$3,"mmm-yyyy")) -> 9187710 | BD6: =SUMIFS(Banco[Monto],Banco[CtaCtbl],$C6,Banco[Periodo Contable],TEXT(BD$3,"mmm-yyyy")) -> 9156780 | ... BH6: =SUMIFS(Banco[Monto],Banco[CtaCtbl],$C6,Banco[Periodo Contable],TEXT(BH$3,"mmm-yyyy")) -> 8938800 | BI6: =SUM(Tabla17[[#This Row],[ene-25]:[dic-25]]) -> 96415352 | BJ6: =SUMIFS(Banco[Monto],Banco[CtaCtbl],$C6,Banco[Periodo Contable],TEXT(BJ$3,"mmm-yyyy")) -> 8933850 | BK6: =SUMIFS(Banco[Monto],Banco[CtaCtbl],$C6,Banco[Periodo Contable],TEXT(BK$3,"mmm-yyyy")) -> 8455375 | BL6: =SUMIFS(Banco[Monto],Banco[CtaCtbl],$C6,Banco[Periodo Contable],TEXT(BL$3,"mmm-yyyy")) -> 0 | BM6: =SUMIFS(Banco[Monto],Banco[CtaCtbl],$C6,Banco[Periodo Contable],TEXT(BM$3,"mmm-yyyy")) -> 0 | BN6: =SUMIFS(Banco[Monto],Banco[CtaCtbl],$C6,Banco[Periodo Contable],TEXT(BN$3,"mmm-yyyy")) -> 0 | BO6: =SUMIFS(Banco[Monto],Banco[CtaCtbl],$C6,Banco[Periodo Contable],TEXT(BO$3,"mmm-yyyy")) -> 0 | BP6: =SUMIFS(Banco[Monto],Banco[CtaCtbl],$C6,Banco[Periodo Contable],TEXT(BP$3,"mmm-yyyy")) -> 0 | BQ6: =SUMIFS(Banco[Monto],Banco[CtaCtbl],$C6,Banco[Periodo Contable],TEXT(BQ$3,"mmm-yyyy")) -> 0 | ... BU6: =SUMIFS(Banco[Monto],Banco[CtaCtbl],$C6,Banco[Periodo Contable],TEXT(BU$3,"mmm-yyyy")) -> 0 | BV6: =SUM(Tabla17[[#This Row],[ene-26]:[dic-26]]) -> 17389225 | BW6: =SUMIFS(Banco[Monto],Banco[CtaCtbl],$C6,Banco[Periodo Contable],TEXT(BW$3,"mmm-yyyy")) -> 0
A7: 1.01.02 | B7: Cuota Extraordinaria | C7: =+Tabla17[[#This Row],[Cuenta]]&" - "&Tabla17[[#This Row],[Descripcion Cuenta]] -> 1.01.02 - Cuota Extraordinaria | E7: =SUMIFS(Banco[Monto],Banco[CtaCtbl],$C7,Banco[Periodo Contable],TEXT(E$3,"mmm-yyyy")) -> 0 | F7: =SUMIFS(Banco[Monto],Banco[CtaCtbl],$C7,Banco[Periodo Contable],TEXT(F$3,"mmm-yyyy")) -> 2349346 | G7: =SUMIFS(Banco[Monto],Banco[CtaCtbl],$C7,Banco[Periodo Contable],TEXT(G$3,"mmm-yyyy")) -> 107667 | H7: =SUMIFS(Banco[Monto],Banco[CtaCtbl],$C7,Banco[Periodo Contable],TEXT(H$3,"mmm-yyyy")) -> 216944 | I7: =SUM(Tabla17[[#This Row],[sept-21]:[dic-21]]) -> 2673957 | J7: =SUMIFS(Banco[Monto],Banco[CtaCtbl],$C7,Banco[Periodo Contable],TEXT(J$3,"mmm-yyyy")) -> 109242 | K7: =SUMIFS(Banco[Monto],Banco[CtaCtbl],$C7,Banco[Periodo Contable],TEXT(K$3,"mmm-yyyy")) -> 282712 | L7: =SUMIFS(Banco[Monto],Banco[CtaCtbl],$C7,Banco[Periodo Contable],TEXT(L$3,"mmm-yyyy")) -> 523512 | M7: =SUMIFS(Banco[Monto],Banco[CtaCtbl],$C7,Banco[Periodo Contable],TEXT(M$3,"mmm-yyyy")) -> 0 | N7: =SUMIFS(Banco[Monto],Banco[CtaCtbl],$C7,Banco[Periodo Contable],TEXT(N$3,"mmm-yyyy")) -> 0 | O7: =SUMIFS(Banco[Monto],Banco[CtaCtbl],$C7,Banco[Periodo Contable],TEXT(O$3,"mmm-yyyy")) -> 82487 | P7: =SUMIFS(Banco[Monto],Banco[CtaCtbl],$C7,Banco[Periodo Contable],TEXT(P$3,"mmm-yyyy")) -> 0 | Q7: =SUMIFS(Banco[Monto],Banco[CtaCtbl],$C7,Banco[Periodo Contable],TEXT(Q$3,"mmm-yyyy")) -> 0 | ... U7: =SUMIFS(Banco[Monto],Banco[CtaCtbl],$C7,Banco[Periodo Contable],TEXT(U$3,"mmm-yyyy")) -> 0 | V7: =SUM(Tabla17[[#This Row],[ene-22]:[dic-22]]) -> 997953 | W7: =SUMIFS(Banco[Monto],Banco[CtaCtbl],$C7,Banco[Periodo Contable],TEXT(W$3,"mmm-yyyy")) -> 0 | X7: =SUMIFS(Banco[Monto],Banco[CtaCtbl],$C7,Banco[Periodo Contable],TEXT(X$3,"mmm-yyyy")) -> 0 | Y7: =SUMIFS(Banco[Monto],Banco[CtaCtbl],$C7,Banco[Periodo Contable],TEXT(Y$3,"mmm-yyyy")) -> 0 | Z7: =SUMIFS(Banco[Monto],Banco[CtaCtbl],$C7,Banco[Periodo Contable],TEXT(Z$3,"mmm-yyyy")) -> 2134184 | AA7: =SUMIFS(Banco[Monto],Banco[CtaCtbl],$C7,Banco[Periodo Contable],TEXT(AA$3,"mmm-yyyy")) -> 0 | AB7: =SUMIFS(Banco[Monto],Banco[CtaCtbl],$C7,Banco[Periodo Contable],TEXT(AB$3,"mmm-yyyy")) -> 0 | AC7: =SUMIFS(Banco[Monto],Banco[CtaCtbl],$C7,Banco[Periodo Contable],TEXT(AC$3,"mmm-yyyy")) -> 0 | AD7: =SUMIFS(Banco[Monto],Banco[CtaCtbl],$C7,Banco[Periodo Contable],TEXT(AD$3,"mmm-yyyy")) -> 18025 | ... AH7: =SUMIFS(Banco[Monto],Banco[CtaCtbl],$C7,Banco[Periodo Contable],TEXT(AH$3,"mmm-yyyy")) -> 18282 | AI7: =SUM(Tabla17[[#This Row],[ene-23]:[dic-23]]) -> 2466551 | AJ7: =SUMIFS(Banco[Monto],Banco[CtaCtbl],$C7,Banco[Periodo Contable],TEXT(AJ$3,"mmm-yyyy")) -> 36649 | AK7: =SUMIFS(Banco[Monto],Banco[CtaCtbl],$C7,Banco[Periodo Contable],TEXT(AK$3,"mmm-yyyy")) -> 18282 | AL7: =SUMIFS(Banco[Monto],Banco[CtaCtbl],$C7,Banco[Periodo Contable],TEXT(AL$3,"mmm-yyyy")) -> 2257607 | AM7: =SUMIFS(Banco[Monto],Banco[CtaCtbl],$C7,Banco[Periodo Contable],TEXT(AM$3,"mmm-yyyy")) -> 92806 | AN7: =SUMIFS(Banco[Monto],Banco[CtaCtbl],$C7,Banco[Periodo Contable],TEXT(AN$3,"mmm-yyyy")) -> 18282 | AO7: =SUMIFS(Banco[Monto],Banco[CtaCtbl],$C7,Banco[Periodo Contable],TEXT(AO$3,"mmm-yyyy")) -> 18282 | AP7: =SUMIFS(Banco[Monto],Banco[CtaCtbl],$C7,Banco[Periodo Contable],TEXT(AP$3,"mmm-yyyy")) -> 18282 | AQ7: =SUMIFS(Banco[Monto],Banco[CtaCtbl],$C7,Banco[Periodo Contable],TEXT(AQ$3,"mmm-yyyy")) -> 18282 | ... AU7: =SUMIFS(Banco[Monto],Banco[CtaCtbl],$C7,Banco[Periodo Contable],TEXT(AU$3,"mmm-yyyy")) -> 1450664 | AV7: =SUM(Tabla17[[#This Row],[ene-24]:[dic-24]]) -> 3983982 | AW7: =SUMIFS(Banco[Monto],Banco[CtaCtbl],$C7,Banco[Periodo Contable],TEXT(AW$3,"mmm-yyyy")) -> 0 | AX7: =SUMIFS(Banco[Monto],Banco[CtaCtbl],$C7,Banco[Periodo Contable],TEXT(AX$3,"mmm-yyyy")) -> 3594264 | AY7: =SUMIFS(Banco[Monto],Banco[CtaCtbl],$C7,Banco[Periodo Contable],TEXT(AY$3,"mmm-yyyy")) -> 738986 | AZ7: =SUMIFS(Banco[Monto],Banco[CtaCtbl],$C7,Banco[Periodo Contable],TEXT(AZ$3,"mmm-yyyy")) -> 0 | BA7: =SUMIFS(Banco[Monto],Banco[CtaCtbl],$C7,Banco[Periodo Contable],TEXT(BA$3,"mmm-yyyy")) -> 0 | BB7: =SUMIFS(Banco[Monto],Banco[CtaCtbl],$C7,Banco[Periodo Contable],TEXT(BB$3,"mmm-yyyy")) -> 0 | BC7: =SUMIFS(Banco[Monto],Banco[CtaCtbl],$C7,Banco[Periodo Contable],TEXT(BC$3,"mmm-yyyy")) -> 0 | BD7: =SUMIFS(Banco[Monto],Banco[CtaCtbl],$C7,Banco[Periodo Contable],TEXT(BD$3,"mmm-yyyy")) -> 0 | ... BH7: =SUMIFS(Banco[Monto],Banco[CtaCtbl],$C7,Banco[Periodo Contable],TEXT(BH$3,"mmm-yyyy")) -> 0 | BI7: =SUM(Tabla17[[#This Row],[ene-25]:[dic-25]]) -> 4333250 | BJ7: =SUMIFS(Banco[Monto],Banco[CtaCtbl],$C7,Banco[Periodo Contable],TEXT(BJ$3,"mmm-yyyy")) -> 0 | BK7: =SUMIFS(Banco[Monto],Banco[CtaCtbl],$C7,Banco[Periodo Contable],TEXT(BK$3,"mmm-yyyy")) -> 0 | BL7: =SUMIFS(Banco[Monto],Banco[CtaCtbl],$C7,Banco[Periodo Contable],TEXT(BL$3,"mmm-yyyy")) -> 0 | BM7: =SUMIFS(Banco[Monto],Banco[CtaCtbl],$C7,Banco[Periodo Contable],TEXT(BM$3,"mmm-yyyy")) -> 0 | BN7: =SUMIFS(Banco[Monto],Banco[CtaCtbl],$C7,Banco[Periodo Contable],TEXT(BN$3,"mmm-yyyy")) -> 0 | BO7: =SUMIFS(Banco[Monto],Banco[CtaCtbl],$C7,Banco[Periodo Contable],TEXT(BO$3,"mmm-yyyy")) -> 0 | BP7: =SUMIFS(Banco[Monto],Banco[CtaCtbl],$C7,Banco[Periodo Contable],TEXT(BP$3,"mmm-yyyy")) -> 0 | BQ7: =SUMIFS(Banco[Monto],Banco[CtaCtbl],$C7,Banco[Periodo Contable],TEXT(BQ$3,"mmm-yyyy")) -> 0 | ... BU7: =SUMIFS(Banco[Monto],Banco[CtaCtbl],$C7,Banco[Periodo Contable],TEXT(BU$3,"mmm-yyyy")) -> 0 | BV7: =SUM(Tabla17[[#This Row],[ene-26]:[dic-26]]) -> 0 | BW7: =SUMIFS(Banco[Monto],Banco[CtaCtbl],$C7,Banco[Periodo Contable],TEXT(BW$3,"mmm-yyyy")) -> 0
A8: 1.01.03 | C8: =+Tabla17[[#This Row],[Cuenta]]&" - "&Tabla17[[#This Row],[Descripcion Cuenta]] -> 1.01.03 - | E8: =SUMIFS(Banco[Monto],Banco[CtaCtbl],$C8,Banco[Periodo Contable],TEXT(E$3,"mmm-yyyy")) -> 0 | F8: =SUMIFS(Banco[Monto],Banco[CtaCtbl],$C8,Banco[Periodo Contable],TEXT(F$3,"mmm-yyyy")) -> 0 | G8: =SUMIFS(Banco[Monto],Banco[CtaCtbl],$C8,Banco[Periodo Contable],TEXT(G$3,"mmm-yyyy")) -> 0 | H8: =SUMIFS(Banco[Monto],Banco[CtaCtbl],$C8,Banco[Periodo Contable],TEXT(H$3,"mmm-yyyy")) -> 0 | I8: =SUM(Tabla17[[#This Row],[sept-21]:[dic-21]]) -> 0 | J8: =SUMIFS(Banco[Monto],Banco[CtaCtbl],$C8,Banco[Periodo Contable],TEXT(J$3,"mmm-yyyy")) -> 0 | K8: =SUMIFS(Banco[Monto],Banco[CtaCtbl],$C8,Banco[Periodo Contable],TEXT(K$3,"mmm-yyyy")) -> 0 | L8: =SUMIFS(Banco[Monto],Banco[CtaCtbl],$C8,Banco[Periodo Contable],TEXT(L$3,"mmm-yyyy")) -> 0 | M8: =SUMIFS(Banco[Monto],Banco[CtaCtbl],$C8,Banco[Periodo Contable],TEXT(M$3,"mmm-yyyy")) -> 0 | N8: =SUMIFS(Banco[Monto],Banco[CtaCtbl],$C8,Banco[Periodo Contable],TEXT(N$3,"mmm-yyyy")) -> 0 | O8: =SUMIFS(Banco[Monto],Banco[CtaCtbl],$C8,Banco[Periodo Contable],TEXT(O$3,"mmm-yyyy")) -> 0 | P8: =SUMIFS(Banco[Monto],Banco[CtaCtbl],$C8,Banco[Periodo Contable],TEXT(P$3,"mmm-yyyy")) -> 0 | Q8: =SUMIFS(Banco[Monto],Banco[CtaCtbl],$C8,Banco[Periodo Contable],TEXT(Q$3,"mmm-yyyy")) -> 0 | ... U8: =SUMIFS(Banco[Monto],Banco[CtaCtbl],$C8,Banco[Periodo Contable],TEXT(U$3,"mmm-yyyy")) -> 0 | V8: =SUM(Tabla17[[#This Row],[ene-22]:[dic-22]]) -> 0 | W8: =SUMIFS(Banco[Monto],Banco[CtaCtbl],$C8,Banco[Periodo Contable],TEXT(W$3,"mmm-yyyy")) -> 0 | X8: =SUMIFS(Banco[Monto],Banco[CtaCtbl],$C8,Banco[Periodo Contable],TEXT(X$3,"mmm-yyyy")) -> 0 | Y8: =SUMIFS(Banco[Monto],Banco[CtaCtbl],$C8,Banco[Periodo Contable],TEXT(Y$3,"mmm-yyyy")) -> 0 | Z8: =SUMIFS(Banco[Monto],Banco[CtaCtbl],$C8,Banco[Periodo Contable],TEXT(Z$3,"mmm-yyyy")) -> 0 | AA8: =SUMIFS(Banco[Monto],Banco[CtaCtbl],$C8,Banco[Periodo Contable],TEXT(AA$3,"mmm-yyyy")) -> 0 | AB8: =SUMIFS(Banco[Monto],Banco[CtaCtbl],$C8,Banco[Periodo Contable],TEXT(AB$3,"mmm-yyyy")) -> 0 | AC8: =SUMIFS(Banco[Monto],Banco[CtaCtbl],$C8,Banco[Periodo Contable],TEXT(AC$3,"mmm-yyyy")) -> 0 | AD8: =SUMIFS(Banco[Monto],Banco[CtaCtbl],$C8,Banco[Periodo Contable],TEXT(AD$3,"mmm-yyyy")) -> 0 | ... AH8: =SUMIFS(Banco[Monto],Banco[CtaCtbl],$C8,Banco[Periodo Contable],TEXT(AH$3,"mmm-yyyy")) -> 0 | AI8: =SUM(Tabla17[[#This Row],[ene-23]:[dic-23]]) -> 0 | AJ8: =SUMIFS(Banco[Monto],Banco[CtaCtbl],$C8,Banco[Periodo Contable],TEXT(AJ$3,"mmm-yyyy")) -> 0 | AK8: =SUMIFS(Banco[Monto],Banco[CtaCtbl],$C8,Banco[Periodo Contable],TEXT(AK$3,"mmm-yyyy")) -> 0 | AL8: =SUMIFS(Banco[Monto],Banco[CtaCtbl],$C8,Banco[Periodo Contable],TEXT(AL$3,"mmm-yyyy")) -> 0 | AM8: =SUMIFS(Banco[Monto],Banco[CtaCtbl],$C8,Banco[Periodo Contable],TEXT(AM$3,"mmm-yyyy")) -> 0 | AN8: =SUMIFS(Banco[Monto],Banco[CtaCtbl],$C8,Banco[Periodo Contable],TEXT(AN$3,"mmm-yyyy")) -> 0 | AO8: =SUMIFS(Banco[Monto],Banco[CtaCtbl],$C8,Banco[Periodo Contable],TEXT(AO$3,"mmm-yyyy")) -> 0 | AP8: =SUMIFS(Banco[Monto],Banco[CtaCtbl],$C8,Banco[Periodo Contable],TEXT(AP$3,"mmm-yyyy")) -> 0 | AQ8: =SUMIFS(Banco[Monto],Banco[CtaCtbl],$C8,Banco[Periodo Contable],TEXT(AQ$3,"mmm-yyyy")) -> 0 | ... AU8: =SUMIFS(Banco[Monto],Banco[CtaCtbl],$C8,Banco[Periodo Contable],TEXT(AU$3,"mmm-yyyy")) -> 0 | AV8: =SUM(Tabla17[[#This Row],[ene-24]:[dic-24]]) -> 0 | AW8: =SUMIFS(Banco[Monto],Banco[CtaCtbl],$C8,Banco[Periodo Contable],TEXT(AW$3,"mmm-yyyy")) -> 0 | AX8: =SUMIFS(Banco[Monto],Banco[CtaCtbl],$C8,Banco[Periodo Contable],TEXT(AX$3,"mmm-yyyy")) -> 0 | AY8: =SUMIFS(Banco[Monto],Banco[CtaCtbl],$C8,Banco[Periodo Contable],TEXT(AY$3,"mmm-yyyy")) -> 0 | AZ8: =SUMIFS(Banco[Monto],Banco[CtaCtbl],$C8,Banco[Periodo Contable],TEXT(AZ$3,"mmm-yyyy")) -> 0 | BA8: =SUMIFS(Banco[Monto],Banco[CtaCtbl],$C8,Banco[Periodo Contable],TEXT(BA$3,"mmm-yyyy")) -> 0 | BB8: =SUMIFS(Banco[Monto],Banco[CtaCtbl],$C8,Banco[Periodo Contable],TEXT(BB$3,"mmm-yyyy")) -> 0 | BC8: =SUMIFS(Banco[Monto],Banco[CtaCtbl],$C8,Banco[Periodo Contable],TEXT(BC$3,"mmm-yyyy")) -> 0 | BD8: =SUMIFS(Banco[Monto],Banco[CtaCtbl],$C8,Banco[Periodo Contable],TEXT(BD$3,"mmm-yyyy")) -> 0 | ... BH8: =SUMIFS(Banco[Monto],Banco[CtaCtbl],$C8,Banco[Periodo Contable],TEXT(BH$3,"mmm-yyyy")) -> 0 | BI8: =SUM(Tabla17[[#This Row],[ene-25]:[dic-25]]) -> 0 | BJ8: =SUMIFS(Banco[Monto],Banco[CtaCtbl],$C8,Banco[Periodo Contable],TEXT(BJ$3,"mmm-yyyy")) -> 0 | BK8: =SUMIFS(Banco[Monto],Banco[CtaCtbl],$C8,Banco[Periodo Contable],TEXT(BK$3,"mmm-yyyy")) -> 0 | BL8: =SUMIFS(Banco[Monto],Banco[CtaCtbl],$C8,Banco[Periodo Contable],TEXT(BL$3,"mmm-yyyy")) -> 0 | BM8: =SUMIFS(Banco[Monto],Banco[CtaCtbl],$C8,Banco[Periodo Contable],TEXT(BM$3,"mmm-yyyy")) -> 0 | BN8: =SUMIFS(Banco[Monto],Banco[CtaCtbl],$C8,Banco[Periodo Contable],TEXT(BN$3,"mmm-yyyy")) -> 0 | BO8: =SUMIFS(Banco[Monto],Banco[CtaCtbl],$C8,Banco[Periodo Contable],TEXT(BO$3,"mmm-yyyy")) -> 0 | BP8: =SUMIFS(Banco[Monto],Banco[CtaCtbl],$C8,Banco[Periodo Contable],TEXT(BP$3,"mmm-yyyy")) -> 0 | BQ8: =SUMIFS(Banco[Monto],Banco[CtaCtbl],$C8,Banco[Periodo Contable],TEXT(BQ$3,"mmm-yyyy")) -> 0 | ... BU8: =SUMIFS(Banco[Monto],Banco[CtaCtbl],$C8,Banco[Periodo Contable],TEXT(BU$3,"mmm-yyyy")) -> 0 | BV8: =SUM(Tabla17[[#This Row],[ene-26]:[dic-26]]) -> 0 | BW8: =SUMIFS(Banco[Monto],Banco[CtaCtbl],$C8,Banco[Periodo Contable],TEXT(BW$3,"mmm-yyyy")) -> 0
A9: 1.02 | B9: Multas | C9: =+Tabla17[[#This Row],[Cuenta]]&" - "&Tabla17[[#This Row],[Descripcion Cuenta]] -> 1.02 - Multas | E9: =SUBTOTAL(9,E10:E11) -> 0 | F9: =SUBTOTAL(9,F10:F11) -> 0 | G9: =SUBTOTAL(9,G10:G11) -> 0 | H9: =SUBTOTAL(9,H10:H11) -> 0 | I9: =SUM(Tabla17[[#This Row],[sept-21]:[dic-21]]) -> 0 | J9: =SUBTOTAL(9,J10:J11) -> 0 | K9: =SUBTOTAL(9,K10:K11) -> 0 | L9: =SUBTOTAL(9,L10:L11) -> 0 | M9: =SUBTOTAL(9,M10:M11) -> 0 | N9: =SUBTOTAL(9,N10:N11) -> 0 | O9: =SUBTOTAL(9,O10:O11) -> 0 | P9: =SUBTOTAL(9,P10:P11) -> 0 | Q9: =SUBTOTAL(9,Q10:Q11) -> 0 | ... BW9: =SUBTOTAL(9,BW10:BW11) -> 0
A10: 1.02.01 | B10: Multa Inasistencia | C10: =+Tabla17[[#This Row],[Cuenta]]&" - "&Tabla17[[#This Row],[Descripcion Cuenta]] -> 1.02.01 - Multa Inasistencia | E10: =SUMIFS(Banco[Monto],Banco[CtaCtbl],$C10,Banco[Periodo Contable],TEXT(E$3,"mmm-yyyy")) -> 0 | F10: =SUMIFS(Banco[Monto],Banco[CtaCtbl],$C10,Banco[Periodo Contable],TEXT(F$3,"mmm-yyyy")) -> 0 | G10: =SUMIFS(Banco[Monto],Banco[CtaCtbl],$C10,Banco[Periodo Contable],TEXT(G$3,"mmm-yyyy")) -> 0 | H10: =SUMIFS(Banco[Monto],Banco[CtaCtbl],$C10,Banco[Periodo Contable],TEXT(H$3,"mmm-yyyy")) -> 0 | I10: =SUM(Tabla17[[#This Row],[sept-21]:[dic-21]]) -> 0 | J10: =SUMIFS(Banco[Monto],Banco[CtaCtbl],$C10,Banco[Periodo Contable],TEXT(J$3,"mmm-yyyy")) -> 0 | K10: =SUMIFS(Banco[Monto],Banco[CtaCtbl],$C10,Banco[Periodo Contable],TEXT(K$3,"mmm-yyyy")) -> 0 | L10: =SUMIFS(Banco[Monto],Banco[CtaCtbl],$C10,Banco[Periodo Contable],TEXT(L$3,"mmm-yyyy")) -> 0 | M10: =SUMIFS(Banco[Monto],Banco[CtaCtbl],$C10,Banco[Periodo Contable],TEXT(M$3,"mmm-yyyy")) -> 0 | N10: =SUMIFS(Banco[Monto],Banco[CtaCtbl],$C10,Banco[Periodo Contable],TEXT(N$3,"mmm-yyyy")) -> 0 | O10: =SUMIFS(Banco[Monto],Banco[CtaCtbl],$C10,Banco[Periodo Contable],TEXT(O$3,"mmm-yyyy")) -> 0 | P10: =SUMIFS(Banco[Monto],Banco[CtaCtbl],$C10,Banco[Periodo Contable],TEXT(P$3,"mmm-yyyy")) -> 0 | Q10: =SUMIFS(Banco[Monto],Banco[CtaCtbl],$C10,Banco[Periodo Contable],TEXT(Q$3,"mmm-yyyy")) -> 0 | ... U10: =SUMIFS(Banco[Monto],Banco[CtaCtbl],$C10,Banco[Periodo Contable],TEXT(U$3,"mmm-yyyy")) -> 0 | V10: =SUM(Tabla17[[#This Row],[ene-22]:[dic-22]]) -> 0 | W10: =SUMIFS(Banco[Monto],Banco[CtaCtbl],$C10,Banco[Periodo Contable],TEXT(W$3,"mmm-yyyy")) -> 0 | X10: =SUMIFS(Banco[Monto],Banco[CtaCtbl],$C10,Banco[Periodo Contable],TEXT(X$3,"mmm-yyyy")) -> 0 | Y10: =SUMIFS(Banco[Monto],Banco[CtaCtbl],$C10,Banco[Periodo Contable],TEXT(Y$3,"mmm-yyyy")) -> 0 | Z10: =SUMIFS(Banco[Monto],Banco[CtaCtbl],$C10,Banco[Periodo Contable],TEXT(Z$3,"mmm-yyyy")) -> 0 | AA10: =SUMIFS(Banco[Monto],Banco[CtaCtbl],$C10,Banco[Periodo Contable],TEXT(AA$3,"mmm-yyyy")) -> 0 | AB10: =SUMIFS(Banco[Monto],Banco[CtaCtbl],$C10,Banco[Periodo Contable],TEXT(AB$3,"mmm-yyyy")) -> 0 | AC10: =SUMIFS(Banco[Monto],Banco[CtaCtbl],$C10,Banco[Periodo Contable],TEXT(AC$3,"mmm-yyyy")) -> 0 | AD10: =SUMIFS(Banco[Monto],Banco[CtaCtbl],$C10,Banco[Periodo Contable],TEXT(AD$3,"mmm-yyyy")) -> 0 | ... AH10: =SUMIFS(Banco[Monto],Banco[CtaCtbl],$C10,Banco[Periodo Contable],TEXT(AH$3,"mmm-yyyy")) -> 0 | AI10: =SUM(Tabla17[[#This Row],[ene-23]:[dic-23]]) -> 0 | AJ10: =SUMIFS(Banco[Monto],Banco[CtaCtbl],$C10,Banco[Periodo Contable],TEXT(AJ$3,"mmm-yyyy")) -> 0 | AK10: =SUMIFS(Banco[Monto],Banco[CtaCtbl],$C10,Banco[Periodo Contable],TEXT(AK$3,"mmm-yyyy")) -> 0 | AL10: =SUMIFS(Banco[Monto],Banco[CtaCtbl],$C10,Banco[Periodo Contable],TEXT(AL$3,"mmm-yyyy")) -> 0 | AM10: =SUMIFS(Banco[Monto],Banco[CtaCtbl],$C10,Banco[Periodo Contable],TEXT(AM$3,"mmm-yyyy")) -> 0 | AN10: =SUMIFS(Banco[Monto],Banco[CtaCtbl],$C10,Banco[Periodo Contable],TEXT(AN$3,"mmm-yyyy")) -> 0 | AO10: =SUMIFS(Banco[Monto],Banco[CtaCtbl],$C10,Banco[Periodo Contable],TEXT(AO$3,"mmm-yyyy")) -> 0 | AP10: =SUMIFS(Banco[Monto],Banco[CtaCtbl],$C10,Banco[Periodo Contable],TEXT(AP$3,"mmm-yyyy")) -> 0 | AQ10: =SUMIFS(Banco[Monto],Banco[CtaCtbl],$C10,Banco[Periodo Contable],TEXT(AQ$3,"mmm-yyyy")) -> 0 | ... AU10: =SUMIFS(Banco[Monto],Banco[CtaCtbl],$C10,Banco[Periodo Contable],TEXT(AU$3,"mmm-yyyy")) -> 0 | AV10: =SUM(Tabla17[[#This Row],[ene-24]:[dic-24]]) -> 0 | AW10: =SUMIFS(Banco[Monto],Banco[CtaCtbl],$C10,Banco[Periodo Contable],TEXT(AW$3,"mmm-yyyy")) -> 0 | AX10: =SUMIFS(Banco[Monto],Banco[CtaCtbl],$C10,Banco[Periodo Contable],TEXT(AX$3,"mmm-yyyy")) -> 0 | AY10: =SUMIFS(Banco[Monto],Banco[CtaCtbl],$C10,Banco[Periodo Contable],TEXT(AY$3,"mmm-yyyy")) -> 0 | AZ10: =SUMIFS(Banco[Monto],Banco[CtaCtbl],$C10,Banco[Periodo Contable],TEXT(AZ$3,"mmm-yyyy")) -> 0 | BA10: =SUMIFS(Banco[Monto],Banco[CtaCtbl],$C10,Banco[Periodo Contable],TEXT(BA$3,"mmm-yyyy")) -> 0 | BB10: =SUMIFS(Banco[Monto],Banco[CtaCtbl],$C10,Banco[Periodo Contable],TEXT(BB$3,"mmm-yyyy")) -> 0 | BC10: =SUMIFS(Banco[Monto],Banco[CtaCtbl],$C10,Banco[Periodo Contable],TEXT(BC$3,"mmm-yyyy")) -> 0 | BD10: =SUMIFS(Banco[Monto],Banco[CtaCtbl],$C10,Banco[Periodo Contable],TEXT(BD$3,"mmm-yyyy")) -> 0 | ... BH10: =SUMIFS(Banco[Monto],Banco[CtaCtbl],$C10,Banco[Periodo Contable],TEXT(BH$3,"mmm-yyyy")) -> 0 | BI10: =SUM(Tabla17[[#This Row],[ene-25]:[dic-25]]) -> 0 | BJ10: =SUMIFS(Banco[Monto],Banco[CtaCtbl],$C10,Banco[Periodo Contable],TEXT(BJ$3,"mmm-yyyy")) -> 0 | BK10: =SUMIFS(Banco[Monto],Banco[CtaCtbl],$C10,Banco[Periodo Contable],TEXT(BK$3,"mmm-yyyy")) -> 0 | BL10: =SUMIFS(Banco[Monto],Banco[CtaCtbl],$C10,Banco[Periodo Contable],TEXT(BL$3,"mmm-yyyy")) -> 0 | BM10: =SUMIFS(Banco[Monto],Banco[CtaCtbl],$C10,Banco[Periodo Contable],TEXT(BM$3,"mmm-yyyy")) -> 0 | BN10: =SUMIFS(Banco[Monto],Banco[CtaCtbl],$C10,Banco[Periodo Contable],TEXT(BN$3,"mmm-yyyy")) -> 0 | BO10: =SUMIFS(Banco[Monto],Banco[CtaCtbl],$C10,Banco[Periodo Contable],TEXT(BO$3,"mmm-yyyy")) -> 0 | BP10: =SUMIFS(Banco[Monto],Banco[CtaCtbl],$C10,Banco[Periodo Contable],TEXT(BP$3,"mmm-yyyy")) -> 0 | BQ10: =SUMIFS(Banco[Monto],Banco[CtaCtbl],$C10,Banco[Periodo Contable],TEXT(BQ$3,"mmm-yyyy")) -> 0 | ... BU10: =SUMIFS(Banco[Monto],Banco[CtaCtbl],$C10,Banco[Periodo Contable],TEXT(BU$3,"mmm-yyyy")) -> 0 | BV10: =SUM(Tabla17[[#This Row],[ene-26]:[dic-26]]) -> 0 | BW10: =SUMIFS(Banco[Monto],Banco[CtaCtbl],$C10,Banco[Periodo Contable],TEXT(BW$3,"mmm-yyyy")) -> 0
A11: 1.02.02 | B11: Otras Multas | C11: =+Tabla17[[#This Row],[Cuenta]]&" - "&Tabla17[[#This Row],[Descripcion Cuenta]] -> 1.02.02 - Otras Multas | E11: =SUMIFS(Banco[Monto],Banco[CtaCtbl],$C11,Banco[Periodo Contable],TEXT(E$3,"mmm-yyyy")) -> 0 | F11: =SUMIFS(Banco[Monto],Banco[CtaCtbl],$C11,Banco[Periodo Contable],TEXT(F$3,"mmm-yyyy")) -> 0 | G11: =SUMIFS(Banco[Monto],Banco[CtaCtbl],$C11,Banco[Periodo Contable],TEXT(G$3,"mmm-yyyy")) -> 0 | H11: =SUMIFS(Banco[Monto],Banco[CtaCtbl],$C11,Banco[Periodo Contable],TEXT(H$3,"mmm-yyyy")) -> 0 | I11: =SUM(Tabla17[[#This Row],[sept-21]:[dic-21]]) -> 0 | J11: =SUMIFS(Banco[Monto],Banco[CtaCtbl],$C11,Banco[Periodo Contable],TEXT(J$3,"mmm-yyyy")) -> 0 | K11: =SUMIFS(Banco[Monto],Banco[CtaCtbl],$C11,Banco[Periodo Contable],TEXT(K$3,"mmm-yyyy")) -> 0 | L11: =SUMIFS(Banco[Monto],Banco[CtaCtbl],$C11,Banco[Periodo Contable],TEXT(L$3,"mmm-yyyy")) -> 0 | M11: =SUMIFS(Banco[Monto],Banco[CtaCtbl],$C11,Banco[Periodo Contable],TEXT(M$3,"mmm-yyyy")) -> 0 | N11: =SUMIFS(Banco[Monto],Banco[CtaCtbl],$C11,Banco[Periodo Contable],TEXT(N$3,"mmm-yyyy")) -> 0 | O11: =SUMIFS(Banco[Monto],Banco[CtaCtbl],$C11,Banco[Periodo Contable],TEXT(O$3,"mmm-yyyy")) -> 0 | P11: =SUMIFS(Banco[Monto],Banco[CtaCtbl],$C11,Banco[Periodo Contable],TEXT(P$3,"mmm-yyyy")) -> 0 | Q11: =SUMIFS(Banco[Monto],Banco[CtaCtbl],$C11,Banco[Periodo Contable],TEXT(Q$3,"mmm-yyyy")) -> 0 | ... U11: =SUMIFS(Banco[Monto],Banco[CtaCtbl],$C11,Banco[Periodo Contable],TEXT(U$3,"mmm-yyyy")) -> 0 | V11: =SUM(Tabla17[[#This Row],[ene-22]:[dic-22]]) -> 0 | W11: =SUMIFS(Banco[Monto],Banco[CtaCtbl],$C11,Banco[Periodo Contable],TEXT(W$3,"mmm-yyyy")) -> 0 | X11: =SUMIFS(Banco[Monto],Banco[CtaCtbl],$C11,Banco[Periodo Contable],TEXT(X$3,"mmm-yyyy")) -> 0 | Y11: =SUMIFS(Banco[Monto],Banco[CtaCtbl],$C11,Banco[Periodo Contable],TEXT(Y$3,"mmm-yyyy")) -> 0 | Z11: =SUMIFS(Banco[Monto],Banco[CtaCtbl],$C11,Banco[Periodo Contable],TEXT(Z$3,"mmm-yyyy")) -> 0 | AA11: =SUMIFS(Banco[Monto],Banco[CtaCtbl],$C11,Banco[Periodo Contable],TEXT(AA$3,"mmm-yyyy")) -> 0 | AB11: =SUMIFS(Banco[Monto],Banco[CtaCtbl],$C11,Banco[Periodo Contable],TEXT(AB$3,"mmm-yyyy")) -> 0 | AC11: =SUMIFS(Banco[Monto],Banco[CtaCtbl],$C11,Banco[Periodo Contable],TEXT(AC$3,"mmm-yyyy")) -> 0 | AD11: =SUMIFS(Banco[Monto],Banco[CtaCtbl],$C11,Banco[Periodo Contable],TEXT(AD$3,"mmm-yyyy")) -> 0 | ... AH11: =SUMIFS(Banco[Monto],Banco[CtaCtbl],$C11,Banco[Periodo Contable],TEXT(AH$3,"mmm-yyyy")) -> 0 | AI11: =SUM(Tabla17[[#This Row],[ene-23]:[dic-23]]) -> 0 | AJ11: =SUMIFS(Banco[Monto],Banco[CtaCtbl],$C11,Banco[Periodo Contable],TEXT(AJ$3,"mmm-yyyy")) -> 0 | AK11: =SUMIFS(Banco[Monto],Banco[CtaCtbl],$C11,Banco[Periodo Contable],TEXT(AK$3,"mmm-yyyy")) -> 0 | AL11: =SUMIFS(Banco[Monto],Banco[CtaCtbl],$C11,Banco[Periodo Contable],TEXT(AL$3,"mmm-yyyy")) -> 0 | AM11: =SUMIFS(Banco[Monto],Banco[CtaCtbl],$C11,Banco[Periodo Contable],TEXT(AM$3,"mmm-yyyy")) -> 0 | AN11: =SUMIFS(Banco[Monto],Banco[CtaCtbl],$C11,Banco[Periodo Contable],TEXT(AN$3,"mmm-yyyy")) -> 0 | AO11: =SUMIFS(Banco[Monto],Banco[CtaCtbl],$C11,Banco[Periodo Contable],TEXT(AO$3,"mmm-yyyy")) -> 0 | AP11: =SUMIFS(Banco[Monto],Banco[CtaCtbl],$C11,Banco[Periodo Contable],TEXT(AP$3,"mmm-yyyy")) -> 0 | AQ11: =SUMIFS(Banco[Monto],Banco[CtaCtbl],$C11,Banco[Periodo Contable],TEXT(AQ$3,"mmm-yyyy")) -> 0 | ... AU11: =SUMIFS(Banco[Monto],Banco[CtaCtbl],$C11,Banco[Periodo Contable],TEXT(AU$3,"mmm-yyyy")) -> 0 | AV11: =SUM(Tabla17[[#This Row],[ene-24]:[dic-24]]) -> 0 | AW11: =SUMIFS(Banco[Monto],Banco[CtaCtbl],$C11,Banco[Periodo Contable],TEXT(AW$3,"mmm-yyyy")) -> 0 | AX11: =SUMIFS(Banco[Monto],Banco[CtaCtbl],$C11,Banco[Periodo Contable],TEXT(AX$3,"mmm-yyyy")) -> 0 | AY11: =SUMIFS(Banco[Monto],Banco[CtaCtbl],$C11,Banco[Periodo Contable],TEXT(AY$3,"mmm-yyyy")) -> 0 | AZ11: =SUMIFS(Banco[Monto],Banco[CtaCtbl],$C11,Banco[Periodo Contable],TEXT(AZ$3,"mmm-yyyy")) -> 0 | BA11: =SUMIFS(Banco[Monto],Banco[CtaCtbl],$C11,Banco[Periodo Contable],TEXT(BA$3,"mmm-yyyy")) -> 0 | BB11: =SUMIFS(Banco[Monto],Banco[CtaCtbl],$C11,Banco[Periodo Contable],TEXT(BB$3,"mmm-yyyy")) -> 0 | BC11: =SUMIFS(Banco[Monto],Banco[CtaCtbl],$C11,Banco[Periodo Contable],TEXT(BC$3,"mmm-yyyy")) -> 0 | BD11: =SUMIFS(Banco[Monto],Banco[CtaCtbl],$C11,Banco[Periodo Contable],TEXT(BD$3,"mmm-yyyy")) -> 0 | ... BH11: =SUMIFS(Banco[Monto],Banco[CtaCtbl],$C11,Banco[Periodo Contable],TEXT(BH$3,"mmm-yyyy")) -> 0 | BI11: =SUM(Tabla17[[#This Row],[ene-25]:[dic-25]]) -> 0 | BJ11: =SUMIFS(Banco[Monto],Banco[CtaCtbl],$C11,Banco[Periodo Contable],TEXT(BJ$3,"mmm-yyyy")) -> 0 | BK11: =SUMIFS(Banco[Monto],Banco[CtaCtbl],$C11,Banco[Periodo Contable],TEXT(BK$3,"mmm-yyyy")) -> 0 | BL11: =SUMIFS(Banco[Monto],Banco[CtaCtbl],$C11,Banco[Periodo Contable],TEXT(BL$3,"mmm-yyyy")) -> 0 | BM11: =SUMIFS(Banco[Monto],Banco[CtaCtbl],$C11,Banco[Periodo Contable],TEXT(BM$3,"mmm-yyyy")) -> 0 | BN11: =SUMIFS(Banco[Monto],Banco[CtaCtbl],$C11,Banco[Periodo Contable],TEXT(BN$3,"mmm-yyyy")) -> 0 | BO11: =SUMIFS(Banco[Monto],Banco[CtaCtbl],$C11,Banco[Periodo Contable],TEXT(BO$3,"mmm-yyyy")) -> 0 | BP11: =SUMIFS(Banco[Monto],Banco[CtaCtbl],$C11,Banco[Periodo Contable],TEXT(BP$3,"mmm-yyyy")) -> 0 | BQ11: =SUMIFS(Banco[Monto],Banco[CtaCtbl],$C11,Banco[Periodo Contable],TEXT(BQ$3,"mmm-yyyy")) -> 0 | ... BU11: =SUMIFS(Banco[Monto],Banco[CtaCtbl],$C11,Banco[Periodo Contable],TEXT(BU$3,"mmm-yyyy")) -> 0 | BV11: =SUM(Tabla17[[#This Row],[ene-26]:[dic-26]]) -> 0 | BW11: =SUMIFS(Banco[Monto],Banco[CtaCtbl],$C11,Banco[Periodo Contable],TEXT(BW$3,"mmm-yyyy")) -> 0
A12: 1.03 | B12: Aportes Adicionales | C12: =+Tabla17[[#This Row],[Cuenta]]&" - "&Tabla17[[#This Row],[Descripcion Cuenta]] -> 1.03 - Aportes Adicionales | E12: =SUBTOTAL(9,E13:E16) -> 0 | F12: =SUBTOTAL(9,F13:F16) -> 0 | G12: =SUBTOTAL(9,G13:G16) -> 0 | H12: =SUBTOTAL(9,H13:H16) -> 0 | I12: =SUM(Tabla17[[#This Row],[sept-21]:[dic-21]]) -> 0 | J12: =SUBTOTAL(9,J13:J16) -> 0 | K12: =SUBTOTAL(9,K13:K16) -> 0 | L12: =SUBTOTAL(9,L13:L16) -> 0 | M12: =SUBTOTAL(9,M13:M16) -> 0 | N12: =SUBTOTAL(9,N13:N16) -> 107000000 | O12: =SUBTOTAL(9,O13:O16) -> 3000000 | P12: =SUBTOTAL(9,P13:P16) -> 0 | Q12: =SUBTOTAL(9,Q13:Q16) -> 0 | ... BW12: =SUBTOTAL(9,BW13:BW16) -> 0
A13: 1.03.01 | B13: Aportes Voluntarios | C13: =+Tabla17[[#This Row],[Cuenta]]&" - "&Tabla17[[#This Row],[Descripcion Cuenta]] -> 1.03.01 - Aportes Voluntarios | E13: =SUMIFS(Banco[Monto],Banco[CtaCtbl],$C13,Banco[Periodo Contable],TEXT(E$3,"mmm-yyyy")) -> 0 | F13: =SUMIFS(Banco[Monto],Banco[CtaCtbl],$C13,Banco[Periodo Contable],TEXT(F$3,"mmm-yyyy")) -> 0 | G13: =SUMIFS(Banco[Monto],Banco[CtaCtbl],$C13,Banco[Periodo Contable],TEXT(G$3,"mmm-yyyy")) -> 0 | H13: =SUMIFS(Banco[Monto],Banco[CtaCtbl],$C13,Banco[Periodo Contable],TEXT(H$3,"mmm-yyyy")) -> 0 | I13: =SUM(Tabla17[[#This Row],[sept-21]:[dic-21]]) -> 0 | J13: =SUMIFS(Banco[Monto],Banco[CtaCtbl],$C13,Banco[Periodo Contable],TEXT(J$3,"mmm-yyyy")) -> 0 | K13: =SUMIFS(Banco[Monto],Banco[CtaCtbl],$C13,Banco[Periodo Contable],TEXT(K$3,"mmm-yyyy")) -> 0 | L13: =SUMIFS(Banco[Monto],Banco[CtaCtbl],$C13,Banco[Periodo Contable],TEXT(L$3,"mmm-yyyy")) -> 0 | M13: =SUMIFS(Banco[Monto],Banco[CtaCtbl],$C13,Banco[Periodo Contable],TEXT(M$3,"mmm-yyyy")) -> 0 | N13: =SUMIFS(Banco[Monto],Banco[CtaCtbl],$C13,Banco[Periodo Contable],TEXT(N$3,"mmm-yyyy")) -> 0 | O13: =SUMIFS(Banco[Monto],Banco[CtaCtbl],$C13,Banco[Periodo Contable],TEXT(O$3,"mmm-yyyy")) -> 0 | P13: =SUMIFS(Banco[Monto],Banco[CtaCtbl],$C13,Banco[Periodo Contable],TEXT(P$3,"mmm-yyyy")) -> 0 | Q13: =SUMIFS(Banco[Monto],Banco[CtaCtbl],$C13,Banco[Periodo Contable],TEXT(Q$3,"mmm-yyyy")) -> 0 | ... U13: =SUMIFS(Banco[Monto],Banco[CtaCtbl],$C13,Banco[Periodo Contable],TEXT(U$3,"mmm-yyyy")) -> 0 | V13: =SUM(Tabla17[[#This Row],[ene-22]:[dic-22]]) -> 0 | W13: =SUMIFS(Banco[Monto],Banco[CtaCtbl],$C13,Banco[Periodo Contable],TEXT(W$3,"mmm-yyyy")) -> 0 | X13: =SUMIFS(Banco[Monto],Banco[CtaCtbl],$C13,Banco[Periodo Contable],TEXT(X$3,"mmm-yyyy")) -> 0 | Y13: =SUMIFS(Banco[Monto],Banco[CtaCtbl],$C13,Banco[Periodo Contable],TEXT(Y$3,"mmm-yyyy")) -> 0 | Z13: =SUMIFS(Banco[Monto],Banco[CtaCtbl],$C13,Banco[Periodo Contable],TEXT(Z$3,"mmm-yyyy")) -> 0 | AA13: =SUMIFS(Banco[Monto],Banco[CtaCtbl],$C13,Banco[Periodo Contable],TEXT(AA$3,"mmm-yyyy")) -> 0 | AB13: =SUMIFS(Banco[Monto],Banco[CtaCtbl],$C13,Banco[Periodo Contable],TEXT(AB$3,"mmm-yyyy")) -> 0 | AC13: =SUMIFS(Banco[Monto],Banco[CtaCtbl],$C13,Banco[Periodo Contable],TEXT(AC$3,"mmm-yyyy")) -> 0 | AD13: =SUMIFS(Banco[Monto],Banco[CtaCtbl],$C13,Banco[Periodo Contable],TEXT(AD$3,"mmm-yyyy")) -> 0 | ... AH13: =SUMIFS(Banco[Monto],Banco[CtaCtbl],$C13,Banco[Periodo Contable],TEXT(AH$3,"mmm-yyyy")) -> 0 | AI13: =SUM(Tabla17[[#This Row],[ene-23]:[dic-23]]) -> 0 | AJ13: =SUMIFS(Banco[Monto],Banco[CtaCtbl],$C13,Banco[Periodo Contable],TEXT(AJ$3,"mmm-yyyy")) -> 0 | AK13: =SUMIFS(Banco[Monto],Banco[CtaCtbl],$C13,Banco[Periodo Contable],TEXT(AK$3,"mmm-yyyy")) -> 0 | AL13: =SUMIFS(Banco[Monto],Banco[CtaCtbl],$C13,Banco[Periodo Contable],TEXT(AL$3,"mmm-yyyy")) -> 0 | AM13: =SUMIFS(Banco[Monto],Banco[CtaCtbl],$C13,Banco[Periodo Contable],TEXT(AM$3,"mmm-yyyy")) -> 0 | AN13: =SUMIFS(Banco[Monto],Banco[CtaCtbl],$C13,Banco[Periodo Contable],TEXT(AN$3,"mmm-yyyy")) -> 0 | AO13: =SUMIFS(Banco[Monto],Banco[CtaCtbl],$C13,Banco[Periodo Contable],TEXT(AO$3,"mmm-yyyy")) -> 0 | AP13: =SUMIFS(Banco[Monto],Banco[CtaCtbl],$C13,Banco[Periodo Contable],TEXT(AP$3,"mmm-yyyy")) -> 0 | AQ13: =SUMIFS(Banco[Monto],Banco[CtaCtbl],$C13,Banco[Periodo Contable],TEXT(AQ$3,"mmm-yyyy")) -> 0 | ... AU13: =SUMIFS(Banco[Monto],Banco[CtaCtbl],$C13,Banco[Periodo Contable],TEXT(AU$3,"mmm-yyyy")) -> 0 | AV13: =SUM(Tabla17[[#This Row],[ene-24]:[dic-24]]) -> 0 | AW13: =SUMIFS(Banco[Monto],Banco[CtaCtbl],$C13,Banco[Periodo Contable],TEXT(AW$3,"mmm-yyyy")) -> 0 | AX13: =SUMIFS(Banco[Monto],Banco[CtaCtbl],$C13,Banco[Periodo Contable],TEXT(AX$3,"mmm-yyyy")) -> 0 | AY13: =SUMIFS(Banco[Monto],Banco[CtaCtbl],$C13,Banco[Periodo Contable],TEXT(AY$3,"mmm-yyyy")) -> 0 | AZ13: =SUMIFS(Banco[Monto],Banco[CtaCtbl],$C13,Banco[Periodo Contable],TEXT(AZ$3,"mmm-yyyy")) -> 0 | BA13: =SUMIFS(Banco[Monto],Banco[CtaCtbl],$C13,Banco[Periodo Contable],TEXT(BA$3,"mmm-yyyy")) -> 0 | BB13: =SUMIFS(Banco[Monto],Banco[CtaCtbl],$C13,Banco[Periodo Contable],TEXT(BB$3,"mmm-yyyy")) -> 0 | BC13: =SUMIFS(Banco[Monto],Banco[CtaCtbl],$C13,Banco[Periodo Contable],TEXT(BC$3,"mmm-yyyy")) -> 0 | BD13: =SUMIFS(Banco[Monto],Banco[CtaCtbl],$C13,Banco[Periodo Contable],TEXT(BD$3,"mmm-yyyy")) -> 0 | ... BH13: =SUMIFS(Banco[Monto],Banco[CtaCtbl],$C13,Banco[Periodo Contable],TEXT(BH$3,"mmm-yyyy")) -> 0 | BI13: =SUM(Tabla17[[#This Row],[ene-25]:[dic-25]]) -> 0 | BJ13: =SUMIFS(Banco[Monto],Banco[CtaCtbl],$C13,Banco[Periodo Contable],TEXT(BJ$3,"mmm-yyyy")) -> 0 | BK13: =SUMIFS(Banco[Monto],Banco[CtaCtbl],$C13,Banco[Periodo Contable],TEXT(BK$3,"mmm-yyyy")) -> 0 | BL13: =SUMIFS(Banco[Monto],Banco[CtaCtbl],$C13,Banco[Periodo Contable],TEXT(BL$3,"mmm-yyyy")) -> 0 | BM13: =SUMIFS(Banco[Monto],Banco[CtaCtbl],$C13,Banco[Periodo Contable],TEXT(BM$3,"mmm-yyyy")) -> 0 | BN13: =SUMIFS(Banco[Monto],Banco[CtaCtbl],$C13,Banco[Periodo Contable],TEXT(BN$3,"mmm-yyyy")) -> 0 | BO13: =SUMIFS(Banco[Monto],Banco[CtaCtbl],$C13,Banco[Periodo Contable],TEXT(BO$3,"mmm-yyyy")) -> 0 | BP13: =SUMIFS(Banco[Monto],Banco[CtaCtbl],$C13,Banco[Periodo Contable],TEXT(BP$3,"mmm-yyyy")) -> 0 | BQ13: =SUMIFS(Banco[Monto],Banco[CtaCtbl],$C13,Banco[Periodo Contable],TEXT(BQ$3,"mmm-yyyy")) -> 0 | ... BU13: =SUMIFS(Banco[Monto],Banco[CtaCtbl],$C13,Banco[Periodo Contable],TEXT(BU$3,"mmm-yyyy")) -> 0 | BV13: =SUM(Tabla17[[#This Row],[ene-26]:[dic-26]]) -> 0 | BW13: =SUMIFS(Banco[Monto],Banco[CtaCtbl],$C13,Banco[Periodo Contable],TEXT(BW$3,"mmm-yyyy")) -> 0
A14: 1.03.02 | B14: Aportes Terceros | C14: =+Tabla17[[#This Row],[Cuenta]]&" - "&Tabla17[[#This Row],[Descripcion Cuenta]] -> 1.03.02 - Aportes Terceros | E14: =SUMIFS(Banco[Monto],Banco[CtaCtbl],$C14,Banco[Periodo Contable],TEXT(E$3,"mmm-yyyy")) -> 0 | F14: =SUMIFS(Banco[Monto],Banco[CtaCtbl],$C14,Banco[Periodo Contable],TEXT(F$3,"mmm-yyyy")) -> 0 | G14: =SUMIFS(Banco[Monto],Banco[CtaCtbl],$C14,Banco[Periodo Contable],TEXT(G$3,"mmm-yyyy")) -> 0 | H14: =SUMIFS(Banco[Monto],Banco[CtaCtbl],$C14,Banco[Periodo Contable],TEXT(H$3,"mmm-yyyy")) -> 0 | I14: =SUM(Tabla17[[#This Row],[sept-21]:[dic-21]]) -> 0 | J14: =SUMIFS(Banco[Monto],Banco[CtaCtbl],$C14,Banco[Periodo Contable],TEXT(J$3,"mmm-yyyy")) -> 0 | K14: =SUMIFS(Banco[Monto],Banco[CtaCtbl],$C14,Banco[Periodo Contable],TEXT(K$3,"mmm-yyyy")) -> 0 | L14: =SUMIFS(Banco[Monto],Banco[CtaCtbl],$C14,Banco[Periodo Contable],TEXT(L$3,"mmm-yyyy")) -> 0 | M14: =SUMIFS(Banco[Monto],Banco[CtaCtbl],$C14,Banco[Periodo Contable],TEXT(M$3,"mmm-yyyy")) -> 0 | N14: =SUMIFS(Banco[Monto],Banco[CtaCtbl],$C14,Banco[Periodo Contable],TEXT(N$3,"mmm-yyyy")) -> 0 | O14: =SUMIFS(Banco[Monto],Banco[CtaCtbl],$C14,Banco[Periodo Contable],TEXT(O$3,"mmm-yyyy")) -> 0 | P14: =SUMIFS(Banco[Monto],Banco[CtaCtbl],$C14,Banco[Periodo Contable],TEXT(P$3,"mmm-yyyy")) -> 0 | Q14: =SUMIFS(Banco[Monto],Banco[CtaCtbl],$C14,Banco[Periodo Contable],TEXT(Q$3,"mmm-yyyy")) -> 0 | ... U14: =SUMIFS(Banco[Monto],Banco[CtaCtbl],$C14,Banco[Periodo Contable],TEXT(U$3,"mmm-yyyy")) -> 0 | V14: =SUM(Tabla17[[#This Row],[ene-22]:[dic-22]]) -> 0 | W14: =SUMIFS(Banco[Monto],Banco[CtaCtbl],$C14,Banco[Periodo Contable],TEXT(W$3,"mmm-yyyy")) -> 0 | X14: =SUMIFS(Banco[Monto],Banco[CtaCtbl],$C14,Banco[Periodo Contable],TEXT(X$3,"mmm-yyyy")) -> 0 | Y14: =SUMIFS(Banco[Monto],Banco[CtaCtbl],$C14,Banco[Periodo Contable],TEXT(Y$3,"mmm-yyyy")) -> 0 | Z14: =SUMIFS(Banco[Monto],Banco[CtaCtbl],$C14,Banco[Periodo Contable],TEXT(Z$3,"mmm-yyyy")) -> 0 | AA14: =SUMIFS(Banco[Monto],Banco[CtaCtbl],$C14,Banco[Periodo Contable],TEXT(AA$3,"mmm-yyyy")) -> 0 | AB14: =SUMIFS(Banco[Monto],Banco[CtaCtbl],$C14,Banco[Periodo Contable],TEXT(AB$3,"mmm-yyyy")) -> 0 | AC14: =SUMIFS(Banco[Monto],Banco[CtaCtbl],$C14,Banco[Periodo Contable],TEXT(AC$3,"mmm-yyyy")) -> 0 | AD14: =SUMIFS(Banco[Monto],Banco[CtaCtbl],$C14,Banco[Periodo Contable],TEXT(AD$3,"mmm-yyyy")) -> 0 | ... AH14: =SUMIFS(Banco[Monto],Banco[CtaCtbl],$C14,Banco[Periodo Contable],TEXT(AH$3,"mmm-yyyy")) -> 0 | AI14: =SUM(Tabla17[[#This Row],[ene-23]:[dic-23]]) -> 0 | AJ14: =SUMIFS(Banco[Monto],Banco[CtaCtbl],$C14,Banco[Periodo Contable],TEXT(AJ$3,"mmm-yyyy")) -> 0 | AK14: =SUMIFS(Banco[Monto],Banco[CtaCtbl],$C14,Banco[Periodo Contable],TEXT(AK$3,"mmm-yyyy")) -> 0 | AL14: =SUMIFS(Banco[Monto],Banco[CtaCtbl],$C14,Banco[Periodo Contable],TEXT(AL$3,"mmm-yyyy")) -> 0 | AM14: =SUMIFS(Banco[Monto],Banco[CtaCtbl],$C14,Banco[Periodo Contable],TEXT(AM$3,"mmm-yyyy")) -> 0 | AN14: =SUMIFS(Banco[Monto],Banco[CtaCtbl],$C14,Banco[Periodo Contable],TEXT(AN$3,"mmm-yyyy")) -> 0 | AO14: =SUMIFS(Banco[Monto],Banco[CtaCtbl],$C14,Banco[Periodo Contable],TEXT(AO$3,"mmm-yyyy")) -> 0 | AP14: =SUMIFS(Banco[Monto],Banco[CtaCtbl],$C14,Banco[Periodo Contable],TEXT(AP$3,"mmm-yyyy")) -> 0 | AQ14: =SUMIFS(Banco[Monto],Banco[CtaCtbl],$C14,Banco[Periodo Contable],TEXT(AQ$3,"mmm-yyyy")) -> 0 | ... AU14: =SUMIFS(Banco[Monto],Banco[CtaCtbl],$C14,Banco[Periodo Contable],TEXT(AU$3,"mmm-yyyy")) -> 0 | AV14: =SUM(Tabla17[[#This Row],[ene-24]:[dic-24]]) -> 0 | AW14: =SUMIFS(Banco[Monto],Banco[CtaCtbl],$C14,Banco[Periodo Contable],TEXT(AW$3,"mmm-yyyy")) -> 0 | AX14: =SUMIFS(Banco[Monto],Banco[CtaCtbl],$C14,Banco[Periodo Contable],TEXT(AX$3,"mmm-yyyy")) -> 0 | AY14: =SUMIFS(Banco[Monto],Banco[CtaCtbl],$C14,Banco[Periodo Contable],TEXT(AY$3,"mmm-yyyy")) -> 0 | AZ14: =SUMIFS(Banco[Monto],Banco[CtaCtbl],$C14,Banco[Periodo Contable],TEXT(AZ$3,"mmm-yyyy")) -> 0 | BA14: =SUMIFS(Banco[Monto],Banco[CtaCtbl],$C14,Banco[Periodo Contable],TEXT(BA$3,"mmm-yyyy")) -> 0 | BB14: =SUMIFS(Banco[Monto],Banco[CtaCtbl],$C14,Banco[Periodo Contable],TEXT(BB$3,"mmm-yyyy")) -> 0 | BC14: =SUMIFS(Banco[Monto],Banco[CtaCtbl],$C14,Banco[Periodo Contable],TEXT(BC$3,"mmm-yyyy")) -> 0 | BD14: =SUMIFS(Banco[Monto],Banco[CtaCtbl],$C14,Banco[Periodo Contable],TEXT(BD$3,"mmm-yyyy")) -> 0 | ... BH14: =SUMIFS(Banco[Monto],Banco[CtaCtbl],$C14,Banco[Periodo Contable],TEXT(BH$3,"mmm-yyyy")) -> 0 | BI14: =SUM(Tabla17[[#This Row],[ene-25]:[dic-25]]) -> 0 | BJ14: =SUMIFS(Banco[Monto],Banco[CtaCtbl],$C14,Banco[Periodo Contable],TEXT(BJ$3,"mmm-yyyy")) -> 0 | BK14: =SUMIFS(Banco[Monto],Banco[CtaCtbl],$C14,Banco[Periodo Contable],TEXT(BK$3,"mmm-yyyy")) -> 0 | BL14: =SUMIFS(Banco[Monto],Banco[CtaCtbl],$C14,Banco[Periodo Contable],TEXT(BL$3,"mmm-yyyy")) -> 0 | BM14: =SUMIFS(Banco[Monto],Banco[CtaCtbl],$C14,Banco[Periodo Contable],TEXT(BM$3,"mmm-yyyy")) -> 0 | BN14: =SUMIFS(Banco[Monto],Banco[CtaCtbl],$C14,Banco[Periodo Contable],TEXT(BN$3,"mmm-yyyy")) -> 0 | BO14: =SUMIFS(Banco[Monto],Banco[CtaCtbl],$C14,Banco[Periodo Contable],TEXT(BO$3,"mmm-yyyy")) -> 0 | BP14: =SUMIFS(Banco[Monto],Banco[CtaCtbl],$C14,Banco[Periodo Contable],TEXT(BP$3,"mmm-yyyy")) -> 0 | BQ14: =SUMIFS(Banco[Monto],Banco[CtaCtbl],$C14,Banco[Periodo Contable],TEXT(BQ$3,"mmm-yyyy")) -> 0 | ... BU14: =SUMIFS(Banco[Monto],Banco[CtaCtbl],$C14,Banco[Periodo Contable],TEXT(BU$3,"mmm-yyyy")) -> 0 | BV14: =SUM(Tabla17[[#This Row],[ene-26]:[dic-26]]) -> 0 | BW14: =SUMIFS(Banco[Monto],Banco[CtaCtbl],$C14,Banco[Periodo Contable],TEXT(BW$3,"mmm-yyyy")) -> 0
A15: 1.03.03 | B15: Otros Aportes | C15: =+Tabla17[[#This Row],[Cuenta]]&" - "&Tabla17[[#This Row],[Descripcion Cuenta]] -> 1.03.03 - Otros Aportes | E15: =SUMIFS(Banco[Monto],Banco[CtaCtbl],$C15,Banco[Periodo Contable],TEXT(E$3,"mmm-yyyy")) -> 0 | F15: =SUMIFS(Banco[Monto],Banco[CtaCtbl],$C15,Banco[Periodo Contable],TEXT(F$3,"mmm-yyyy")) -> 0 | G15: =SUMIFS(Banco[Monto],Banco[CtaCtbl],$C15,Banco[Periodo Contable],TEXT(G$3,"mmm-yyyy")) -> 0 | H15: =SUMIFS(Banco[Monto],Banco[CtaCtbl],$C15,Banco[Periodo Contable],TEXT(H$3,"mmm-yyyy")) -> 0 | I15: =SUM(Tabla17[[#This Row],[sept-21]:[dic-21]]) -> 0 | J15: =SUMIFS(Banco[Monto],Banco[CtaCtbl],$C15,Banco[Periodo Contable],TEXT(J$3,"mmm-yyyy")) -> 0 | K15: =SUMIFS(Banco[Monto],Banco[CtaCtbl],$C15,Banco[Periodo Contable],TEXT(K$3,"mmm-yyyy")) -> 0 | L15: =SUMIFS(Banco[Monto],Banco[CtaCtbl],$C15,Banco[Periodo Contable],TEXT(L$3,"mmm-yyyy")) -> 0 | M15: =SUMIFS(Banco[Monto],Banco[CtaCtbl],$C15,Banco[Periodo Contable],TEXT(M$3,"mmm-yyyy")) -> 0 | N15: =SUMIFS(Banco[Monto],Banco[CtaCtbl],$C15,Banco[Periodo Contable],TEXT(N$3,"mmm-yyyy")) -> 0 | O15: =SUMIFS(Banco[Monto],Banco[CtaCtbl],$C15,Banco[Periodo Contable],TEXT(O$3,"mmm-yyyy")) -> 3000000 | P15: =SUMIFS(Banco[Monto],Banco[CtaCtbl],$C15,Banco[Periodo Contable],TEXT(P$3,"mmm-yyyy")) -> 0 | Q15: =SUMIFS(Banco[Monto],Banco[CtaCtbl],$C15,Banco[Periodo Contable],TEXT(Q$3,"mmm-yyyy")) -> 0 | ... U15: =SUMIFS(Banco[Monto],Banco[CtaCtbl],$C15,Banco[Periodo Contable],TEXT(U$3,"mmm-yyyy")) -> 138362 | V15: =SUM(Tabla17[[#This Row],[ene-22]:[dic-22]]) -> 3138362 | W15: =SUMIFS(Banco[Monto],Banco[CtaCtbl],$C15,Banco[Periodo Contable],TEXT(W$3,"mmm-yyyy")) -> 0 | X15: =SUMIFS(Banco[Monto],Banco[CtaCtbl],$C15,Banco[Periodo Contable],TEXT(X$3,"mmm-yyyy")) -> 0 | Y15: =SUMIFS(Banco[Monto],Banco[CtaCtbl],$C15,Banco[Periodo Contable],TEXT(Y$3,"mmm-yyyy")) -> 0 | Z15: =SUMIFS(Banco[Monto],Banco[CtaCtbl],$C15,Banco[Periodo Contable],TEXT(Z$3,"mmm-yyyy")) -> 0 | AA15: =SUMIFS(Banco[Monto],Banco[CtaCtbl],$C15,Banco[Periodo Contable],TEXT(AA$3,"mmm-yyyy")) -> 0 | AB15: =SUMIFS(Banco[Monto],Banco[CtaCtbl],$C15,Banco[Periodo Contable],TEXT(AB$3,"mmm-yyyy")) -> 0 | AC15: =SUMIFS(Banco[Monto],Banco[CtaCtbl],$C15,Banco[Periodo Contable],TEXT(AC$3,"mmm-yyyy")) -> 0 | AD15: =SUMIFS(Banco[Monto],Banco[CtaCtbl],$C15,Banco[Periodo Contable],TEXT(AD$3,"mmm-yyyy")) -> 0 | ... AH15: =SUMIFS(Banco[Monto],Banco[CtaCtbl],$C15,Banco[Periodo Contable],TEXT(AH$3,"mmm-yyyy")) -> 0 | AI15: =SUM(Tabla17[[#This Row],[ene-23]:[dic-23]]) -> 0 | AJ15: =SUMIFS(Banco[Monto],Banco[CtaCtbl],$C15,Banco[Periodo Contable],TEXT(AJ$3,"mmm-yyyy")) -> 0 | AK15: =SUMIFS(Banco[Monto],Banco[CtaCtbl],$C15,Banco[Periodo Contable],TEXT(AK$3,"mmm-yyyy")) -> 0 | AL15: =SUMIFS(Banco[Monto],Banco[CtaCtbl],$C15,Banco[Periodo Contable],TEXT(AL$3,"mmm-yyyy")) -> 0 | AM15: =SUMIFS(Banco[Monto],Banco[CtaCtbl],$C15,Banco[Periodo Contable],TEXT(AM$3,"mmm-yyyy")) -> 0 | AN15: =SUMIFS(Banco[Monto],Banco[CtaCtbl],$C15,Banco[Periodo Contable],TEXT(AN$3,"mmm-yyyy")) -> 0 | AO15: =SUMIFS(Banco[Monto],Banco[CtaCtbl],$C15,Banco[Periodo Contable],TEXT(AO$3,"mmm-yyyy")) -> 0 | AP15: =SUMIFS(Banco[Monto],Banco[CtaCtbl],$C15,Banco[Periodo Contable],TEXT(AP$3,"mmm-yyyy")) -> 0 | AQ15: =SUMIFS(Banco[Monto],Banco[CtaCtbl],$C15,Banco[Periodo Contable],TEXT(AQ$3,"mmm-yyyy")) -> 0 | ... AU15: =SUMIFS(Banco[Monto],Banco[CtaCtbl],$C15,Banco[Periodo Contable],TEXT(AU$3,"mmm-yyyy")) -> 0 | AV15: =SUM(Tabla17[[#This Row],[ene-24]:[dic-24]]) -> 0 | AW15: =SUMIFS(Banco[Monto],Banco[CtaCtbl],$C15,Banco[Periodo Contable],TEXT(AW$3,"mmm-yyyy")) -> 0 | AX15: =SUMIFS(Banco[Monto],Banco[CtaCtbl],$C15,Banco[Periodo Contable],TEXT(AX$3,"mmm-yyyy")) -> 0 | AY15: =SUMIFS(Banco[Monto],Banco[CtaCtbl],$C15,Banco[Periodo Contable],TEXT(AY$3,"mmm-yyyy")) -> 0 | AZ15: =SUMIFS(Banco[Monto],Banco[CtaCtbl],$C15,Banco[Periodo Contable],TEXT(AZ$3,"mmm-yyyy")) -> 0 | BA15: =SUMIFS(Banco[Monto],Banco[CtaCtbl],$C15,Banco[Periodo Contable],TEXT(BA$3,"mmm-yyyy")) -> 0 | BB15: =SUMIFS(Banco[Monto],Banco[CtaCtbl],$C15,Banco[Periodo Contable],TEXT(BB$3,"mmm-yyyy")) -> 0 | BC15: =SUMIFS(Banco[Monto],Banco[CtaCtbl],$C15,Banco[Periodo Contable],TEXT(BC$3,"mmm-yyyy")) -> 0 | BD15: =SUMIFS(Banco[Monto],Banco[CtaCtbl],$C15,Banco[Periodo Contable],TEXT(BD$3,"mmm-yyyy")) -> 0 | ... BH15: =SUMIFS(Banco[Monto],Banco[CtaCtbl],$C15,Banco[Periodo Contable],TEXT(BH$3,"mmm-yyyy")) -> 0 | BI15: =SUM(Tabla17[[#This Row],[ene-25]:[dic-25]]) -> 0 | BJ15: =SUMIFS(Banco[Monto],Banco[CtaCtbl],$C15,Banco[Periodo Contable],TEXT(BJ$3,"mmm-yyyy")) -> 0 | BK15: =SUMIFS(Banco[Monto],Banco[CtaCtbl],$C15,Banco[Periodo Contable],TEXT(BK$3,"mmm-yyyy")) -> 0 | BL15: =SUMIFS(Banco[Monto],Banco[CtaCtbl],$C15,Banco[Periodo Contable],TEXT(BL$3,"mmm-yyyy")) -> 0 | BM15: =SUMIFS(Banco[Monto],Banco[CtaCtbl],$C15,Banco[Periodo Contable],TEXT(BM$3,"mmm-yyyy")) -> 0 | BN15: =SUMIFS(Banco[Monto],Banco[CtaCtbl],$C15,Banco[Periodo Contable],TEXT(BN$3,"mmm-yyyy")) -> 0 | BO15: =SUMIFS(Banco[Monto],Banco[CtaCtbl],$C15,Banco[Periodo Contable],TEXT(BO$3,"mmm-yyyy")) -> 0 | BP15: =SUMIFS(Banco[Monto],Banco[CtaCtbl],$C15,Banco[Periodo Contable],TEXT(BP$3,"mmm-yyyy")) -> 0 | BQ15: =SUMIFS(Banco[Monto],Banco[CtaCtbl],$C15,Banco[Periodo Contable],TEXT(BQ$3,"mmm-yyyy")) -> 0 | ... BU15: =SUMIFS(Banco[Monto],Banco[CtaCtbl],$C15,Banco[Periodo Contable],TEXT(BU$3,"mmm-yyyy")) -> 0 | BV15: =SUM(Tabla17[[#This Row],[ene-26]:[dic-26]]) -> 0 | BW15: =SUMIFS(Banco[Monto],Banco[CtaCtbl],$C15,Banco[Periodo Contable],TEXT(BW$3,"mmm-yyyy")) -> 0
A16: 1.03.04 | B16: Aporte Colbun | C16: =+Tabla17[[#This Row],[Cuenta]]&" - "&Tabla17[[#This Row],[Descripcion Cuenta]] -> 1.03.04 - Aporte Colbun | E16: =SUMIFS(Banco[Monto],Banco[CtaCtbl],$C16,Banco[Periodo Contable],TEXT(E$3,"mmm-yyyy")) -> 0 | F16: =SUMIFS(Banco[Monto],Banco[CtaCtbl],$C16,Banco[Periodo Contable],TEXT(F$3,"mmm-yyyy")) -> 0 | G16: =SUMIFS(Banco[Monto],Banco[CtaCtbl],$C16,Banco[Periodo Contable],TEXT(G$3,"mmm-yyyy")) -> 0 | H16: =SUMIFS(Banco[Monto],Banco[CtaCtbl],$C16,Banco[Periodo Contable],TEXT(H$3,"mmm-yyyy")) -> 0 | I16: =SUM(Tabla17[[#This Row],[sept-21]:[dic-21]]) -> 0 | J16: =SUMIFS(Banco[Monto],Banco[CtaCtbl],$C16,Banco[Periodo Contable],TEXT(J$3,"mmm-yyyy")) -> 0 | K16: =SUMIFS(Banco[Monto],Banco[CtaCtbl],$C16,Banco[Periodo Contable],TEXT(K$3,"mmm-yyyy")) -> 0 | L16: =SUMIFS(Banco[Monto],Banco[CtaCtbl],$C16,Banco[Periodo Contable],TEXT(L$3,"mmm-yyyy")) -> 0 | M16: =SUMIFS(Banco[Monto],Banco[CtaCtbl],$C16,Banco[Periodo Contable],TEXT(M$3,"mmm-yyyy")) -> 0 | N16: =SUMIFS(Banco[Monto],Banco[CtaCtbl],$C16,Banco[Periodo Contable],TEXT(N$3,"mmm-yyyy")) -> 107000000 | O16: =SUMIFS(Banco[Monto],Banco[CtaCtbl],$C16,Banco[Periodo Contable],TEXT(O$3,"mmm-yyyy")) -> 0 | P16: =SUMIFS(Banco[Monto],Banco[CtaCtbl],$C16,Banco[Periodo Contable],TEXT(P$3,"mmm-yyyy")) -> 0 | Q16: =SUMIFS(Banco[Monto],Banco[CtaCtbl],$C16,Banco[Periodo Contable],TEXT(Q$3,"mmm-yyyy")) -> 0 | ... U16: =SUMIFS(Banco[Monto],Banco[CtaCtbl],$C16,Banco[Periodo Contable],TEXT(U$3,"mmm-yyyy")) -> 0 | V16: =SUM(Tabla17[[#This Row],[ene-22]:[dic-22]]) -> 107000000 | W16: =SUMIFS(Banco[Monto],Banco[CtaCtbl],$C16,Banco[Periodo Contable],TEXT(W$3,"mmm-yyyy")) -> 0 | X16: =SUMIFS(Banco[Monto],Banco[CtaCtbl],$C16,Banco[Periodo Contable],TEXT(X$3,"mmm-yyyy")) -> 0 | Y16: =SUMIFS(Banco[Monto],Banco[CtaCtbl],$C16,Banco[Periodo Contable],TEXT(Y$3,"mmm-yyyy")) -> 0 | Z16: =SUMIFS(Banco[Monto],Banco[CtaCtbl],$C16,Banco[Periodo Contable],TEXT(Z$3,"mmm-yyyy")) -> 0 | AA16: =SUMIFS(Banco[Monto],Banco[CtaCtbl],$C16,Banco[Periodo Contable],TEXT(AA$3,"mmm-yyyy")) -> 0 | AB16: =SUMIFS(Banco[Monto],Banco[CtaCtbl],$C16,Banco[Periodo Contable],TEXT(AB$3,"mmm-yyyy")) -> 0 | AC16: =SUMIFS(Banco[Monto],Banco[CtaCtbl],$C16,Banco[Periodo Contable],TEXT(AC$3,"mmm-yyyy")) -> 0 | AD16: =SUMIFS(Banco[Monto],Banco[CtaCtbl],$C16,Banco[Periodo Contable],TEXT(AD$3,"mmm-yyyy")) -> 0 | ... AH16: =SUMIFS(Banco[Monto],Banco[CtaCtbl],$C16,Banco[Periodo Contable],TEXT(AH$3,"mmm-yyyy")) -> 0 | AI16: =SUM(Tabla17[[#This Row],[ene-23]:[dic-23]]) -> 0 | AJ16: =SUMIFS(Banco[Monto],Banco[CtaCtbl],$C16,Banco[Periodo Contable],TEXT(AJ$3,"mmm-yyyy")) -> 0 | AK16: =SUMIFS(Banco[Monto],Banco[CtaCtbl],$C16,Banco[Periodo Contable],TEXT(AK$3,"mmm-yyyy")) -> 0 | AL16: =SUMIFS(Banco[Monto],Banco[CtaCtbl],$C16,Banco[Periodo Contable],TEXT(AL$3,"mmm-yyyy")) -> 0 | AM16: =SUMIFS(Banco[Monto],Banco[CtaCtbl],$C16,Banco[Periodo Contable],TEXT(AM$3,"mmm-yyyy")) -> 0 | AN16: =SUMIFS(Banco[Monto],Banco[CtaCtbl],$C16,Banco[Periodo Contable],TEXT(AN$3,"mmm-yyyy")) -> 0 | AO16: =SUMIFS(Banco[Monto],Banco[CtaCtbl],$C16,Banco[Periodo Contable],TEXT(AO$3,"mmm-yyyy")) -> 0 | AP16: =SUMIFS(Banco[Monto],Banco[CtaCtbl],$C16,Banco[Periodo Contable],TEXT(AP$3,"mmm-yyyy")) -> 0 | AQ16: =SUMIFS(Banco[Monto],Banco[CtaCtbl],$C16,Banco[Periodo Contable],TEXT(AQ$3,"mmm-yyyy")) -> 0 | ... AU16: =SUMIFS(Banco[Monto],Banco[CtaCtbl],$C16,Banco[Periodo Contable],TEXT(AU$3,"mmm-yyyy")) -> 0 | AV16: =SUM(Tabla17[[#This Row],[ene-24]:[dic-24]]) -> 0 | AW16: =SUMIFS(Banco[Monto],Banco[CtaCtbl],$C16,Banco[Periodo Contable],TEXT(AW$3,"mmm-yyyy")) -> 0 | AX16: =SUMIFS(Banco[Monto],Banco[CtaCtbl],$C16,Banco[Periodo Contable],TEXT(AX$3,"mmm-yyyy")) -> 0 | AY16: =SUMIFS(Banco[Monto],Banco[CtaCtbl],$C16,Banco[Periodo Contable],TEXT(AY$3,"mmm-yyyy")) -> 0 | AZ16: =SUMIFS(Banco[Monto],Banco[CtaCtbl],$C16,Banco[Periodo Contable],TEXT(AZ$3,"mmm-yyyy")) -> 2334248 | BA16: =SUMIFS(Banco[Monto],Banco[CtaCtbl],$C16,Banco[Periodo Contable],TEXT(BA$3,"mmm-yyyy")) -> 478000000 | BB16: =SUMIFS(Banco[Monto],Banco[CtaCtbl],$C16,Banco[Periodo Contable],TEXT(BB$3,"mmm-yyyy")) -> 0 | BC16: =SUMIFS(Banco[Monto],Banco[CtaCtbl],$C16,Banco[Periodo Contable],TEXT(BC$3,"mmm-yyyy")) -> 0 | BD16: =SUMIFS(Banco[Monto],Banco[CtaCtbl],$C16,Banco[Periodo Contable],TEXT(BD$3,"mmm-yyyy")) -> 0 | ... BH16: =SUMIFS(Banco[Monto],Banco[CtaCtbl],$C16,Banco[Periodo Contable],TEXT(BH$3,"mmm-yyyy")) -> 0 | BI16: =SUM(Tabla17[[#This Row],[ene-25]:[dic-25]]) -> 480334248 | BJ16: =SUMIFS(Banco[Monto],Banco[CtaCtbl],$C16,Banco[Periodo Contable],TEXT(BJ$3,"mmm-yyyy")) -> 0 | BK16: =SUMIFS(Banco[Monto],Banco[CtaCtbl],$C16,Banco[Periodo Contable],TEXT(BK$3,"mmm-yyyy")) -> 0 | BL16: =SUMIFS(Banco[Monto],Banco[CtaCtbl],$C16,Banco[Periodo Contable],TEXT(BL$3,"mmm-yyyy")) -> 0 | BM16: =SUMIFS(Banco[Monto],Banco[CtaCtbl],$C16,Banco[Periodo Contable],TEXT(BM$3,"mmm-yyyy")) -> 0 | BN16: =SUMIFS(Banco[Monto],Banco[CtaCtbl],$C16,Banco[Periodo Contable],TEXT(BN$3,"mmm-yyyy")) -> 0 | BO16: =SUMIFS(Banco[Monto],Banco[CtaCtbl],$C16,Banco[Periodo Contable],TEXT(BO$3,"mmm-yyyy")) -> 0 | BP16: =SUMIFS(Banco[Monto],Banco[CtaCtbl],$C16,Banco[Periodo Contable],TEXT(BP$3,"mmm-yyyy")) -> 0 | BQ16: =SUMIFS(Banco[Monto],Banco[CtaCtbl],$C16,Banco[Periodo Contable],TEXT(BQ$3,"mmm-yyyy")) -> 0 | ... BU16: =SUMIFS(Banco[Monto],Banco[CtaCtbl],$C16,Banco[Periodo Contable],TEXT(BU$3,"mmm-yyyy")) -> 0 | BV16: =SUM(Tabla17[[#This Row],[ene-26]:[dic-26]]) -> 0 | BW16: =SUMIFS(Banco[Monto],Banco[CtaCtbl],$C16,Banco[Periodo Contable],TEXT(BW$3,"mmm-yyyy")) -> 0
A17: 1.04 | B17: Utilidades Bancarias / Otros Banco | C17: =+Tabla17[[#This Row],[Cuenta]]&" - "&Tabla17[[#This Row],[Descripcion Cuenta]] -> 1.04 - Utilidades Bancarias / Otros Banco | E17: =SUBTOTAL(9,E18:E24) -> 0 | F17: =SUBTOTAL(9,F18:F24) -> 0 | G17: =SUBTOTAL(9,G18:G24) -> 0 | H17: =SUBTOTAL(9,H18:H24) -> 0 | I17: =SUM(Tabla17[[#This Row],[sept-21]:[dic-21]]) -> 0 | J17: =SUBTOTAL(9,J18:J24) -> 0 | K17: =SUBTOTAL(9,K18:K24) -> 0 | L17: =SUBTOTAL(9,L18:L24) -> 0 | M17: =SUBTOTAL(9,M18:M24) -> 0 | N17: =SUBTOTAL(9,N18:N24) -> 0 | O17: =SUBTOTAL(9,O18:O24) -> 0 | P17: =SUBTOTAL(9,P18:P24) -> 0 | Q17: =SUBTOTAL(9,Q18:Q24) -> 0 | ... BW17: =SUBTOTAL(9,BW18:BW24) -> 0
A18: 1.04.01 | B18: Utilidades Plazo Fijo | C18: =+Tabla17[[#This Row],[Cuenta]]&" - "&Tabla17[[#This Row],[Descripcion Cuenta]] -> 1.04.01 - Utilidades Plazo Fijo | E18: =SUMIFS(Banco[Monto],Banco[CtaCtbl],$C18,Banco[Periodo Contable],TEXT(E$3,"mmm-yyyy")) -> 0 | F18: =SUMIFS(Banco[Monto],Banco[CtaCtbl],$C18,Banco[Periodo Contable],TEXT(F$3,"mmm-yyyy")) -> 0 | G18: =SUMIFS(Banco[Monto],Banco[CtaCtbl],$C18,Banco[Periodo Contable],TEXT(G$3,"mmm-yyyy")) -> 0 | H18: =SUMIFS(Banco[Monto],Banco[CtaCtbl],$C18,Banco[Periodo Contable],TEXT(H$3,"mmm-yyyy")) -> 0 | I18: =SUM(Tabla17[[#This Row],[sept-21]:[dic-21]]) -> 0 | J18: =SUMIFS(Banco[Monto],Banco[CtaCtbl],$C18,Banco[Periodo Contable],TEXT(J$3,"mmm-yyyy")) -> 0 | K18: =SUMIFS(Banco[Monto],Banco[CtaCtbl],$C18,Banco[Periodo Contable],TEXT(K$3,"mmm-yyyy")) -> 0 | L18: =SUMIFS(Banco[Monto],Banco[CtaCtbl],$C18,Banco[Periodo Contable],TEXT(L$3,"mmm-yyyy")) -> 0 | M18: =SUMIFS(Banco[Monto],Banco[CtaCtbl],$C18,Banco[Periodo Contable],TEXT(M$3,"mmm-yyyy")) -> 0 | N18: =SUMIFS(Banco[Monto],Banco[CtaCtbl],$C18,Banco[Periodo Contable],TEXT(N$3,"mmm-yyyy")) -> 0 | O18: =SUMIFS(Banco[Monto],Banco[CtaCtbl],$C18,Banco[Periodo Contable],TEXT(O$3,"mmm-yyyy")) -> 0 | P18: =SUMIFS(Banco[Monto],Banco[CtaCtbl],$C18,Banco[Periodo Contable],TEXT(P$3,"mmm-yyyy")) -> 0 | Q18: =SUMIFS(Banco[Monto],Banco[CtaCtbl],$C18,Banco[Periodo Contable],TEXT(Q$3,"mmm-yyyy")) -> 0 | ... U18: =SUMIFS(Banco[Monto],Banco[CtaCtbl],$C18,Banco[Periodo Contable],TEXT(U$3,"mmm-yyyy")) -> 0 | V18: =SUM(Tabla17[[#This Row],[ene-22]:[dic-22]]) -> 0 | W18: =SUMIFS(Banco[Monto],Banco[CtaCtbl],$C18,Banco[Periodo Contable],TEXT(W$3,"mmm-yyyy")) -> 0 | X18: =SUMIFS(Banco[Monto],Banco[CtaCtbl],$C18,Banco[Periodo Contable],TEXT(X$3,"mmm-yyyy")) -> 0 | Y18: =SUMIFS(Banco[Monto],Banco[CtaCtbl],$C18,Banco[Periodo Contable],TEXT(Y$3,"mmm-yyyy")) -> 0 | Z18: =SUMIFS(Banco[Monto],Banco[CtaCtbl],$C18,Banco[Periodo Contable],TEXT(Z$3,"mmm-yyyy")) -> 0 | AA18: =SUMIFS(Banco[Monto],Banco[CtaCtbl],$C18,Banco[Periodo Contable],TEXT(AA$3,"mmm-yyyy")) -> 0 | AB18: =SUMIFS(Banco[Monto],Banco[CtaCtbl],$C18,Banco[Periodo Contable],TEXT(AB$3,"mmm-yyyy")) -> 0 | AC18: =SUMIFS(Banco[Monto],Banco[CtaCtbl],$C18,Banco[Periodo Contable],TEXT(AC$3,"mmm-yyyy")) -> 0 | AD18: =SUMIFS(Banco[Monto],Banco[CtaCtbl],$C18,Banco[Periodo Contable],TEXT(AD$3,"mmm-yyyy")) -> 0 | ... AH18: =SUMIFS(Banco[Monto],Banco[CtaCtbl],$C18,Banco[Periodo Contable],TEXT(AH$3,"mmm-yyyy")) -> 0 | AI18: =SUM(Tabla17[[#This Row],[ene-23]:[dic-23]]) -> 0 | AJ18: =SUMIFS(Banco[Monto],Banco[CtaCtbl],$C18,Banco[Periodo Contable],TEXT(AJ$3,"mmm-yyyy")) -> 0 | AK18: =SUMIFS(Banco[Monto],Banco[CtaCtbl],$C18,Banco[Periodo Contable],TEXT(AK$3,"mmm-yyyy")) -> 0 | AL18: =SUMIFS(Banco[Monto],Banco[CtaCtbl],$C18,Banco[Periodo Contable],TEXT(AL$3,"mmm-yyyy")) -> 0 | AM18: =SUMIFS(Banco[Monto],Banco[CtaCtbl],$C18,Banco[Periodo Contable],TEXT(AM$3,"mmm-yyyy")) -> 0 | AN18: =SUMIFS(Banco[Monto],Banco[CtaCtbl],$C18,Banco[Periodo Contable],TEXT(AN$3,"mmm-yyyy")) -> 0 | AO18: =SUMIFS(Banco[Monto],Banco[CtaCtbl],$C18,Banco[Periodo Contable],TEXT(AO$3,"mmm-yyyy")) -> 0 | AP18: =SUMIFS(Banco[Monto],Banco[CtaCtbl],$C18,Banco[Periodo Contable],TEXT(AP$3,"mmm-yyyy")) -> 0 | AQ18: =SUMIFS(Banco[Monto],Banco[CtaCtbl],$C18,Banco[Periodo Contable],TEXT(AQ$3,"mmm-yyyy")) -> 0 | ... AU18: =SUMIFS(Banco[Monto],Banco[CtaCtbl],$C18,Banco[Periodo Contable],TEXT(AU$3,"mmm-yyyy")) -> 0 | AV18: =SUM(Tabla17[[#This Row],[ene-24]:[dic-24]]) -> 0 | AW18: =SUMIFS(Banco[Monto],Banco[CtaCtbl],$C18,Banco[Periodo Contable],TEXT(AW$3,"mmm-yyyy")) -> 0 | AX18: =SUMIFS(Banco[Monto],Banco[CtaCtbl],$C18,Banco[Periodo Contable],TEXT(AX$3,"mmm-yyyy")) -> 0 | AY18: =SUMIFS(Banco[Monto],Banco[CtaCtbl],$C18,Banco[Periodo Contable],TEXT(AY$3,"mmm-yyyy")) -> 0 | AZ18: =SUMIFS(Banco[Monto],Banco[CtaCtbl],$C18,Banco[Periodo Contable],TEXT(AZ$3,"mmm-yyyy")) -> 0 | BA18: =SUMIFS(Banco[Monto],Banco[CtaCtbl],$C18,Banco[Periodo Contable],TEXT(BA$3,"mmm-yyyy")) -> 0 | BB18: =SUMIFS(Banco[Monto],Banco[CtaCtbl],$C18,Banco[Periodo Contable],TEXT(BB$3,"mmm-yyyy")) -> 7862624 | BC18: =SUMIFS(Banco[Monto],Banco[CtaCtbl],$C18,Banco[Periodo Contable],TEXT(BC$3,"mmm-yyyy")) -> 0 | BD18: =SUMIFS(Banco[Monto],Banco[CtaCtbl],$C18,Banco[Periodo Contable],TEXT(BD$3,"mmm-yyyy")) -> 0 | ... BH18: =SUMIFS(Banco[Monto],Banco[CtaCtbl],$C18,Banco[Periodo Contable],TEXT(BH$3,"mmm-yyyy")) -> 0 | BI18: =SUM(Tabla17[[#This Row],[ene-25]:[dic-25]]) -> 7862624 | BJ18: =SUMIFS(Banco[Monto],Banco[CtaCtbl],$C18,Banco[Periodo Contable],TEXT(BJ$3,"mmm-yyyy")) -> 0 | BK18: =SUMIFS(Banco[Monto],Banco[CtaCtbl],$C18,Banco[Periodo Contable],TEXT(BK$3,"mmm-yyyy")) -> 0 | BL18: =SUMIFS(Banco[Monto],Banco[CtaCtbl],$C18,Banco[Periodo Contable],TEXT(BL$3,"mmm-yyyy")) -> 0 | BM18: =SUMIFS(Banco[Monto],Banco[CtaCtbl],$C18,Banco[Periodo Contable],TEXT(BM$3,"mmm-yyyy")) -> 0 | BN18: =SUMIFS(Banco[Monto],Banco[CtaCtbl],$C18,Banco[Periodo Contable],TEXT(BN$3,"mmm-yyyy")) -> 0 | BO18: =SUMIFS(Banco[Monto],Banco[CtaCtbl],$C18,Banco[Periodo Contable],TEXT(BO$3,"mmm-yyyy")) -> 0 | BP18: =SUMIFS(Banco[Monto],Banco[CtaCtbl],$C18,Banco[Periodo Contable],TEXT(BP$3,"mmm-yyyy")) -> 0 | BQ18: =SUMIFS(Banco[Monto],Banco[CtaCtbl],$C18,Banco[Periodo Contable],TEXT(BQ$3,"mmm-yyyy")) -> 0 | ... BU18: =SUMIFS(Banco[Monto],Banco[CtaCtbl],$C18,Banco[Periodo Contable],TEXT(BU$3,"mmm-yyyy")) -> 0 | BV18: =SUM(Tabla17[[#This Row],[ene-26]:[dic-26]]) -> 0 | BW18: =SUMIFS(Banco[Monto],Banco[CtaCtbl],$C18,Banco[Periodo Contable],TEXT(BW$3,"mmm-yyyy")) -> 0
A19: 1.04.02 | B19: Utilidades Fondos Mutos | C19: =+Tabla17[[#This Row],[Cuenta]]&" - "&Tabla17[[#This Row],[Descripcion Cuenta]] -> 1.04.02 - Utilidades Fondos Mutos | E19: =SUMIFS(Banco[Monto],Banco[CtaCtbl],$C19,Banco[Periodo Contable],TEXT(E$3,"mmm-yyyy")) -> 0 | F19: =SUMIFS(Banco[Monto],Banco[CtaCtbl],$C19,Banco[Periodo Contable],TEXT(F$3,"mmm-yyyy")) -> 0 | G19: =SUMIFS(Banco[Monto],Banco[CtaCtbl],$C19,Banco[Periodo Contable],TEXT(G$3,"mmm-yyyy")) -> 0 | H19: =SUMIFS(Banco[Monto],Banco[CtaCtbl],$C19,Banco[Periodo Contable],TEXT(H$3,"mmm-yyyy")) -> 0 | I19: =SUM(Tabla17[[#This Row],[sept-21]:[dic-21]]) -> 0 | J19: =SUMIFS(Banco[Monto],Banco[CtaCtbl],$C19,Banco[Periodo Contable],TEXT(J$3,"mmm-yyyy")) -> 0 | K19: =SUMIFS(Banco[Monto],Banco[CtaCtbl],$C19,Banco[Periodo Contable],TEXT(K$3,"mmm-yyyy")) -> 0 | L19: =SUMIFS(Banco[Monto],Banco[CtaCtbl],$C19,Banco[Periodo Contable],TEXT(L$3,"mmm-yyyy")) -> 0 | M19: =SUMIFS(Banco[Monto],Banco[CtaCtbl],$C19,Banco[Periodo Contable],TEXT(M$3,"mmm-yyyy")) -> 0 | N19: =SUMIFS(Banco[Monto],Banco[CtaCtbl],$C19,Banco[Periodo Contable],TEXT(N$3,"mmm-yyyy")) -> 0 | O19: =SUMIFS(Banco[Monto],Banco[CtaCtbl],$C19,Banco[Periodo Contable],TEXT(O$3,"mmm-yyyy")) -> 0 | P19: =SUMIFS(Banco[Monto],Banco[CtaCtbl],$C19,Banco[Periodo Contable],TEXT(P$3,"mmm-yyyy")) -> 0 | Q19: =SUMIFS(Banco[Monto],Banco[CtaCtbl],$C19,Banco[Periodo Contable],TEXT(Q$3,"mmm-yyyy")) -> 0 | ... U19: =SUMIFS(Banco[Monto],Banco[CtaCtbl],$C19,Banco[Periodo Contable],TEXT(U$3,"mmm-yyyy")) -> 0 | V19: =SUM(Tabla17[[#This Row],[ene-22]:[dic-22]]) -> 0 | W19: =SUMIFS(Banco[Monto],Banco[CtaCtbl],$C19,Banco[Periodo Contable],TEXT(W$3,"mmm-yyyy")) -> 0 | X19: =SUMIFS(Banco[Monto],Banco[CtaCtbl],$C19,Banco[Periodo Contable],TEXT(X$3,"mmm-yyyy")) -> 0 | Y19: =SUMIFS(Banco[Monto],Banco[CtaCtbl],$C19,Banco[Periodo Contable],TEXT(Y$3,"mmm-yyyy")) -> 0 | Z19: =SUMIFS(Banco[Monto],Banco[CtaCtbl],$C19,Banco[Periodo Contable],TEXT(Z$3,"mmm-yyyy")) -> 0 | AA19: =SUMIFS(Banco[Monto],Banco[CtaCtbl],$C19,Banco[Periodo Contable],TEXT(AA$3,"mmm-yyyy")) -> 0 | AB19: =SUMIFS(Banco[Monto],Banco[CtaCtbl],$C19,Banco[Periodo Contable],TEXT(AB$3,"mmm-yyyy")) -> 0 | AC19: =SUMIFS(Banco[Monto],Banco[CtaCtbl],$C19,Banco[Periodo Contable],TEXT(AC$3,"mmm-yyyy")) -> 0 | AD19: =SUMIFS(Banco[Monto],Banco[CtaCtbl],$C19,Banco[Periodo Contable],TEXT(AD$3,"mmm-yyyy")) -> 0 | ... AH19: =SUMIFS(Banco[Monto],Banco[CtaCtbl],$C19,Banco[Periodo Contable],TEXT(AH$3,"mmm-yyyy")) -> 0 | AI19: =SUM(Tabla17[[#This Row],[ene-23]:[dic-23]]) -> 0 | AJ19: =SUMIFS(Banco[Monto],Banco[CtaCtbl],$C19,Banco[Periodo Contable],TEXT(AJ$3,"mmm-yyyy")) -> 0 | AK19: =SUMIFS(Banco[Monto],Banco[CtaCtbl],$C19,Banco[Periodo Contable],TEXT(AK$3,"mmm-yyyy")) -> 0 | AL19: =SUMIFS(Banco[Monto],Banco[CtaCtbl],$C19,Banco[Periodo Contable],TEXT(AL$3,"mmm-yyyy")) -> 0 | AM19: =SUMIFS(Banco[Monto],Banco[CtaCtbl],$C19,Banco[Periodo Contable],TEXT(AM$3,"mmm-yyyy")) -> 0 | AN19: =SUMIFS(Banco[Monto],Banco[CtaCtbl],$C19,Banco[Periodo Contable],TEXT(AN$3,"mmm-yyyy")) -> 0 | AO19: =SUMIFS(Banco[Monto],Banco[CtaCtbl],$C19,Banco[Periodo Contable],TEXT(AO$3,"mmm-yyyy")) -> 0 | AP19: =SUMIFS(Banco[Monto],Banco[CtaCtbl],$C19,Banco[Periodo Contable],TEXT(AP$3,"mmm-yyyy")) -> 0 | AQ19: =SUMIFS(Banco[Monto],Banco[CtaCtbl],$C19,Banco[Periodo Contable],TEXT(AQ$3,"mmm-yyyy")) -> 0 | ... AU19: =SUMIFS(Banco[Monto],Banco[CtaCtbl],$C19,Banco[Periodo Contable],TEXT(AU$3,"mmm-yyyy")) -> 0 | AV19: =SUM(Tabla17[[#This Row],[ene-24]:[dic-24]]) -> 0 | AW19: =SUMIFS(Banco[Monto],Banco[CtaCtbl],$C19,Banco[Periodo Contable],TEXT(AW$3,"mmm-yyyy")) -> 0 | AX19: =SUMIFS(Banco[Monto],Banco[CtaCtbl],$C19,Banco[Periodo Contable],TEXT(AX$3,"mmm-yyyy")) -> 0 | AY19: =SUMIFS(Banco[Monto],Banco[CtaCtbl],$C19,Banco[Periodo Contable],TEXT(AY$3,"mmm-yyyy")) -> 0 | AZ19: =SUMIFS(Banco[Monto],Banco[CtaCtbl],$C19,Banco[Periodo Contable],TEXT(AZ$3,"mmm-yyyy")) -> 0 | BA19: =SUMIFS(Banco[Monto],Banco[CtaCtbl],$C19,Banco[Periodo Contable],TEXT(BA$3,"mmm-yyyy")) -> 0 | BB19: =SUMIFS(Banco[Monto],Banco[CtaCtbl],$C19,Banco[Periodo Contable],TEXT(BB$3,"mmm-yyyy")) -> 0 | BC19: =SUMIFS(Banco[Monto],Banco[CtaCtbl],$C19,Banco[Periodo Contable],TEXT(BC$3,"mmm-yyyy")) -> 0 | BD19: =SUMIFS(Banco[Monto],Banco[CtaCtbl],$C19,Banco[Periodo Contable],TEXT(BD$3,"mmm-yyyy")) -> 0 | ... BH19: =SUMIFS(Banco[Monto],Banco[CtaCtbl],$C19,Banco[Periodo Contable],TEXT(BH$3,"mmm-yyyy")) -> 0 | BI19: =SUM(Tabla17[[#This Row],[ene-25]:[dic-25]]) -> 0 | BJ19: =SUMIFS(Banco[Monto],Banco[CtaCtbl],$C19,Banco[Periodo Contable],TEXT(BJ$3,"mmm-yyyy")) -> 0 | BK19: =SUMIFS(Banco[Monto],Banco[CtaCtbl],$C19,Banco[Periodo Contable],TEXT(BK$3,"mmm-yyyy")) -> 0 | BL19: =SUMIFS(Banco[Monto],Banco[CtaCtbl],$C19,Banco[Periodo Contable],TEXT(BL$3,"mmm-yyyy")) -> 0 | BM19: =SUMIFS(Banco[Monto],Banco[CtaCtbl],$C19,Banco[Periodo Contable],TEXT(BM$3,"mmm-yyyy")) -> 0 | BN19: =SUMIFS(Banco[Monto],Banco[CtaCtbl],$C19,Banco[Periodo Contable],TEXT(BN$3,"mmm-yyyy")) -> 0 | BO19: =SUMIFS(Banco[Monto],Banco[CtaCtbl],$C19,Banco[Periodo Contable],TEXT(BO$3,"mmm-yyyy")) -> 0 | BP19: =SUMIFS(Banco[Monto],Banco[CtaCtbl],$C19,Banco[Periodo Contable],TEXT(BP$3,"mmm-yyyy")) -> 0 | BQ19: =SUMIFS(Banco[Monto],Banco[CtaCtbl],$C19,Banco[Periodo Contable],TEXT(BQ$3,"mmm-yyyy")) -> 0 | ... BU19: =SUMIFS(Banco[Monto],Banco[CtaCtbl],$C19,Banco[Periodo Contable],TEXT(BU$3,"mmm-yyyy")) -> 0 | BV19: =SUM(Tabla17[[#This Row],[ene-26]:[dic-26]]) -> 0 | BW19: =SUMIFS(Banco[Monto],Banco[CtaCtbl],$C19,Banco[Periodo Contable],TEXT(BW$3,"mmm-yyyy")) -> 0
A20: 1.04.03 | B20: Rescate Fondos Mutuos | C20: =+Tabla17[[#This Row],[Cuenta]]&" - "&Tabla17[[#This Row],[Descripcion Cuenta]] -> 1.04.03 - Rescate Fondos Mutuos | E20: =SUMIFS(Banco[Monto],Banco[CtaCtbl],$C20,Banco[Periodo Contable],TEXT(E$3,"mmm-yyyy")) -> 0 | F20: =SUMIFS(Banco[Monto],Banco[CtaCtbl],$C20,Banco[Periodo Contable],TEXT(F$3,"mmm-yyyy")) -> 0 | G20: =SUMIFS(Banco[Monto],Banco[CtaCtbl],$C20,Banco[Periodo Contable],TEXT(G$3,"mmm-yyyy")) -> 0 | H20: =SUMIFS(Banco[Monto],Banco[CtaCtbl],$C20,Banco[Periodo Contable],TEXT(H$3,"mmm-yyyy")) -> 0 | I20: =SUM(Tabla17[[#This Row],[sept-21]:[dic-21]]) -> 0 | J20: =SUMIFS(Banco[Monto],Banco[CtaCtbl],$C20,Banco[Periodo Contable],TEXT(J$3,"mmm-yyyy")) -> 0 | K20: =SUMIFS(Banco[Monto],Banco[CtaCtbl],$C20,Banco[Periodo Contable],TEXT(K$3,"mmm-yyyy")) -> 0 | L20: =SUMIFS(Banco[Monto],Banco[CtaCtbl],$C20,Banco[Periodo Contable],TEXT(L$3,"mmm-yyyy")) -> 0 | M20: =SUMIFS(Banco[Monto],Banco[CtaCtbl],$C20,Banco[Periodo Contable],TEXT(M$3,"mmm-yyyy")) -> 0 | N20: =SUMIFS(Banco[Monto],Banco[CtaCtbl],$C20,Banco[Periodo Contable],TEXT(N$3,"mmm-yyyy")) -> 0 | O20: =SUMIFS(Banco[Monto],Banco[CtaCtbl],$C20,Banco[Periodo Contable],TEXT(O$3,"mmm-yyyy")) -> 0 | P20: =SUMIFS(Banco[Monto],Banco[CtaCtbl],$C20,Banco[Periodo Contable],TEXT(P$3,"mmm-yyyy")) -> 0 | Q20: =SUMIFS(Banco[Monto],Banco[CtaCtbl],$C20,Banco[Periodo Contable],TEXT(Q$3,"mmm-yyyy")) -> 0 | ... U20: =SUMIFS(Banco[Monto],Banco[CtaCtbl],$C20,Banco[Periodo Contable],TEXT(U$3,"mmm-yyyy")) -> 0 | V20: =SUM(Tabla17[[#This Row],[ene-22]:[dic-22]]) -> 0 | W20: =SUMIFS(Banco[Monto],Banco[CtaCtbl],$C20,Banco[Periodo Contable],TEXT(W$3,"mmm-yyyy")) -> 0 | X20: =SUMIFS(Banco[Monto],Banco[CtaCtbl],$C20,Banco[Periodo Contable],TEXT(X$3,"mmm-yyyy")) -> 0 | Y20: =SUMIFS(Banco[Monto],Banco[CtaCtbl],$C20,Banco[Periodo Contable],TEXT(Y$3,"mmm-yyyy")) -> 0 | Z20: =SUMIFS(Banco[Monto],Banco[CtaCtbl],$C20,Banco[Periodo Contable],TEXT(Z$3,"mmm-yyyy")) -> 0 | AA20: =SUMIFS(Banco[Monto],Banco[CtaCtbl],$C20,Banco[Periodo Contable],TEXT(AA$3,"mmm-yyyy")) -> 0 | AB20: =SUMIFS(Banco[Monto],Banco[CtaCtbl],$C20,Banco[Periodo Contable],TEXT(AB$3,"mmm-yyyy")) -> 0 | AC20: =SUMIFS(Banco[Monto],Banco[CtaCtbl],$C20,Banco[Periodo Contable],TEXT(AC$3,"mmm-yyyy")) -> 0 | AD20: =SUMIFS(Banco[Monto],Banco[CtaCtbl],$C20,Banco[Periodo Contable],TEXT(AD$3,"mmm-yyyy")) -> 0 | ... AH20: =SUMIFS(Banco[Monto],Banco[CtaCtbl],$C20,Banco[Periodo Contable],TEXT(AH$3,"mmm-yyyy")) -> 0 | AI20: =SUM(Tabla17[[#This Row],[ene-23]:[dic-23]]) -> 0 | AJ20: =SUMIFS(Banco[Monto],Banco[CtaCtbl],$C20,Banco[Periodo Contable],TEXT(AJ$3,"mmm-yyyy")) -> 0 | AK20: =SUMIFS(Banco[Monto],Banco[CtaCtbl],$C20,Banco[Periodo Contable],TEXT(AK$3,"mmm-yyyy")) -> 0 | AL20: =SUMIFS(Banco[Monto],Banco[CtaCtbl],$C20,Banco[Periodo Contable],TEXT(AL$3,"mmm-yyyy")) -> 0 | AM20: =SUMIFS(Banco[Monto],Banco[CtaCtbl],$C20,Banco[Periodo Contable],TEXT(AM$3,"mmm-yyyy")) -> 0 | AN20: =SUMIFS(Banco[Monto],Banco[CtaCtbl],$C20,Banco[Periodo Contable],TEXT(AN$3,"mmm-yyyy")) -> 0 | AO20: =SUMIFS(Banco[Monto],Banco[CtaCtbl],$C20,Banco[Periodo Contable],TEXT(AO$3,"mmm-yyyy")) -> 0 | AP20: =SUMIFS(Banco[Monto],Banco[CtaCtbl],$C20,Banco[Periodo Contable],TEXT(AP$3,"mmm-yyyy")) -> 0 | AQ20: =SUMIFS(Banco[Monto],Banco[CtaCtbl],$C20,Banco[Periodo Contable],TEXT(AQ$3,"mmm-yyyy")) -> 0 | ... AU20: =SUMIFS(Banco[Monto],Banco[CtaCtbl],$C20,Banco[Periodo Contable],TEXT(AU$3,"mmm-yyyy")) -> 0 | AV20: =SUM(Tabla17[[#This Row],[ene-24]:[dic-24]]) -> 0 | AW20: =SUMIFS(Banco[Monto],Banco[CtaCtbl],$C20,Banco[Periodo Contable],TEXT(AW$3,"mmm-yyyy")) -> 0 | AX20: =SUMIFS(Banco[Monto],Banco[CtaCtbl],$C20,Banco[Periodo Contable],TEXT(AX$3,"mmm-yyyy")) -> 0 | AY20: =SUMIFS(Banco[Monto],Banco[CtaCtbl],$C20,Banco[Periodo Contable],TEXT(AY$3,"mmm-yyyy")) -> 0 | AZ20: =SUMIFS(Banco[Monto],Banco[CtaCtbl],$C20,Banco[Periodo Contable],TEXT(AZ$3,"mmm-yyyy")) -> 0 | BA20: =SUMIFS(Banco[Monto],Banco[CtaCtbl],$C20,Banco[Periodo Contable],TEXT(BA$3,"mmm-yyyy")) -> 0 | BB20: =SUMIFS(Banco[Monto],Banco[CtaCtbl],$C20,Banco[Periodo Contable],TEXT(BB$3,"mmm-yyyy")) -> 0 | BC20: =SUMIFS(Banco[Monto],Banco[CtaCtbl],$C20,Banco[Periodo Contable],TEXT(BC$3,"mmm-yyyy")) -> 0 | BD20: =SUMIFS(Banco[Monto],Banco[CtaCtbl],$C20,Banco[Periodo Contable],TEXT(BD$3,"mmm-yyyy")) -> 0 | ... BH20: =SUMIFS(Banco[Monto],Banco[CtaCtbl],$C20,Banco[Periodo Contable],TEXT(BH$3,"mmm-yyyy")) -> 0 | BI20: =SUM(Tabla17[[#This Row],[ene-25]:[dic-25]]) -> 0 | BJ20: =SUMIFS(Banco[Monto],Banco[CtaCtbl],$C20,Banco[Periodo Contable],TEXT(BJ$3,"mmm-yyyy")) -> 0 | BK20: =SUMIFS(Banco[Monto],Banco[CtaCtbl],$C20,Banco[Periodo Contable],TEXT(BK$3,"mmm-yyyy")) -> 0 | BL20: =SUMIFS(Banco[Monto],Banco[CtaCtbl],$C20,Banco[Periodo Contable],TEXT(BL$3,"mmm-yyyy")) -> 0 | BM20: =SUMIFS(Banco[Monto],Banco[CtaCtbl],$C20,Banco[Periodo Contable],TEXT(BM$3,"mmm-yyyy")) -> 0 | BN20: =SUMIFS(Banco[Monto],Banco[CtaCtbl],$C20,Banco[Periodo Contable],TEXT(BN$3,"mmm-yyyy")) -> 0 | BO20: =SUMIFS(Banco[Monto],Banco[CtaCtbl],$C20,Banco[Periodo Contable],TEXT(BO$3,"mmm-yyyy")) -> 0 | BP20: =SUMIFS(Banco[Monto],Banco[CtaCtbl],$C20,Banco[Periodo Contable],TEXT(BP$3,"mmm-yyyy")) -> 0 | BQ20: =SUMIFS(Banco[Monto],Banco[CtaCtbl],$C20,Banco[Periodo Contable],TEXT(BQ$3,"mmm-yyyy")) -> 0 | ... BU20: =SUMIFS(Banco[Monto],Banco[CtaCtbl],$C20,Banco[Periodo Contable],TEXT(BU$3,"mmm-yyyy")) -> 0 | BV20: =SUM(Tabla17[[#This Row],[ene-26]:[dic-26]]) -> 0 | BW20: =SUMIFS(Banco[Monto],Banco[CtaCtbl],$C20,Banco[Periodo Contable],TEXT(BW$3,"mmm-yyyy")) -> 0
A21: 1.04.04 | B21: Rescate Plazo Fijo | C21: =+Tabla17[[#This Row],[Cuenta]]&" - "&Tabla17[[#This Row],[Descripcion Cuenta]] -> 1.04.04 - Rescate Plazo Fijo | E21: =SUMIFS(Banco[Monto],Banco[CtaCtbl],$C21,Banco[Periodo Contable],TEXT(E$3,"mmm-yyyy")) -> 0 | F21: =SUMIFS(Banco[Monto],Banco[CtaCtbl],$C21,Banco[Periodo Contable],TEXT(F$3,"mmm-yyyy")) -> 0 | G21: =SUMIFS(Banco[Monto],Banco[CtaCtbl],$C21,Banco[Periodo Contable],TEXT(G$3,"mmm-yyyy")) -> 0 | H21: =SUMIFS(Banco[Monto],Banco[CtaCtbl],$C21,Banco[Periodo Contable],TEXT(H$3,"mmm-yyyy")) -> 0 | I21: =SUM(Tabla17[[#This Row],[sept-21]:[dic-21]]) -> 0 | J21: =SUMIFS(Banco[Monto],Banco[CtaCtbl],$C21,Banco[Periodo Contable],TEXT(J$3,"mmm-yyyy")) -> 0 | K21: =SUMIFS(Banco[Monto],Banco[CtaCtbl],$C21,Banco[Periodo Contable],TEXT(K$3,"mmm-yyyy")) -> 0 | L21: =SUMIFS(Banco[Monto],Banco[CtaCtbl],$C21,Banco[Periodo Contable],TEXT(L$3,"mmm-yyyy")) -> 0 | M21: =SUMIFS(Banco[Monto],Banco[CtaCtbl],$C21,Banco[Periodo Contable],TEXT(M$3,"mmm-yyyy")) -> 0 | N21: =SUMIFS(Banco[Monto],Banco[CtaCtbl],$C21,Banco[Periodo Contable],TEXT(N$3,"mmm-yyyy")) -> 0 | O21: =SUMIFS(Banco[Monto],Banco[CtaCtbl],$C21,Banco[Periodo Contable],TEXT(O$3,"mmm-yyyy")) -> 0 | P21: =SUMIFS(Banco[Monto],Banco[CtaCtbl],$C21,Banco[Periodo Contable],TEXT(P$3,"mmm-yyyy")) -> 0 | Q21: =SUMIFS(Banco[Monto],Banco[CtaCtbl],$C21,Banco[Periodo Contable],TEXT(Q$3,"mmm-yyyy")) -> 0 | ... U21: =SUMIFS(Banco[Monto],Banco[CtaCtbl],$C21,Banco[Periodo Contable],TEXT(U$3,"mmm-yyyy")) -> 0 | V21: =SUM(Tabla17[[#This Row],[ene-22]:[dic-22]]) -> 0 | W21: =SUMIFS(Banco[Monto],Banco[CtaCtbl],$C21,Banco[Periodo Contable],TEXT(W$3,"mmm-yyyy")) -> 0 | X21: =SUMIFS(Banco[Monto],Banco[CtaCtbl],$C21,Banco[Periodo Contable],TEXT(X$3,"mmm-yyyy")) -> 0 | Y21: =SUMIFS(Banco[Monto],Banco[CtaCtbl],$C21,Banco[Periodo Contable],TEXT(Y$3,"mmm-yyyy")) -> 0 | Z21: =SUMIFS(Banco[Monto],Banco[CtaCtbl],$C21,Banco[Periodo Contable],TEXT(Z$3,"mmm-yyyy")) -> 0 | AA21: =SUMIFS(Banco[Monto],Banco[CtaCtbl],$C21,Banco[Periodo Contable],TEXT(AA$3,"mmm-yyyy")) -> 0 | AB21: =SUMIFS(Banco[Monto],Banco[CtaCtbl],$C21,Banco[Periodo Contable],TEXT(AB$3,"mmm-yyyy")) -> 0 | AC21: =SUMIFS(Banco[Monto],Banco[CtaCtbl],$C21,Banco[Periodo Contable],TEXT(AC$3,"mmm-yyyy")) -> 0 | AD21: =SUMIFS(Banco[Monto],Banco[CtaCtbl],$C21,Banco[Periodo Contable],TEXT(AD$3,"mmm-yyyy")) -> 0 | ... AH21: =SUMIFS(Banco[Monto],Banco[CtaCtbl],$C21,Banco[Periodo Contable],TEXT(AH$3,"mmm-yyyy")) -> 0 | AI21: =SUM(Tabla17[[#This Row],[ene-23]:[dic-23]]) -> 0 | AJ21: =SUMIFS(Banco[Monto],Banco[CtaCtbl],$C21,Banco[Periodo Contable],TEXT(AJ$3,"mmm-yyyy")) -> 0 | AK21: =SUMIFS(Banco[Monto],Banco[CtaCtbl],$C21,Banco[Periodo Contable],TEXT(AK$3,"mmm-yyyy")) -> 0 | AL21: =SUMIFS(Banco[Monto],Banco[CtaCtbl],$C21,Banco[Periodo Contable],TEXT(AL$3,"mmm-yyyy")) -> 0 | AM21: =SUMIFS(Banco[Monto],Banco[CtaCtbl],$C21,Banco[Periodo Contable],TEXT(AM$3,"mmm-yyyy")) -> 0 | AN21: =SUMIFS(Banco[Monto],Banco[CtaCtbl],$C21,Banco[Periodo Contable],TEXT(AN$3,"mmm-yyyy")) -> 0 | AO21: =SUMIFS(Banco[Monto],Banco[CtaCtbl],$C21,Banco[Periodo Contable],TEXT(AO$3,"mmm-yyyy")) -> 0 | AP21: =SUMIFS(Banco[Monto],Banco[CtaCtbl],$C21,Banco[Periodo Contable],TEXT(AP$3,"mmm-yyyy")) -> 0 | AQ21: =SUMIFS(Banco[Monto],Banco[CtaCtbl],$C21,Banco[Periodo Contable],TEXT(AQ$3,"mmm-yyyy")) -> 0 | ... AU21: =SUMIFS(Banco[Monto],Banco[CtaCtbl],$C21,Banco[Periodo Contable],TEXT(AU$3,"mmm-yyyy")) -> 0 | AV21: =SUM(Tabla17[[#This Row],[ene-24]:[dic-24]]) -> 0 | AW21: =SUMIFS(Banco[Monto],Banco[CtaCtbl],$C21,Banco[Periodo Contable],TEXT(AW$3,"mmm-yyyy")) -> 0 | AX21: =SUMIFS(Banco[Monto],Banco[CtaCtbl],$C21,Banco[Periodo Contable],TEXT(AX$3,"mmm-yyyy")) -> 0 | AY21: =SUMIFS(Banco[Monto],Banco[CtaCtbl],$C21,Banco[Periodo Contable],TEXT(AY$3,"mmm-yyyy")) -> 0 | AZ21: =SUMIFS(Banco[Monto],Banco[CtaCtbl],$C21,Banco[Periodo Contable],TEXT(AZ$3,"mmm-yyyy")) -> 0 | BA21: =SUMIFS(Banco[Monto],Banco[CtaCtbl],$C21,Banco[Periodo Contable],TEXT(BA$3,"mmm-yyyy")) -> 0 | BB21: =SUMIFS(Banco[Monto],Banco[CtaCtbl],$C21,Banco[Periodo Contable],TEXT(BB$3,"mmm-yyyy")) -> 70000000 | BC21: =SUMIFS(Banco[Monto],Banco[CtaCtbl],$C21,Banco[Periodo Contable],TEXT(BC$3,"mmm-yyyy")) -> 0 | BD21: =SUMIFS(Banco[Monto],Banco[CtaCtbl],$C21,Banco[Periodo Contable],TEXT(BD$3,"mmm-yyyy")) -> 0 | ... BH21: =SUMIFS(Banco[Monto],Banco[CtaCtbl],$C21,Banco[Periodo Contable],TEXT(BH$3,"mmm-yyyy")) -> 0 | BI21: =SUM(Tabla17[[#This Row],[ene-25]:[dic-25]]) -> 70000000 | BJ21: =SUMIFS(Banco[Monto],Banco[CtaCtbl],$C21,Banco[Periodo Contable],TEXT(BJ$3,"mmm-yyyy")) -> 0 | BK21: =SUMIFS(Banco[Monto],Banco[CtaCtbl],$C21,Banco[Periodo Contable],TEXT(BK$3,"mmm-yyyy")) -> 0 | BL21: =SUMIFS(Banco[Monto],Banco[CtaCtbl],$C21,Banco[Periodo Contable],TEXT(BL$3,"mmm-yyyy")) -> 0 | BM21: =SUMIFS(Banco[Monto],Banco[CtaCtbl],$C21,Banco[Periodo Contable],TEXT(BM$3,"mmm-yyyy")) -> 0 | BN21: =SUMIFS(Banco[Monto],Banco[CtaCtbl],$C21,Banco[Periodo Contable],TEXT(BN$3,"mmm-yyyy")) -> 0 | BO21: =SUMIFS(Banco[Monto],Banco[CtaCtbl],$C21,Banco[Periodo Contable],TEXT(BO$3,"mmm-yyyy")) -> 0 | BP21: =SUMIFS(Banco[Monto],Banco[CtaCtbl],$C21,Banco[Periodo Contable],TEXT(BP$3,"mmm-yyyy")) -> 0 | BQ21: =SUMIFS(Banco[Monto],Banco[CtaCtbl],$C21,Banco[Periodo Contable],TEXT(BQ$3,"mmm-yyyy")) -> 0 | ... BU21: =SUMIFS(Banco[Monto],Banco[CtaCtbl],$C21,Banco[Periodo Contable],TEXT(BU$3,"mmm-yyyy")) -> 0 | BV21: =SUM(Tabla17[[#This Row],[ene-26]:[dic-26]]) -> 0 | BW21: =SUMIFS(Banco[Monto],Banco[CtaCtbl],$C21,Banco[Periodo Contable],TEXT(BW$3,"mmm-yyyy")) -> 0
A22: 1.04.05 | B22: Restitución Fondos / Rechazo Depositos | C22: =+Tabla17[[#This Row],[Cuenta]]&" - "&Tabla17[[#This Row],[Descripcion Cuenta]] -> 1.04.05 - Restitución Fondos / Rechazo Depositos | E22: =SUMIFS(Banco[Monto],Banco[CtaCtbl],$C22,Banco[Periodo Contable],TEXT(E$3,"mmm-yyyy")) -> 0 | F22: =SUMIFS(Banco[Monto],Banco[CtaCtbl],$C22,Banco[Periodo Contable],TEXT(F$3,"mmm-yyyy")) -> 0 | G22: =SUMIFS(Banco[Monto],Banco[CtaCtbl],$C22,Banco[Periodo Contable],TEXT(G$3,"mmm-yyyy")) -> 0 | H22: =SUMIFS(Banco[Monto],Banco[CtaCtbl],$C22,Banco[Periodo Contable],TEXT(H$3,"mmm-yyyy")) -> 0 | I22: =SUM(Tabla17[[#This Row],[sept-21]:[dic-21]]) -> 0 | J22: =SUMIFS(Banco[Monto],Banco[CtaCtbl],$C22,Banco[Periodo Contable],TEXT(J$3,"mmm-yyyy")) -> 0 | K22: =SUMIFS(Banco[Monto],Banco[CtaCtbl],$C22,Banco[Periodo Contable],TEXT(K$3,"mmm-yyyy")) -> 0 | L22: =SUMIFS(Banco[Monto],Banco[CtaCtbl],$C22,Banco[Periodo Contable],TEXT(L$3,"mmm-yyyy")) -> 0 | M22: =SUMIFS(Banco[Monto],Banco[CtaCtbl],$C22,Banco[Periodo Contable],TEXT(M$3,"mmm-yyyy")) -> 0 | N22: =SUMIFS(Banco[Monto],Banco[CtaCtbl],$C22,Banco[Periodo Contable],TEXT(N$3,"mmm-yyyy")) -> 0 | O22: =SUMIFS(Banco[Monto],Banco[CtaCtbl],$C22,Banco[Periodo Contable],TEXT(O$3,"mmm-yyyy")) -> 0 | P22: =SUMIFS(Banco[Monto],Banco[CtaCtbl],$C22,Banco[Periodo Contable],TEXT(P$3,"mmm-yyyy")) -> 0 | Q22: =SUMIFS(Banco[Monto],Banco[CtaCtbl],$C22,Banco[Periodo Contable],TEXT(Q$3,"mmm-yyyy")) -> 0 | ... U22: =SUMIFS(Banco[Monto],Banco[CtaCtbl],$C22,Banco[Periodo Contable],TEXT(U$3,"mmm-yyyy")) -> 0 | V22: =SUM(Tabla17[[#This Row],[ene-22]:[dic-22]]) -> 0 | W22: =SUMIFS(Banco[Monto],Banco[CtaCtbl],$C22,Banco[Periodo Contable],TEXT(W$3,"mmm-yyyy")) -> 0 | X22: =SUMIFS(Banco[Monto],Banco[CtaCtbl],$C22,Banco[Periodo Contable],TEXT(X$3,"mmm-yyyy")) -> 0 | Y22: =SUMIFS(Banco[Monto],Banco[CtaCtbl],$C22,Banco[Periodo Contable],TEXT(Y$3,"mmm-yyyy")) -> 0 | Z22: =SUMIFS(Banco[Monto],Banco[CtaCtbl],$C22,Banco[Periodo Contable],TEXT(Z$3,"mmm-yyyy")) -> 0 | AA22: =SUMIFS(Banco[Monto],Banco[CtaCtbl],$C22,Banco[Periodo Contable],TEXT(AA$3,"mmm-yyyy")) -> 0 | AB22: =SUMIFS(Banco[Monto],Banco[CtaCtbl],$C22,Banco[Periodo Contable],TEXT(AB$3,"mmm-yyyy")) -> 0 | AC22: =SUMIFS(Banco[Monto],Banco[CtaCtbl],$C22,Banco[Periodo Contable],TEXT(AC$3,"mmm-yyyy")) -> 0 | AD22: =SUMIFS(Banco[Monto],Banco[CtaCtbl],$C22,Banco[Periodo Contable],TEXT(AD$3,"mmm-yyyy")) -> 0 | ... AH22: =SUMIFS(Banco[Monto],Banco[CtaCtbl],$C22,Banco[Periodo Contable],TEXT(AH$3,"mmm-yyyy")) -> 0 | AI22: =SUM(Tabla17[[#This Row],[ene-23]:[dic-23]]) -> 0 | AJ22: =SUMIFS(Banco[Monto],Banco[CtaCtbl],$C22,Banco[Periodo Contable],TEXT(AJ$3,"mmm-yyyy")) -> 0 | AK22: =SUMIFS(Banco[Monto],Banco[CtaCtbl],$C22,Banco[Periodo Contable],TEXT(AK$3,"mmm-yyyy")) -> 0 | AL22: =SUMIFS(Banco[Monto],Banco[CtaCtbl],$C22,Banco[Periodo Contable],TEXT(AL$3,"mmm-yyyy")) -> 0 | AM22: =SUMIFS(Banco[Monto],Banco[CtaCtbl],$C22,Banco[Periodo Contable],TEXT(AM$3,"mmm-yyyy")) -> 0 | AN22: =SUMIFS(Banco[Monto],Banco[CtaCtbl],$C22,Banco[Periodo Contable],TEXT(AN$3,"mmm-yyyy")) -> 0 | AO22: =SUMIFS(Banco[Monto],Banco[CtaCtbl],$C22,Banco[Periodo Contable],TEXT(AO$3,"mmm-yyyy")) -> 0 | AP22: =SUMIFS(Banco[Monto],Banco[CtaCtbl],$C22,Banco[Periodo Contable],TEXT(AP$3,"mmm-yyyy")) -> 0 | AQ22: =SUMIFS(Banco[Monto],Banco[CtaCtbl],$C22,Banco[Periodo Contable],TEXT(AQ$3,"mmm-yyyy")) -> 0 | ... AU22: =SUMIFS(Banco[Monto],Banco[CtaCtbl],$C22,Banco[Periodo Contable],TEXT(AU$3,"mmm-yyyy")) -> 0 | AV22: =SUM(Tabla17[[#This Row],[ene-24]:[dic-24]]) -> 0 | AW22: =SUMIFS(Banco[Monto],Banco[CtaCtbl],$C22,Banco[Periodo Contable],TEXT(AW$3,"mmm-yyyy")) -> 0 | AX22: =SUMIFS(Banco[Monto],Banco[CtaCtbl],$C22,Banco[Periodo Contable],TEXT(AX$3,"mmm-yyyy")) -> 0 | AY22: =SUMIFS(Banco[Monto],Banco[CtaCtbl],$C22,Banco[Periodo Contable],TEXT(AY$3,"mmm-yyyy")) -> 0 | AZ22: =SUMIFS(Banco[Monto],Banco[CtaCtbl],$C22,Banco[Periodo Contable],TEXT(AZ$3,"mmm-yyyy")) -> 0 | BA22: =SUMIFS(Banco[Monto],Banco[CtaCtbl],$C22,Banco[Periodo Contable],TEXT(BA$3,"mmm-yyyy")) -> 0 | BB22: =SUMIFS(Banco[Monto],Banco[CtaCtbl],$C22,Banco[Periodo Contable],TEXT(BB$3,"mmm-yyyy")) -> 22271056 | BC22: =SUMIFS(Banco[Monto],Banco[CtaCtbl],$C22,Banco[Periodo Contable],TEXT(BC$3,"mmm-yyyy")) -> 0 | BD22: =SUMIFS(Banco[Monto],Banco[CtaCtbl],$C22,Banco[Periodo Contable],TEXT(BD$3,"mmm-yyyy")) -> 0 | ... BH22: =SUMIFS(Banco[Monto],Banco[CtaCtbl],$C22,Banco[Periodo Contable],TEXT(BH$3,"mmm-yyyy")) -> 0 | BI22: =SUM(Tabla17[[#This Row],[ene-25]:[dic-25]]) -> 22271056 | BJ22: =SUMIFS(Banco[Monto],Banco[CtaCtbl],$C22,Banco[Periodo Contable],TEXT(BJ$3,"mmm-yyyy")) -> 0 | BK22: =SUMIFS(Banco[Monto],Banco[CtaCtbl],$C22,Banco[Periodo Contable],TEXT(BK$3,"mmm-yyyy")) -> 0 | BL22: =SUMIFS(Banco[Monto],Banco[CtaCtbl],$C22,Banco[Periodo Contable],TEXT(BL$3,"mmm-yyyy")) -> 857907 | BM22: =SUMIFS(Banco[Monto],Banco[CtaCtbl],$C22,Banco[Periodo Contable],TEXT(BM$3,"mmm-yyyy")) -> 0 | BN22: =SUMIFS(Banco[Monto],Banco[CtaCtbl],$C22,Banco[Periodo Contable],TEXT(BN$3,"mmm-yyyy")) -> 0 | BO22: =SUMIFS(Banco[Monto],Banco[CtaCtbl],$C22,Banco[Periodo Contable],TEXT(BO$3,"mmm-yyyy")) -> 0 | BP22: =SUMIFS(Banco[Monto],Banco[CtaCtbl],$C22,Banco[Periodo Contable],TEXT(BP$3,"mmm-yyyy")) -> 0 | BQ22: =SUMIFS(Banco[Monto],Banco[CtaCtbl],$C22,Banco[Periodo Contable],TEXT(BQ$3,"mmm-yyyy")) -> 0 | ... BU22: =SUMIFS(Banco[Monto],Banco[CtaCtbl],$C22,Banco[Periodo Contable],TEXT(BU$3,"mmm-yyyy")) -> 0 | BV22: =SUM(Tabla17[[#This Row],[ene-26]:[dic-26]]) -> 857907 | BW22: =SUMIFS(Banco[Monto],Banco[CtaCtbl],$C22,Banco[Periodo Contable],TEXT(BW$3,"mmm-yyyy")) -> 0
C23: =+Tabla17[[#This Row],[Cuenta]]&" - "&Tabla17[[#This Row],[Descripcion Cuenta]] -> - | E23: =SUMIFS(Banco[Monto],Banco[CtaCtbl],$C23,Banco[Periodo Contable],TEXT(E$3,"mmm-yyyy")) -> 0 | F23: =SUMIFS(Banco[Monto],Banco[CtaCtbl],$C23,Banco[Periodo Contable],TEXT(F$3,"mmm-yyyy")) -> 0 | G23: =SUMIFS(Banco[Monto],Banco[CtaCtbl],$C23,Banco[Periodo Contable],TEXT(G$3,"mmm-yyyy")) -> 0 | H23: =SUMIFS(Banco[Monto],Banco[CtaCtbl],$C23,Banco[Periodo Contable],TEXT(H$3,"mmm-yyyy")) -> 0 | I23: =SUM(Tabla17[[#This Row],[sept-21]:[dic-21]]) -> 0 | J23: =SUMIFS(Banco[Monto],Banco[CtaCtbl],$C23,Banco[Periodo Contable],TEXT(J$3,"mmm-yyyy")) -> 0 | K23: =SUMIFS(Banco[Monto],Banco[CtaCtbl],$C23,Banco[Periodo Contable],TEXT(K$3,"mmm-yyyy")) -> 0 | L23: =SUMIFS(Banco[Monto],Banco[CtaCtbl],$C23,Banco[Periodo Contable],TEXT(L$3,"mmm-yyyy")) -> 0 | M23: =SUMIFS(Banco[Monto],Banco[CtaCtbl],$C23,Banco[Periodo Contable],TEXT(M$3,"mmm-yyyy")) -> 0 | N23: =SUMIFS(Banco[Monto],Banco[CtaCtbl],$C23,Banco[Periodo Contable],TEXT(N$3,"mmm-yyyy")) -> 0 | O23: =SUMIFS(Banco[Monto],Banco[CtaCtbl],$C23,Banco[Periodo Contable],TEXT(O$3,"mmm-yyyy")) -> 0 | P23: =SUMIFS(Banco[Monto],Banco[CtaCtbl],$C23,Banco[Periodo Contable],TEXT(P$3,"mmm-yyyy")) -> 0 | Q23: =SUMIFS(Banco[Monto],Banco[CtaCtbl],$C23,Banco[Periodo Contable],TEXT(Q$3,"mmm-yyyy")) -> 0 | ... U23: =SUMIFS(Banco[Monto],Banco[CtaCtbl],$C23,Banco[Periodo Contable],TEXT(U$3,"mmm-yyyy")) -> 0 | V23: =SUM(Tabla17[[#This Row],[ene-22]:[dic-22]]) -> 0 | W23: =SUMIFS(Banco[Monto],Banco[CtaCtbl],$C23,Banco[Periodo Contable],TEXT(W$3,"mmm-yyyy")) -> 0 | X23: =SUMIFS(Banco[Monto],Banco[CtaCtbl],$C23,Banco[Periodo Contable],TEXT(X$3,"mmm-yyyy")) -> 0 | Y23: =SUMIFS(Banco[Monto],Banco[CtaCtbl],$C23,Banco[Periodo Contable],TEXT(Y$3,"mmm-yyyy")) -> 0 | Z23: =SUMIFS(Banco[Monto],Banco[CtaCtbl],$C23,Banco[Periodo Contable],TEXT(Z$3,"mmm-yyyy")) -> 0 | AA23: =SUMIFS(Banco[Monto],Banco[CtaCtbl],$C23,Banco[Periodo Contable],TEXT(AA$3,"mmm-yyyy")) -> 0 | AB23: =SUMIFS(Banco[Monto],Banco[CtaCtbl],$C23,Banco[Periodo Contable],TEXT(AB$3,"mmm-yyyy")) -> 0 | AC23: =SUMIFS(Banco[Monto],Banco[CtaCtbl],$C23,Banco[Periodo Contable],TEXT(AC$3,"mmm-yyyy")) -> 0 | AD23: =SUMIFS(Banco[Monto],Banco[CtaCtbl],$C23,Banco[Periodo Contable],TEXT(AD$3,"mmm-yyyy")) -> 0 | ... AH23: =SUMIFS(Banco[Monto],Banco[CtaCtbl],$C23,Banco[Periodo Contable],TEXT(AH$3,"mmm-yyyy")) -> 0 | AI23: =SUM(Tabla17[[#This Row],[ene-23]:[dic-23]]) -> 0 | AJ23: =SUMIFS(Banco[Monto],Banco[CtaCtbl],$C23,Banco[Periodo Contable],TEXT(AJ$3,"mmm-yyyy")) -> 0 | AK23: =SUMIFS(Banco[Monto],Banco[CtaCtbl],$C23,Banco[Periodo Contable],TEXT(AK$3,"mmm-yyyy")) -> 0 | AL23: =SUMIFS(Banco[Monto],Banco[CtaCtbl],$C23,Banco[Periodo Contable],TEXT(AL$3,"mmm-yyyy")) -> 0 | AM23: =SUMIFS(Banco[Monto],Banco[CtaCtbl],$C23,Banco[Periodo Contable],TEXT(AM$3,"mmm-yyyy")) -> 0 | AN23: =SUMIFS(Banco[Monto],Banco[CtaCtbl],$C23,Banco[Periodo Contable],TEXT(AN$3,"mmm-yyyy")) -> 0 | AO23: =SUMIFS(Banco[Monto],Banco[CtaCtbl],$C23,Banco[Periodo Contable],TEXT(AO$3,"mmm-yyyy")) -> 0 | AP23: =SUMIFS(Banco[Monto],Banco[CtaCtbl],$C23,Banco[Periodo Contable],TEXT(AP$3,"mmm-yyyy")) -> 0 | AQ23: =SUMIFS(Banco[Monto],Banco[CtaCtbl],$C23,Banco[Periodo Contable],TEXT(AQ$3,"mmm-yyyy")) -> 0 | ... AU23: =SUMIFS(Banco[Monto],Banco[CtaCtbl],$C23,Banco[Periodo Contable],TEXT(AU$3,"mmm-yyyy")) -> 0 | AV23: =SUM(Tabla17[[#This Row],[ene-24]:[dic-24]]) -> 0 | AW23: =SUMIFS(Banco[Monto],Banco[CtaCtbl],$C23,Banco[Periodo Contable],TEXT(AW$3,"mmm-yyyy")) -> 0 | AX23: =SUMIFS(Banco[Monto],Banco[CtaCtbl],$C23,Banco[Periodo Contable],TEXT(AX$3,"mmm-yyyy")) -> 0 | AY23: =SUMIFS(Banco[Monto],Banco[CtaCtbl],$C23,Banco[Periodo Contable],TEXT(AY$3,"mmm-yyyy")) -> 0 | AZ23: =SUMIFS(Banco[Monto],Banco[CtaCtbl],$C23,Banco[Periodo Contable],TEXT(AZ$3,"mmm-yyyy")) -> 0 | BA23: =SUMIFS(Banco[Monto],Banco[CtaCtbl],$C23,Banco[Periodo Contable],TEXT(BA$3,"mmm-yyyy")) -> 0 | BB23: =SUMIFS(Banco[Monto],Banco[CtaCtbl],$C23,Banco[Periodo Contable],TEXT(BB$3,"mmm-yyyy")) -> 0 | BC23: =SUMIFS(Banco[Monto],Banco[CtaCtbl],$C23,Banco[Periodo Contable],TEXT(BC$3,"mmm-yyyy")) -> 0 | BD23: =SUMIFS(Banco[Monto],Banco[CtaCtbl],$C23,Banco[Periodo Contable],TEXT(BD$3,"mmm-yyyy")) -> 0 | ... BH23: =SUMIFS(Banco[Monto],Banco[CtaCtbl],$C23,Banco[Periodo Contable],TEXT(BH$3,"mmm-yyyy")) -> 0 | BI23: =SUM(Tabla17[[#This Row],[ene-25]:[dic-25]]) -> 0 | BJ23: =SUMIFS(Banco[Monto],Banco[CtaCtbl],$C23,Banco[Periodo Contable],TEXT(BJ$3,"mmm-yyyy")) -> 0 | BK23: =SUMIFS(Banco[Monto],Banco[CtaCtbl],$C23,Banco[Periodo Contable],TEXT(BK$3,"mmm-yyyy")) -> 0 | BL23: =SUMIFS(Banco[Monto],Banco[CtaCtbl],$C23,Banco[Periodo Contable],TEXT(BL$3,"mmm-yyyy")) -> 0 | BM23: =SUMIFS(Banco[Monto],Banco[CtaCtbl],$C23,Banco[Periodo Contable],TEXT(BM$3,"mmm-yyyy")) -> 0 | BN23: =SUMIFS(Banco[Monto],Banco[CtaCtbl],$C23,Banco[Periodo Contable],TEXT(BN$3,"mmm-yyyy")) -> 0 | BO23: =SUMIFS(Banco[Monto],Banco[CtaCtbl],$C23,Banco[Periodo Contable],TEXT(BO$3,"mmm-yyyy")) -> 0 | BP23: =SUMIFS(Banco[Monto],Banco[CtaCtbl],$C23,Banco[Periodo Contable],TEXT(BP$3,"mmm-yyyy")) -> 0 | BQ23: =SUMIFS(Banco[Monto],Banco[CtaCtbl],$C23,Banco[Periodo Contable],TEXT(BQ$3,"mmm-yyyy")) -> 0 | ... BU23: =SUMIFS(Banco[Monto],Banco[CtaCtbl],$C23,Banco[Periodo Contable],TEXT(BU$3,"mmm-yyyy")) -> 0 | BV23: =SUM(Tabla17[[#This Row],[ene-26]:[dic-26]]) -> 0 | BW23: =SUMIFS(Banco[Monto],Banco[CtaCtbl],$C23,Banco[Periodo Contable],TEXT(BW$3,"mmm-yyyy")) -> 0
C24: =+Tabla17[[#This Row],[Cuenta]]&" - "&Tabla17[[#This Row],[Descripcion Cuenta]] -> - | E24: =SUMIFS(Banco[Monto],Banco[CtaCtbl],$C24,Banco[Periodo Contable],TEXT(E$3,"mmm-yyyy")) -> 0 | F24: =SUMIFS(Banco[Monto],Banco[CtaCtbl],$C24,Banco[Periodo Contable],TEXT(F$3,"mmm-yyyy")) -> 0 | G24: =SUMIFS(Banco[Monto],Banco[CtaCtbl],$C24,Banco[Periodo Contable],TEXT(G$3,"mmm-yyyy")) -> 0 | H24: =SUMIFS(Banco[Monto],Banco[CtaCtbl],$C24,Banco[Periodo Contable],TEXT(H$3,"mmm-yyyy")) -> 0 | I24: =SUM(Tabla17[[#This Row],[sept-21]:[dic-21]]) -> 0 | J24: =SUMIFS(Banco[Monto],Banco[CtaCtbl],$C24,Banco[Periodo Contable],TEXT(J$3,"mmm-yyyy")) -> 0 | K24: =SUMIFS(Banco[Monto],Banco[CtaCtbl],$C24,Banco[Periodo Contable],TEXT(K$3,"mmm-yyyy")) -> 0 | L24: =SUMIFS(Banco[Monto],Banco[CtaCtbl],$C24,Banco[Periodo Contable],TEXT(L$3,"mmm-yyyy")) -> 0 | M24: =SUMIFS(Banco[Monto],Banco[CtaCtbl],$C24,Banco[Periodo Contable],TEXT(M$3,"mmm-yyyy")) -> 0 | N24: =SUMIFS(Banco[Monto],Banco[CtaCtbl],$C24,Banco[Periodo Contable],TEXT(N$3,"mmm-yyyy")) -> 0 | O24: =SUMIFS(Banco[Monto],Banco[CtaCtbl],$C24,Banco[Periodo Contable],TEXT(O$3,"mmm-yyyy")) -> 0 | P24: =SUMIFS(Banco[Monto],Banco[CtaCtbl],$C24,Banco[Periodo Contable],TEXT(P$3,"mmm-yyyy")) -> 0 | Q24: =SUMIFS(Banco[Monto],Banco[CtaCtbl],$C24,Banco[Periodo Contable],TEXT(Q$3,"mmm-yyyy")) -> 0 | ... U24: =SUMIFS(Banco[Monto],Banco[CtaCtbl],$C24,Banco[Periodo Contable],TEXT(U$3,"mmm-yyyy")) -> 0 | V24: =SUM(Tabla17[[#This Row],[ene-22]:[dic-22]]) -> 0 | W24: =SUMIFS(Banco[Monto],Banco[CtaCtbl],$C24,Banco[Periodo Contable],TEXT(W$3,"mmm-yyyy")) -> 0 | X24: =SUMIFS(Banco[Monto],Banco[CtaCtbl],$C24,Banco[Periodo Contable],TEXT(X$3,"mmm-yyyy")) -> 0 | Y24: =SUMIFS(Banco[Monto],Banco[CtaCtbl],$C24,Banco[Periodo Contable],TEXT(Y$3,"mmm-yyyy")) -> 0 | Z24: =SUMIFS(Banco[Monto],Banco[CtaCtbl],$C24,Banco[Periodo Contable],TEXT(Z$3,"mmm-yyyy")) -> 0 | AA24: =SUMIFS(Banco[Monto],Banco[CtaCtbl],$C24,Banco[Periodo Contable],TEXT(AA$3,"mmm-yyyy")) -> 0 | AB24: =SUMIFS(Banco[Monto],Banco[CtaCtbl],$C24,Banco[Periodo Contable],TEXT(AB$3,"mmm-yyyy")) -> 0 | AC24: =SUMIFS(Banco[Monto],Banco[CtaCtbl],$C24,Banco[Periodo Contable],TEXT(AC$3,"mmm-yyyy")) -> 0 | AD24: =SUMIFS(Banco[Monto],Banco[CtaCtbl],$C24,Banco[Periodo Contable],TEXT(AD$3,"mmm-yyyy")) -> 0 | ... AH24: =SUMIFS(Banco[Monto],Banco[CtaCtbl],$C24,Banco[Periodo Contable],TEXT(AH$3,"mmm-yyyy")) -> 0 | AI24: =SUM(Tabla17[[#This Row],[ene-23]:[dic-23]]) -> 0 | AJ24: =SUMIFS(Banco[Monto],Banco[CtaCtbl],$C24,Banco[Periodo Contable],TEXT(AJ$3,"mmm-yyyy")) -> 0 | AK24: =SUMIFS(Banco[Monto],Banco[CtaCtbl],$C24,Banco[Periodo Contable],TEXT(AK$3,"mmm-yyyy")) -> 0 | AL24: =SUMIFS(Banco[Monto],Banco[CtaCtbl],$C24,Banco[Periodo Contable],TEXT(AL$3,"mmm-yyyy")) -> 0 | AM24: =SUMIFS(Banco[Monto],Banco[CtaCtbl],$C24,Banco[Periodo Contable],TEXT(AM$3,"mmm-yyyy")) -> 0 | AN24: =SUMIFS(Banco[Monto],Banco[CtaCtbl],$C24,Banco[Periodo Contable],TEXT(AN$3,"mmm-yyyy")) -> 0 | AO24: =SUMIFS(Banco[Monto],Banco[CtaCtbl],$C24,Banco[Periodo Contable],TEXT(AO$3,"mmm-yyyy")) -> 0 | AP24: =SUMIFS(Banco[Monto],Banco[CtaCtbl],$C24,Banco[Periodo Contable],TEXT(AP$3,"mmm-yyyy")) -> 0 | AQ24: =SUMIFS(Banco[Monto],Banco[CtaCtbl],$C24,Banco[Periodo Contable],TEXT(AQ$3,"mmm-yyyy")) -> 0 | ... AU24: =SUMIFS(Banco[Monto],Banco[CtaCtbl],$C24,Banco[Periodo Contable],TEXT(AU$3,"mmm-yyyy")) -> 0 | AV24: =SUM(Tabla17[[#This Row],[ene-24]:[dic-24]]) -> 0 | AW24: =SUMIFS(Banco[Monto],Banco[CtaCtbl],$C24,Banco[Periodo Contable],TEXT(AW$3,"mmm-yyyy")) -> 0 | AX24: =SUMIFS(Banco[Monto],Banco[CtaCtbl],$C24,Banco[Periodo Contable],TEXT(AX$3,"mmm-yyyy")) -> 0 | AY24: =SUMIFS(Banco[Monto],Banco[CtaCtbl],$C24,Banco[Periodo Contable],TEXT(AY$3,"mmm-yyyy")) -> 0 | AZ24: =SUMIFS(Banco[Monto],Banco[CtaCtbl],$C24,Banco[Periodo Contable],TEXT(AZ$3,"mmm-yyyy")) -> 0 | BA24: =SUMIFS(Banco[Monto],Banco[CtaCtbl],$C24,Banco[Periodo Contable],TEXT(BA$3,"mmm-yyyy")) -> 0 | BB24: =SUMIFS(Banco[Monto],Banco[CtaCtbl],$C24,Banco[Periodo Contable],TEXT(BB$3,"mmm-yyyy")) -> 0 | BC24: =SUMIFS(Banco[Monto],Banco[CtaCtbl],$C24,Banco[Periodo Contable],TEXT(BC$3,"mmm-yyyy")) -> 0 | BD24: =SUMIFS(Banco[Monto],Banco[CtaCtbl],$C24,Banco[Periodo Contable],TEXT(BD$3,"mmm-yyyy")) -> 0 | ... BH24: =SUMIFS(Banco[Monto],Banco[CtaCtbl],$C24,Banco[Periodo Contable],TEXT(BH$3,"mmm-yyyy")) -> 0 | BI24: =SUM(Tabla17[[#This Row],[ene-25]:[dic-25]]) -> 0 | BJ24: =SUMIFS(Banco[Monto],Banco[CtaCtbl],$C24,Banco[Periodo Contable],TEXT(BJ$3,"mmm-yyyy")) -> 0 | BK24: =SUMIFS(Banco[Monto],Banco[CtaCtbl],$C24,Banco[Periodo Contable],TEXT(BK$3,"mmm-yyyy")) -> 0 | BL24: =SUMIFS(Banco[Monto],Banco[CtaCtbl],$C24,Banco[Periodo Contable],TEXT(BL$3,"mmm-yyyy")) -> 0 | BM24: =SUMIFS(Banco[Monto],Banco[CtaCtbl],$C24,Banco[Periodo Contable],TEXT(BM$3,"mmm-yyyy")) -> 0 | BN24: =SUMIFS(Banco[Monto],Banco[CtaCtbl],$C24,Banco[Periodo Contable],TEXT(BN$3,"mmm-yyyy")) -> 0 | BO24: =SUMIFS(Banco[Monto],Banco[CtaCtbl],$C24,Banco[Periodo Contable],TEXT(BO$3,"mmm-yyyy")) -> 0 | BP24: =SUMIFS(Banco[Monto],Banco[CtaCtbl],$C24,Banco[Periodo Contable],TEXT(BP$3,"mmm-yyyy")) -> 0 | BQ24: =SUMIFS(Banco[Monto],Banco[CtaCtbl],$C24,Banco[Periodo Contable],TEXT(BQ$3,"mmm-yyyy")) -> 0 | ... BU24: =SUMIFS(Banco[Monto],Banco[CtaCtbl],$C24,Banco[Periodo Contable],TEXT(BU$3,"mmm-yyyy")) -> 0 | BV24: =SUM(Tabla17[[#This Row],[ene-26]:[dic-26]]) -> 0 | BW24: =SUMIFS(Banco[Monto],Banco[CtaCtbl],$C24,Banco[Periodo Contable],TEXT(BW$3,"mmm-yyyy")) -> 0
A25: 2 | B25: Egresos | C25: =+Tabla17[[#This Row],[Cuenta]]&" - "&Tabla17[[#This Row],[Descripcion Cuenta]] -> 2 - Egresos | E25: =SUBTOTAL(9,E26:E83) -> 0 | F25: =SUBTOTAL(9,F26:F83) -> 0 | G25: =SUBTOTAL(9,G26:G83) -> -723071 | H25: =SUBTOTAL(9,H26:H83) -> -113400 | I25: =SUM(Tabla17[[#This Row],[sept-21]:[dic-21]]) -> -836471 | J25: =SUBTOTAL(9,J26:J83) -> -554937 | K25: =SUBTOTAL(9,K26:K83) -> -208149 | L25: =SUBTOTAL(9,L26:L83) -> -2125916 | M25: =SUBTOTAL(9,M26:M83) -> -3976249 | N25: =SUBTOTAL(9,N26:N83) -> -680172 | O25: =SUBTOTAL(9,O26:O83) -> -109500000 | P25: =SUBTOTAL(9,P26:P83) -> 0 | Q25: =SUBTOTAL(9,Q26:Q83) -> -510630 | ... BW25: =SUBTOTAL(9,BW26:BW83) -> 0
A26: 2.01 | B26: Gasto Fijo | C26: =+Tabla17[[#This Row],[Cuenta]]&" - "&Tabla17[[#This Row],[Descripcion Cuenta]] -> 2.01 - Gasto Fijo | E26: =SUBTOTAL(9,E27:E66) -> 0 | F26: =SUBTOTAL(9,F27:F66) -> 0 | G26: =SUBTOTAL(9,G27:G66) -> -723071 | H26: =SUBTOTAL(9,H27:H66) -> -113400 | I26: =SUM(Tabla17[[#This Row],[sept-21]:[dic-21]]) -> -836471 | J26: =SUBTOTAL(9,J27:J66) -> -554937 | K26: =SUBTOTAL(9,K27:K66) -> -208149 | L26: =SUBTOTAL(9,L27:L66) -> -2110100 | M26: =SUBTOTAL(9,M27:M66) -> -3960643 | N26: =SUBTOTAL(9,N27:N66) -> -680172 | O26: =SUBTOTAL(9,O27:O66) -> 0 | P26: =SUBTOTAL(9,P27:P66) -> 0 | Q26: =SUBTOTAL(9,Q27:Q66) -> -510630 | ... BW26: =SUBTOTAL(9,BW27:BW66) -> 0
A27: 2.01.01 | B27: Asesorias | C27: =+Tabla17[[#This Row],[Cuenta]]&" - "&Tabla17[[#This Row],[Descripcion Cuenta]] -> 2.01.01 - Asesorias | E27: =SUBTOTAL(9,E28:E33) -> 0 | F27: =SUBTOTAL(9,F28:F33) -> 0 | G27: =SUBTOTAL(9,G28:G33) -> -108500 | H27: =SUBTOTAL(9,H28:H33) -> -113400 | I27: =SUM(Tabla17[[#This Row],[sept-21]:[dic-21]]) -> -221900 | J27: =SUBTOTAL(9,J28:J33) -> -121100 | K27: =SUBTOTAL(9,K28:K33) -> -88200 | L27: =SUBTOTAL(9,L28:L33) -> -2107800 | M27: =SUBTOTAL(9,M28:M33) -> -3221600 | N27: =SUBTOTAL(9,N28:N33) -> -299600 | O27: =SUBTOTAL(9,O28:O33) -> 0 | P27: =SUBTOTAL(9,P28:P33) -> 0 | Q27: =SUBTOTAL(9,Q28:Q33) -> -449400 | ... BW27: =SUBTOTAL(9,BW28:BW33) -> 0
A28: 2.01.01.01 | B28: Legales | C28: =+Tabla17[[#This Row],[Cuenta]]&" - "&Tabla17[[#This Row],[Descripcion Cuenta]] -> 2.01.01.01 - Legales | E28: =SUBTOTAL(9,E29:E30) -> 0 | F28: =SUBTOTAL(9,F29:F30) -> 0 | G28: =SUBTOTAL(9,G29:G30) -> -108500 | H28: =SUBTOTAL(9,H29:H30) -> -113400 | I28: =SUM(Tabla17[[#This Row],[sept-21]:[dic-21]]) -> -221900 | J28: =SUBTOTAL(9,J29:J30) -> -121100 | K28: =SUBTOTAL(9,K29:K30) -> -88200 | L28: =SUBTOTAL(9,L29:L30) -> -2107800 | M28: =SUBTOTAL(9,M29:M30) -> -3221600 | N28: =SUBTOTAL(9,N29:N30) -> -299600 | O28: =SUBTOTAL(9,O29:O30) -> 0 | P28: =SUBTOTAL(9,P29:P30) -> 0 | Q28: =SUBTOTAL(9,Q29:Q30) -> -449400 | ... BW28: =SUBTOTAL(9,BW29:BW30) -> 0
A29: 2.01.01.01.1 | B29: Asesoria Legal - Convenio Fijo Mensual | C29: =+Tabla17[[#This Row],[Cuenta]]&" - "&Tabla17[[#This Row],[Descripcion Cuenta]] -> 2.01.01.01.1 - Asesoria Legal - Convenio Fijo Mensual | E29: =SUMIFS(Banco[Monto],Banco[CtaCtbl],$C29,Banco[Periodo Contable],TEXT(E$3,"mmm-yyyy")) -> 0 | F29: =SUMIFS(Banco[Monto],Banco[CtaCtbl],$C29,Banco[Periodo Contable],TEXT(F$3,"mmm-yyyy")) -> 0 | G29: =SUMIFS(Banco[Monto],Banco[CtaCtbl],$C29,Banco[Periodo Contable],TEXT(G$3,"mmm-yyyy")) -> -108500 | H29: =SUMIFS(Banco[Monto],Banco[CtaCtbl],$C29,Banco[Periodo Contable],TEXT(H$3,"mmm-yyyy")) -> -113400 | I29: =SUM(Tabla17[[#This Row],[sept-21]:[dic-21]]) -> -221900 | J29: =SUMIFS(Banco[Monto],Banco[CtaCtbl],$C29,Banco[Periodo Contable],TEXT(J$3,"mmm-yyyy")) -> -121100 | K29: =SUMIFS(Banco[Monto],Banco[CtaCtbl],$C29,Banco[Periodo Contable],TEXT(K$3,"mmm-yyyy")) -> -88200 | L29: =SUMIFS(Banco[Monto],Banco[CtaCtbl],$C29,Banco[Periodo Contable],TEXT(L$3,"mmm-yyyy")) -> -107800 | M29: =SUMIFS(Banco[Monto],Banco[CtaCtbl],$C29,Banco[Periodo Contable],TEXT(M$3,"mmm-yyyy")) -> -149800 | N29: =SUMIFS(Banco[Monto],Banco[CtaCtbl],$C29,Banco[Periodo Contable],TEXT(N$3,"mmm-yyyy")) -> -299600 | O29: =SUMIFS(Banco[Monto],Banco[CtaCtbl],$C29,Banco[Periodo Contable],TEXT(O$3,"mmm-yyyy")) -> 0 | P29: =SUMIFS(Banco[Monto],Banco[CtaCtbl],$C29,Banco[Periodo Contable],TEXT(P$3,"mmm-yyyy")) -> 0 | Q29: =SUMIFS(Banco[Monto],Banco[CtaCtbl],$C29,Banco[Periodo Contable],TEXT(Q$3,"mmm-yyyy")) -> -449400 | ... U29: =SUMIFS(Banco[Monto],Banco[CtaCtbl],$C29,Banco[Periodo Contable],TEXT(U$3,"mmm-yyyy")) -> 0 | V29: =SUM(Tabla17[[#This Row],[ene-22]:[dic-22]]) -> -1665300 | W29: =SUMIFS(Banco[Monto],Banco[CtaCtbl],$C29,Banco[Periodo Contable],TEXT(W$3,"mmm-yyyy")) -> 0 | X29: =SUMIFS(Banco[Monto],Banco[CtaCtbl],$C29,Banco[Periodo Contable],TEXT(X$3,"mmm-yyyy")) -> -218440 | Y29: =SUMIFS(Banco[Monto],Banco[CtaCtbl],$C29,Banco[Periodo Contable],TEXT(Y$3,"mmm-yyyy")) -> 0 | Z29: =SUMIFS(Banco[Monto],Banco[CtaCtbl],$C29,Banco[Periodo Contable],TEXT(Z$3,"mmm-yyyy")) -> -448920 | AA29: =SUMIFS(Banco[Monto],Banco[CtaCtbl],$C29,Banco[Periodo Contable],TEXT(AA$3,"mmm-yyyy")) -> -161160 | AB29: =SUMIFS(Banco[Monto],Banco[CtaCtbl],$C29,Banco[Periodo Contable],TEXT(AB$3,"mmm-yyyy")) -> 0 | AC29: =SUMIFS(Banco[Monto],Banco[CtaCtbl],$C29,Banco[Periodo Contable],TEXT(AC$3,"mmm-yyyy")) -> -319160 | AD29: =SUMIFS(Banco[Monto],Banco[CtaCtbl],$C29,Banco[Periodo Contable],TEXT(AD$3,"mmm-yyyy")) -> 0 | ... AH29: =SUMIFS(Banco[Monto],Banco[CtaCtbl],$C29,Banco[Periodo Contable],TEXT(AH$3,"mmm-yyyy")) -> 0 | AI29: =SUM(Tabla17[[#This Row],[ene-23]:[dic-23]]) -> -1786000 | AJ29: =SUMIFS(Banco[Monto],Banco[CtaCtbl],$C29,Banco[Periodo Contable],TEXT(AJ$3,"mmm-yyyy")) -> -328600 | AK29: =SUMIFS(Banco[Monto],Banco[CtaCtbl],$C29,Banco[Periodo Contable],TEXT(AK$3,"mmm-yyyy")) -> 0 | AL29: =SUMIFS(Banco[Monto],Banco[CtaCtbl],$C29,Banco[Periodo Contable],TEXT(AL$3,"mmm-yyyy")) -> -328720 | AM29: =SUMIFS(Banco[Monto],Banco[CtaCtbl],$C29,Banco[Periodo Contable],TEXT(AM$3,"mmm-yyyy")) -> 0 | AN29: =SUMIFS(Banco[Monto],Banco[CtaCtbl],$C29,Banco[Periodo Contable],TEXT(AN$3,"mmm-yyyy")) -> -163340 | AO29: =SUMIFS(Banco[Monto],Banco[CtaCtbl],$C29,Banco[Periodo Contable],TEXT(AO$3,"mmm-yyyy")) -> -484720 | AP29: =SUMIFS(Banco[Monto],Banco[CtaCtbl],$C29,Banco[Periodo Contable],TEXT(AP$3,"mmm-yyyy")) -> 0 | AQ29: =SUMIFS(Banco[Monto],Banco[CtaCtbl],$C29,Banco[Periodo Contable],TEXT(AQ$3,"mmm-yyyy")) -> 0 | ... AU29: =SUMIFS(Banco[Monto],Banco[CtaCtbl],$C29,Banco[Periodo Contable],TEXT(AU$3,"mmm-yyyy")) -> 0 | AV29: =SUM(Tabla17[[#This Row],[ene-24]:[dic-24]]) -> -2168604 | AW29: =SUMIFS(Banco[Monto],Banco[CtaCtbl],$C29,Banco[Periodo Contable],TEXT(AW$3,"mmm-yyyy")) -> -444924 | AX29: =SUMIFS(Banco[Monto],Banco[CtaCtbl],$C29,Banco[Periodo Contable],TEXT(AX$3,"mmm-yyyy")) -> 0 | AY29: =SUMIFS(Banco[Monto],Banco[CtaCtbl],$C29,Banco[Periodo Contable],TEXT(AY$3,"mmm-yyyy")) -> 0 | AZ29: =SUMIFS(Banco[Monto],Banco[CtaCtbl],$C29,Banco[Periodo Contable],TEXT(AZ$3,"mmm-yyyy")) -> -667386 | BA29: =SUMIFS(Banco[Monto],Banco[CtaCtbl],$C29,Banco[Periodo Contable],TEXT(BA$3,"mmm-yyyy")) -> 0 | BB29: =SUMIFS(Banco[Monto],Banco[CtaCtbl],$C29,Banco[Periodo Contable],TEXT(BB$3,"mmm-yyyy")) -> -222462 | BC29: =SUMIFS(Banco[Monto],Banco[CtaCtbl],$C29,Banco[Periodo Contable],TEXT(BC$3,"mmm-yyyy")) -> 0 | BD29: =SUMIFS(Banco[Monto],Banco[CtaCtbl],$C29,Banco[Periodo Contable],TEXT(BD$3,"mmm-yyyy")) -> -700000 | ... BH29: =SUMIFS(Banco[Monto],Banco[CtaCtbl],$C29,Banco[Periodo Contable],TEXT(BH$3,"mmm-yyyy")) -> -1400000 | BI29: =SUM(Tabla17[[#This Row],[ene-25]:[dic-25]]) -> -4134772 | BJ29: =SUMIFS(Banco[Monto],Banco[CtaCtbl],$C29,Banco[Periodo Contable],TEXT(BJ$3,"mmm-yyyy")) -> 0 | BK29: =SUMIFS(Banco[Monto],Banco[CtaCtbl],$C29,Banco[Periodo Contable],TEXT(BK$3,"mmm-yyyy")) -> 0 | BL29: =SUMIFS(Banco[Monto],Banco[CtaCtbl],$C29,Banco[Periodo Contable],TEXT(BL$3,"mmm-yyyy")) -> 0 | BM29: =SUMIFS(Banco[Monto],Banco[CtaCtbl],$C29,Banco[Periodo Contable],TEXT(BM$3,"mmm-yyyy")) -> 0 | BN29: =SUMIFS(Banco[Monto],Banco[CtaCtbl],$C29,Banco[Periodo Contable],TEXT(BN$3,"mmm-yyyy")) -> 0 | BO29: =SUMIFS(Banco[Monto],Banco[CtaCtbl],$C29,Banco[Periodo Contable],TEXT(BO$3,"mmm-yyyy")) -> 0 | BP29: =SUMIFS(Banco[Monto],Banco[CtaCtbl],$C29,Banco[Periodo Contable],TEXT(BP$3,"mmm-yyyy")) -> 0 | BQ29: =SUMIFS(Banco[Monto],Banco[CtaCtbl],$C29,Banco[Periodo Contable],TEXT(BQ$3,"mmm-yyyy")) -> 0 | ... BU29: =SUMIFS(Banco[Monto],Banco[CtaCtbl],$C29,Banco[Periodo Contable],TEXT(BU$3,"mmm-yyyy")) -> 0 | BV29: =SUM(Tabla17[[#This Row],[ene-26]:[dic-26]]) -> 0 | BW29: =SUMIFS(Banco[Monto],Banco[CtaCtbl],$C29,Banco[Periodo Contable],TEXT(BW$3,"mmm-yyyy")) -> 0
A30: 2.01.01.01.2 | B30: Asesoria Legal - Proyectos Negociacion | C30: =+Tabla17[[#This Row],[Cuenta]]&" - "&Tabla17[[#This Row],[Descripcion Cuenta]] -> 2.01.01.01.2 - Asesoria Legal - Proyectos Negociacion | E30: =SUMIFS(Banco[Monto],Banco[CtaCtbl],$C30,Banco[Periodo Contable],TEXT(E$3,"mmm-yyyy")) -> 0 | F30: =SUMIFS(Banco[Monto],Banco[CtaCtbl],$C30,Banco[Periodo Contable],TEXT(F$3,"mmm-yyyy")) -> 0 | G30: =SUMIFS(Banco[Monto],Banco[CtaCtbl],$C30,Banco[Periodo Contable],TEXT(G$3,"mmm-yyyy")) -> 0 | H30: =SUMIFS(Banco[Monto],Banco[CtaCtbl],$C30,Banco[Periodo Contable],TEXT(H$3,"mmm-yyyy")) -> 0 | I30: =SUM(Tabla17[[#This Row],[sept-21]:[dic-21]]) -> 0 | J30: =SUMIFS(Banco[Monto],Banco[CtaCtbl],$C30,Banco[Periodo Contable],TEXT(J$3,"mmm-yyyy")) -> 0 | K30: =SUMIFS(Banco[Monto],Banco[CtaCtbl],$C30,Banco[Periodo Contable],TEXT(K$3,"mmm-yyyy")) -> 0 | L30: =SUMIFS(Banco[Monto],Banco[CtaCtbl],$C30,Banco[Periodo Contable],TEXT(L$3,"mmm-yyyy")) -> -2000000 | M30: =SUMIFS(Banco[Monto],Banco[CtaCtbl],$C30,Banco[Periodo Contable],TEXT(M$3,"mmm-yyyy")) -> -3071800 | N30: =SUMIFS(Banco[Monto],Banco[CtaCtbl],$C30,Banco[Periodo Contable],TEXT(N$3,"mmm-yyyy")) -> 0 | O30: =SUMIFS(Banco[Monto],Banco[CtaCtbl],$C30,Banco[Periodo Contable],TEXT(O$3,"mmm-yyyy")) -> 0 | P30: =SUMIFS(Banco[Monto],Banco[CtaCtbl],$C30,Banco[Periodo Contable],TEXT(P$3,"mmm-yyyy")) -> 0 | Q30: =SUMIFS(Banco[Monto],Banco[CtaCtbl],$C30,Banco[Periodo Contable],TEXT(Q$3,"mmm-yyyy")) -> 0 | ... U30: =SUMIFS(Banco[Monto],Banco[CtaCtbl],$C30,Banco[Periodo Contable],TEXT(U$3,"mmm-yyyy")) -> 0 | V30: =SUM(Tabla17[[#This Row],[ene-22]:[dic-22]]) -> -5071800 | W30: =SUMIFS(Banco[Monto],Banco[CtaCtbl],$C30,Banco[Periodo Contable],TEXT(W$3,"mmm-yyyy")) -> 0 | X30: =SUMIFS(Banco[Monto],Banco[CtaCtbl],$C30,Banco[Periodo Contable],TEXT(X$3,"mmm-yyyy")) -> 0 | Y30: =SUMIFS(Banco[Monto],Banco[CtaCtbl],$C30,Banco[Periodo Contable],TEXT(Y$3,"mmm-yyyy")) -> 0 | Z30: =SUMIFS(Banco[Monto],Banco[CtaCtbl],$C30,Banco[Periodo Contable],TEXT(Z$3,"mmm-yyyy")) -> 0 | AA30: =SUMIFS(Banco[Monto],Banco[CtaCtbl],$C30,Banco[Periodo Contable],TEXT(AA$3,"mmm-yyyy")) -> 0 | AB30: =SUMIFS(Banco[Monto],Banco[CtaCtbl],$C30,Banco[Periodo Contable],TEXT(AB$3,"mmm-yyyy")) -> 0 | AC30: =SUMIFS(Banco[Monto],Banco[CtaCtbl],$C30,Banco[Periodo Contable],TEXT(AC$3,"mmm-yyyy")) -> 0 | AD30: =SUMIFS(Banco[Monto],Banco[CtaCtbl],$C30,Banco[Periodo Contable],TEXT(AD$3,"mmm-yyyy")) -> 0 | ... AH30: =SUMIFS(Banco[Monto],Banco[CtaCtbl],$C30,Banco[Periodo Contable],TEXT(AH$3,"mmm-yyyy")) -> 0 | AI30: =SUM(Tabla17[[#This Row],[ene-23]:[dic-23]]) -> 0 | AJ30: =SUMIFS(Banco[Monto],Banco[CtaCtbl],$C30,Banco[Periodo Contable],TEXT(AJ$3,"mmm-yyyy")) -> 0 | AK30: =SUMIFS(Banco[Monto],Banco[CtaCtbl],$C30,Banco[Periodo Contable],TEXT(AK$3,"mmm-yyyy")) -> 0 | AL30: =SUMIFS(Banco[Monto],Banco[CtaCtbl],$C30,Banco[Periodo Contable],TEXT(AL$3,"mmm-yyyy")) -> 0 | AM30: =SUMIFS(Banco[Monto],Banco[CtaCtbl],$C30,Banco[Periodo Contable],TEXT(AM$3,"mmm-yyyy")) -> 0 | AN30: =SUMIFS(Banco[Monto],Banco[CtaCtbl],$C30,Banco[Periodo Contable],TEXT(AN$3,"mmm-yyyy")) -> 0 | AO30: =SUMIFS(Banco[Monto],Banco[CtaCtbl],$C30,Banco[Periodo Contable],TEXT(AO$3,"mmm-yyyy")) -> 0 | AP30: =SUMIFS(Banco[Monto],Banco[CtaCtbl],$C30,Banco[Periodo Contable],TEXT(AP$3,"mmm-yyyy")) -> 0 | AQ30: =SUMIFS(Banco[Monto],Banco[CtaCtbl],$C30,Banco[Periodo Contable],TEXT(AQ$3,"mmm-yyyy")) -> 0 | ... AU30: =SUMIFS(Banco[Monto],Banco[CtaCtbl],$C30,Banco[Periodo Contable],TEXT(AU$3,"mmm-yyyy")) -> 0 | AV30: =SUM(Tabla17[[#This Row],[ene-24]:[dic-24]]) -> 0 | AW30: =SUMIFS(Banco[Monto],Banco[CtaCtbl],$C30,Banco[Periodo Contable],TEXT(AW$3,"mmm-yyyy")) -> 0 | AX30: =SUMIFS(Banco[Monto],Banco[CtaCtbl],$C30,Banco[Periodo Contable],TEXT(AX$3,"mmm-yyyy")) -> -5000000 | AY30: =SUMIFS(Banco[Monto],Banco[CtaCtbl],$C30,Banco[Periodo Contable],TEXT(AY$3,"mmm-yyyy")) -> 0 | AZ30: =SUMIFS(Banco[Monto],Banco[CtaCtbl],$C30,Banco[Periodo Contable],TEXT(AZ$3,"mmm-yyyy")) -> -6950000 | BA30: =SUMIFS(Banco[Monto],Banco[CtaCtbl],$C30,Banco[Periodo Contable],TEXT(BA$3,"mmm-yyyy")) -> 0 | BB30: =SUMIFS(Banco[Monto],Banco[CtaCtbl],$C30,Banco[Periodo Contable],TEXT(BB$3,"mmm-yyyy")) -> 0 | BC30: =SUMIFS(Banco[Monto],Banco[CtaCtbl],$C30,Banco[Periodo Contable],TEXT(BC$3,"mmm-yyyy")) -> 0 | BD30: =SUMIFS(Banco[Monto],Banco[CtaCtbl],$C30,Banco[Periodo Contable],TEXT(BD$3,"mmm-yyyy")) -> 0 | ... BH30: =SUMIFS(Banco[Monto],Banco[CtaCtbl],$C30,Banco[Periodo Contable],TEXT(BH$3,"mmm-yyyy")) -> 0 | BI30: =SUM(Tabla17[[#This Row],[ene-25]:[dic-25]]) -> -11950000 | BJ30: =SUMIFS(Banco[Monto],Banco[CtaCtbl],$C30,Banco[Periodo Contable],TEXT(BJ$3,"mmm-yyyy")) -> 0 | BK30: =SUMIFS(Banco[Monto],Banco[CtaCtbl],$C30,Banco[Periodo Contable],TEXT(BK$3,"mmm-yyyy")) -> 0 | BL30: =SUMIFS(Banco[Monto],Banco[CtaCtbl],$C30,Banco[Periodo Contable],TEXT(BL$3,"mmm-yyyy")) -> 0 | BM30: =SUMIFS(Banco[Monto],Banco[CtaCtbl],$C30,Banco[Periodo Contable],TEXT(BM$3,"mmm-yyyy")) -> 0 | BN30: =SUMIFS(Banco[Monto],Banco[CtaCtbl],$C30,Banco[Periodo Contable],TEXT(BN$3,"mmm-yyyy")) -> 0 | BO30: =SUMIFS(Banco[Monto],Banco[CtaCtbl],$C30,Banco[Periodo Contable],TEXT(BO$3,"mmm-yyyy")) -> 0 | BP30: =SUMIFS(Banco[Monto],Banco[CtaCtbl],$C30,Banco[Periodo Contable],TEXT(BP$3,"mmm-yyyy")) -> 0 | BQ30: =SUMIFS(Banco[Monto],Banco[CtaCtbl],$C30,Banco[Periodo Contable],TEXT(BQ$3,"mmm-yyyy")) -> 0 | ... BU30: =SUMIFS(Banco[Monto],Banco[CtaCtbl],$C30,Banco[Periodo Contable],TEXT(BU$3,"mmm-yyyy")) -> 0 | BV30: =SUM(Tabla17[[#This Row],[ene-26]:[dic-26]]) -> 0 | BW30: =SUMIFS(Banco[Monto],Banco[CtaCtbl],$C30,Banco[Periodo Contable],TEXT(BW$3,"mmm-yyyy")) -> 0
A31: 2.01.01.02 | B31: Contables | C31: =+Tabla17[[#This Row],[Cuenta]]&" - "&Tabla17[[#This Row],[Descripcion Cuenta]] -> 2.01.01.02 - Contables | E31: =SUMIFS(Banco[Monto],Banco[CtaCtbl],$C31,Banco[Periodo Contable],TEXT(E$3,"mmm-yyyy")) -> 0 | F31: =SUMIFS(Banco[Monto],Banco[CtaCtbl],$C31,Banco[Periodo Contable],TEXT(F$3,"mmm-yyyy")) -> 0 | G31: =SUMIFS(Banco[Monto],Banco[CtaCtbl],$C31,Banco[Periodo Contable],TEXT(G$3,"mmm-yyyy")) -> 0 | H31: =SUMIFS(Banco[Monto],Banco[CtaCtbl],$C31,Banco[Periodo Contable],TEXT(H$3,"mmm-yyyy")) -> 0 | I31: =SUM(Tabla17[[#This Row],[sept-21]:[dic-21]]) -> 0 | J31: =SUMIFS(Banco[Monto],Banco[CtaCtbl],$C31,Banco[Periodo Contable],TEXT(J$3,"mmm-yyyy")) -> 0 | K31: =SUMIFS(Banco[Monto],Banco[CtaCtbl],$C31,Banco[Periodo Contable],TEXT(K$3,"mmm-yyyy")) -> 0 | L31: =SUMIFS(Banco[Monto],Banco[CtaCtbl],$C31,Banco[Periodo Contable],TEXT(L$3,"mmm-yyyy")) -> 0 | M31: =SUMIFS(Banco[Monto],Banco[CtaCtbl],$C31,Banco[Periodo Contable],TEXT(M$3,"mmm-yyyy")) -> 0 | N31: =SUMIFS(Banco[Monto],Banco[CtaCtbl],$C31,Banco[Periodo Contable],TEXT(N$3,"mmm-yyyy")) -> 0 | O31: =SUMIFS(Banco[Monto],Banco[CtaCtbl],$C31,Banco[Periodo Contable],TEXT(O$3,"mmm-yyyy")) -> 0 | P31: =SUMIFS(Banco[Monto],Banco[CtaCtbl],$C31,Banco[Periodo Contable],TEXT(P$3,"mmm-yyyy")) -> 0 | Q31: =SUMIFS(Banco[Monto],Banco[CtaCtbl],$C31,Banco[Periodo Contable],TEXT(Q$3,"mmm-yyyy")) -> 0 | ... U31: =SUMIFS(Banco[Monto],Banco[CtaCtbl],$C31,Banco[Periodo Contable],TEXT(U$3,"mmm-yyyy")) -> 0 | V31: =SUM(Tabla17[[#This Row],[ene-22]:[dic-22]]) -> 0 | W31: =SUMIFS(Banco[Monto],Banco[CtaCtbl],$C31,Banco[Periodo Contable],TEXT(W$3,"mmm-yyyy")) -> 0 | X31: =SUMIFS(Banco[Monto],Banco[CtaCtbl],$C31,Banco[Periodo Contable],TEXT(X$3,"mmm-yyyy")) -> 0 | Y31: =SUMIFS(Banco[Monto],Banco[CtaCtbl],$C31,Banco[Periodo Contable],TEXT(Y$3,"mmm-yyyy")) -> 0 | Z31: =SUMIFS(Banco[Monto],Banco[CtaCtbl],$C31,Banco[Periodo Contable],TEXT(Z$3,"mmm-yyyy")) -> 0 | AA31: =SUMIFS(Banco[Monto],Banco[CtaCtbl],$C31,Banco[Periodo Contable],TEXT(AA$3,"mmm-yyyy")) -> 0 | AB31: =SUMIFS(Banco[Monto],Banco[CtaCtbl],$C31,Banco[Periodo Contable],TEXT(AB$3,"mmm-yyyy")) -> 0 | AC31: =SUMIFS(Banco[Monto],Banco[CtaCtbl],$C31,Banco[Periodo Contable],TEXT(AC$3,"mmm-yyyy")) -> 0 | AD31: =SUMIFS(Banco[Monto],Banco[CtaCtbl],$C31,Banco[Periodo Contable],TEXT(AD$3,"mmm-yyyy")) -> 0 | ... AH31: =SUMIFS(Banco[Monto],Banco[CtaCtbl],$C31,Banco[Periodo Contable],TEXT(AH$3,"mmm-yyyy")) -> 0 | AI31: =SUM(Tabla17[[#This Row],[ene-23]:[dic-23]]) -> 0 | AJ31: =SUMIFS(Banco[Monto],Banco[CtaCtbl],$C31,Banco[Periodo Contable],TEXT(AJ$3,"mmm-yyyy")) -> 0 | AK31: =SUMIFS(Banco[Monto],Banco[CtaCtbl],$C31,Banco[Periodo Contable],TEXT(AK$3,"mmm-yyyy")) -> 0 | AL31: =SUMIFS(Banco[Monto],Banco[CtaCtbl],$C31,Banco[Periodo Contable],TEXT(AL$3,"mmm-yyyy")) -> 0 | AM31: =SUMIFS(Banco[Monto],Banco[CtaCtbl],$C31,Banco[Periodo Contable],TEXT(AM$3,"mmm-yyyy")) -> 0 | AN31: =SUMIFS(Banco[Monto],Banco[CtaCtbl],$C31,Banco[Periodo Contable],TEXT(AN$3,"mmm-yyyy")) -> 0 | AO31: =SUMIFS(Banco[Monto],Banco[CtaCtbl],$C31,Banco[Periodo Contable],TEXT(AO$3,"mmm-yyyy")) -> 0 | AP31: =SUMIFS(Banco[Monto],Banco[CtaCtbl],$C31,Banco[Periodo Contable],TEXT(AP$3,"mmm-yyyy")) -> 0 | AQ31: =SUMIFS(Banco[Monto],Banco[CtaCtbl],$C31,Banco[Periodo Contable],TEXT(AQ$3,"mmm-yyyy")) -> 0 | ... AU31: =SUMIFS(Banco[Monto],Banco[CtaCtbl],$C31,Banco[Periodo Contable],TEXT(AU$3,"mmm-yyyy")) -> 0 | AV31: =SUM(Tabla17[[#This Row],[ene-24]:[dic-24]]) -> 0 | AW31: =SUMIFS(Banco[Monto],Banco[CtaCtbl],$C31,Banco[Periodo Contable],TEXT(AW$3,"mmm-yyyy")) -> 0 | AX31: =SUMIFS(Banco[Monto],Banco[CtaCtbl],$C31,Banco[Periodo Contable],TEXT(AX$3,"mmm-yyyy")) -> 0 | AY31: =SUMIFS(Banco[Monto],Banco[CtaCtbl],$C31,Banco[Periodo Contable],TEXT(AY$3,"mmm-yyyy")) -> 0 | AZ31: =SUMIFS(Banco[Monto],Banco[CtaCtbl],$C31,Banco[Periodo Contable],TEXT(AZ$3,"mmm-yyyy")) -> 0 | BA31: =SUMIFS(Banco[Monto],Banco[CtaCtbl],$C31,Banco[Periodo Contable],TEXT(BA$3,"mmm-yyyy")) -> 0 | BB31: =SUMIFS(Banco[Monto],Banco[CtaCtbl],$C31,Banco[Periodo Contable],TEXT(BB$3,"mmm-yyyy")) -> 0 | BC31: =SUMIFS(Banco[Monto],Banco[CtaCtbl],$C31,Banco[Periodo Contable],TEXT(BC$3,"mmm-yyyy")) -> 0 | BD31: =SUMIFS(Banco[Monto],Banco[CtaCtbl],$C31,Banco[Periodo Contable],TEXT(BD$3,"mmm-yyyy")) -> 0 | ... BH31: =SUMIFS(Banco[Monto],Banco[CtaCtbl],$C31,Banco[Periodo Contable],TEXT(BH$3,"mmm-yyyy")) -> 0 | BI31: =SUM(Tabla17[[#This Row],[ene-25]:[dic-25]]) -> 0 | BJ31: =SUMIFS(Banco[Monto],Banco[CtaCtbl],$C31,Banco[Periodo Contable],TEXT(BJ$3,"mmm-yyyy")) -> 0 | BK31: =SUMIFS(Banco[Monto],Banco[CtaCtbl],$C31,Banco[Periodo Contable],TEXT(BK$3,"mmm-yyyy")) -> 0 | BL31: =SUMIFS(Banco[Monto],Banco[CtaCtbl],$C31,Banco[Periodo Contable],TEXT(BL$3,"mmm-yyyy")) -> 0 | BM31: =SUMIFS(Banco[Monto],Banco[CtaCtbl],$C31,Banco[Periodo Contable],TEXT(BM$3,"mmm-yyyy")) -> 0 | BN31: =SUMIFS(Banco[Monto],Banco[CtaCtbl],$C31,Banco[Periodo Contable],TEXT(BN$3,"mmm-yyyy")) -> 0 | BO31: =SUMIFS(Banco[Monto],Banco[CtaCtbl],$C31,Banco[Periodo Contable],TEXT(BO$3,"mmm-yyyy")) -> 0 | BP31: =SUMIFS(Banco[Monto],Banco[CtaCtbl],$C31,Banco[Periodo Contable],TEXT(BP$3,"mmm-yyyy")) -> 0 | BQ31: =SUMIFS(Banco[Monto],Banco[CtaCtbl],$C31,Banco[Periodo Contable],TEXT(BQ$3,"mmm-yyyy")) -> 0 | ... BU31: =SUMIFS(Banco[Monto],Banco[CtaCtbl],$C31,Banco[Periodo Contable],TEXT(BU$3,"mmm-yyyy")) -> 0 | BV31: =SUM(Tabla17[[#This Row],[ene-26]:[dic-26]]) -> 0 | BW31: =SUMIFS(Banco[Monto],Banco[CtaCtbl],$C31,Banco[Periodo Contable],TEXT(BW$3,"mmm-yyyy")) -> 0
A32: 2.01.01.03 | B32: Expertos Legislacion Laboral | C32: =+Tabla17[[#This Row],[Cuenta]]&" - "&Tabla17[[#This Row],[Descripcion Cuenta]] -> 2.01.01.03 - Expertos Legislacion Laboral | E32: =SUMIFS(Banco[Monto],Banco[CtaCtbl],$C32,Banco[Periodo Contable],TEXT(E$3,"mmm-yyyy")) -> 0 | F32: =SUMIFS(Banco[Monto],Banco[CtaCtbl],$C32,Banco[Periodo Contable],TEXT(F$3,"mmm-yyyy")) -> 0 | G32: =SUMIFS(Banco[Monto],Banco[CtaCtbl],$C32,Banco[Periodo Contable],TEXT(G$3,"mmm-yyyy")) -> 0 | H32: =SUMIFS(Banco[Monto],Banco[CtaCtbl],$C32,Banco[Periodo Contable],TEXT(H$3,"mmm-yyyy")) -> 0 | I32: =SUM(Tabla17[[#This Row],[sept-21]:[dic-21]]) -> 0 | J32: =SUMIFS(Banco[Monto],Banco[CtaCtbl],$C32,Banco[Periodo Contable],TEXT(J$3,"mmm-yyyy")) -> 0 | K32: =SUMIFS(Banco[Monto],Banco[CtaCtbl],$C32,Banco[Periodo Contable],TEXT(K$3,"mmm-yyyy")) -> 0 | L32: =SUMIFS(Banco[Monto],Banco[CtaCtbl],$C32,Banco[Periodo Contable],TEXT(L$3,"mmm-yyyy")) -> 0 | M32: =SUMIFS(Banco[Monto],Banco[CtaCtbl],$C32,Banco[Periodo Contable],TEXT(M$3,"mmm-yyyy")) -> 0 | N32: =SUMIFS(Banco[Monto],Banco[CtaCtbl],$C32,Banco[Periodo Contable],TEXT(N$3,"mmm-yyyy")) -> 0 | O32: =SUMIFS(Banco[Monto],Banco[CtaCtbl],$C32,Banco[Periodo Contable],TEXT(O$3,"mmm-yyyy")) -> 0 | P32: =SUMIFS(Banco[Monto],Banco[CtaCtbl],$C32,Banco[Periodo Contable],TEXT(P$3,"mmm-yyyy")) -> 0 | Q32: =SUMIFS(Banco[Monto],Banco[CtaCtbl],$C32,Banco[Periodo Contable],TEXT(Q$3,"mmm-yyyy")) -> 0 | ... U32: =SUMIFS(Banco[Monto],Banco[CtaCtbl],$C32,Banco[Periodo Contable],TEXT(U$3,"mmm-yyyy")) -> 0 | V32: =SUM(Tabla17[[#This Row],[ene-22]:[dic-22]]) -> 0 | W32: =SUMIFS(Banco[Monto],Banco[CtaCtbl],$C32,Banco[Periodo Contable],TEXT(W$3,"mmm-yyyy")) -> 0 | X32: =SUMIFS(Banco[Monto],Banco[CtaCtbl],$C32,Banco[Periodo Contable],TEXT(X$3,"mmm-yyyy")) -> 0 | Y32: =SUMIFS(Banco[Monto],Banco[CtaCtbl],$C32,Banco[Periodo Contable],TEXT(Y$3,"mmm-yyyy")) -> 0 | Z32: =SUMIFS(Banco[Monto],Banco[CtaCtbl],$C32,Banco[Periodo Contable],TEXT(Z$3,"mmm-yyyy")) -> 0 | AA32: =SUMIFS(Banco[Monto],Banco[CtaCtbl],$C32,Banco[Periodo Contable],TEXT(AA$3,"mmm-yyyy")) -> 0 | AB32: =SUMIFS(Banco[Monto],Banco[CtaCtbl],$C32,Banco[Periodo Contable],TEXT(AB$3,"mmm-yyyy")) -> 0 | AC32: =SUMIFS(Banco[Monto],Banco[CtaCtbl],$C32,Banco[Periodo Contable],TEXT(AC$3,"mmm-yyyy")) -> 0 | AD32: =SUMIFS(Banco[Monto],Banco[CtaCtbl],$C32,Banco[Periodo Contable],TEXT(AD$3,"mmm-yyyy")) -> 0 | ... AH32: =SUMIFS(Banco[Monto],Banco[CtaCtbl],$C32,Banco[Periodo Contable],TEXT(AH$3,"mmm-yyyy")) -> 0 | AI32: =SUM(Tabla17[[#This Row],[ene-23]:[dic-23]]) -> 0 | AJ32: =SUMIFS(Banco[Monto],Banco[CtaCtbl],$C32,Banco[Periodo Contable],TEXT(AJ$3,"mmm-yyyy")) -> 0 | AK32: =SUMIFS(Banco[Monto],Banco[CtaCtbl],$C32,Banco[Periodo Contable],TEXT(AK$3,"mmm-yyyy")) -> 0 | AL32: =SUMIFS(Banco[Monto],Banco[CtaCtbl],$C32,Banco[Periodo Contable],TEXT(AL$3,"mmm-yyyy")) -> 0 | AM32: =SUMIFS(Banco[Monto],Banco[CtaCtbl],$C32,Banco[Periodo Contable],TEXT(AM$3,"mmm-yyyy")) -> 0 | AN32: =SUMIFS(Banco[Monto],Banco[CtaCtbl],$C32,Banco[Periodo Contable],TEXT(AN$3,"mmm-yyyy")) -> 0 | AO32: =SUMIFS(Banco[Monto],Banco[CtaCtbl],$C32,Banco[Periodo Contable],TEXT(AO$3,"mmm-yyyy")) -> 0 | AP32: =SUMIFS(Banco[Monto],Banco[CtaCtbl],$C32,Banco[Periodo Contable],TEXT(AP$3,"mmm-yyyy")) -> 0 | AQ32: =SUMIFS(Banco[Monto],Banco[CtaCtbl],$C32,Banco[Periodo Contable],TEXT(AQ$3,"mmm-yyyy")) -> 0 | ... AU32: =SUMIFS(Banco[Monto],Banco[CtaCtbl],$C32,Banco[Periodo Contable],TEXT(AU$3,"mmm-yyyy")) -> 0 | AV32: =SUM(Tabla17[[#This Row],[ene-24]:[dic-24]]) -> 0 | AW32: =SUMIFS(Banco[Monto],Banco[CtaCtbl],$C32,Banco[Periodo Contable],TEXT(AW$3,"mmm-yyyy")) -> 0 | AX32: =SUMIFS(Banco[Monto],Banco[CtaCtbl],$C32,Banco[Periodo Contable],TEXT(AX$3,"mmm-yyyy")) -> 0 | AY32: =SUMIFS(Banco[Monto],Banco[CtaCtbl],$C32,Banco[Periodo Contable],TEXT(AY$3,"mmm-yyyy")) -> 0 | AZ32: =SUMIFS(Banco[Monto],Banco[CtaCtbl],$C32,Banco[Periodo Contable],TEXT(AZ$3,"mmm-yyyy")) -> 0 | BA32: =SUMIFS(Banco[Monto],Banco[CtaCtbl],$C32,Banco[Periodo Contable],TEXT(BA$3,"mmm-yyyy")) -> 0 | BB32: =SUMIFS(Banco[Monto],Banco[CtaCtbl],$C32,Banco[Periodo Contable],TEXT(BB$3,"mmm-yyyy")) -> 0 | BC32: =SUMIFS(Banco[Monto],Banco[CtaCtbl],$C32,Banco[Periodo Contable],TEXT(BC$3,"mmm-yyyy")) -> 0 | BD32: =SUMIFS(Banco[Monto],Banco[CtaCtbl],$C32,Banco[Periodo Contable],TEXT(BD$3,"mmm-yyyy")) -> 0 | ... BH32: =SUMIFS(Banco[Monto],Banco[CtaCtbl],$C32,Banco[Periodo Contable],TEXT(BH$3,"mmm-yyyy")) -> 0 | BI32: =SUM(Tabla17[[#This Row],[ene-25]:[dic-25]]) -> 0 | BJ32: =SUMIFS(Banco[Monto],Banco[CtaCtbl],$C32,Banco[Periodo Contable],TEXT(BJ$3,"mmm-yyyy")) -> 0 | BK32: =SUMIFS(Banco[Monto],Banco[CtaCtbl],$C32,Banco[Periodo Contable],TEXT(BK$3,"mmm-yyyy")) -> 0 | BL32: =SUMIFS(Banco[Monto],Banco[CtaCtbl],$C32,Banco[Periodo Contable],TEXT(BL$3,"mmm-yyyy")) -> 0 | BM32: =SUMIFS(Banco[Monto],Banco[CtaCtbl],$C32,Banco[Periodo Contable],TEXT(BM$3,"mmm-yyyy")) -> 0 | BN32: =SUMIFS(Banco[Monto],Banco[CtaCtbl],$C32,Banco[Periodo Contable],TEXT(BN$3,"mmm-yyyy")) -> 0 | BO32: =SUMIFS(Banco[Monto],Banco[CtaCtbl],$C32,Banco[Periodo Contable],TEXT(BO$3,"mmm-yyyy")) -> 0 | BP32: =SUMIFS(Banco[Monto],Banco[CtaCtbl],$C32,Banco[Periodo Contable],TEXT(BP$3,"mmm-yyyy")) -> 0 | BQ32: =SUMIFS(Banco[Monto],Banco[CtaCtbl],$C32,Banco[Periodo Contable],TEXT(BQ$3,"mmm-yyyy")) -> 0 | ... BU32: =SUMIFS(Banco[Monto],Banco[CtaCtbl],$C32,Banco[Periodo Contable],TEXT(BU$3,"mmm-yyyy")) -> 0 | BV32: =SUM(Tabla17[[#This Row],[ene-26]:[dic-26]]) -> 0 | BW32: =SUMIFS(Banco[Monto],Banco[CtaCtbl],$C32,Banco[Periodo Contable],TEXT(BW$3,"mmm-yyyy")) -> 0
A33: 2.01.01.04 | B33: Otras Asesorias | C33: =+Tabla17[[#This Row],[Cuenta]]&" - "&Tabla17[[#This Row],[Descripcion Cuenta]] -> 2.01.01.04 - Otras Asesorias | E33: =SUMIFS(Banco[Monto],Banco[CtaCtbl],$C33,Banco[Periodo Contable],TEXT(E$3,"mmm-yyyy")) -> 0 | F33: =SUMIFS(Banco[Monto],Banco[CtaCtbl],$C33,Banco[Periodo Contable],TEXT(F$3,"mmm-yyyy")) -> 0 | G33: =SUMIFS(Banco[Monto],Banco[CtaCtbl],$C33,Banco[Periodo Contable],TEXT(G$3,"mmm-yyyy")) -> 0 | H33: =SUMIFS(Banco[Monto],Banco[CtaCtbl],$C33,Banco[Periodo Contable],TEXT(H$3,"mmm-yyyy")) -> 0 | I33: =SUM(Tabla17[[#This Row],[sept-21]:[dic-21]]) -> 0 | J33: =SUMIFS(Banco[Monto],Banco[CtaCtbl],$C33,Banco[Periodo Contable],TEXT(J$3,"mmm-yyyy")) -> 0 | K33: =SUMIFS(Banco[Monto],Banco[CtaCtbl],$C33,Banco[Periodo Contable],TEXT(K$3,"mmm-yyyy")) -> 0 | L33: =SUMIFS(Banco[Monto],Banco[CtaCtbl],$C33,Banco[Periodo Contable],TEXT(L$3,"mmm-yyyy")) -> 0 | M33: =SUMIFS(Banco[Monto],Banco[CtaCtbl],$C33,Banco[Periodo Contable],TEXT(M$3,"mmm-yyyy")) -> 0 | N33: =SUMIFS(Banco[Monto],Banco[CtaCtbl],$C33,Banco[Periodo Contable],TEXT(N$3,"mmm-yyyy")) -> 0 | O33: =SUMIFS(Banco[Monto],Banco[CtaCtbl],$C33,Banco[Periodo Contable],TEXT(O$3,"mmm-yyyy")) -> 0 | P33: =SUMIFS(Banco[Monto],Banco[CtaCtbl],$C33,Banco[Periodo Contable],TEXT(P$3,"mmm-yyyy")) -> 0 | Q33: =SUMIFS(Banco[Monto],Banco[CtaCtbl],$C33,Banco[Periodo Contable],TEXT(Q$3,"mmm-yyyy")) -> 0 | ... U33: =SUMIFS(Banco[Monto],Banco[CtaCtbl],$C33,Banco[Periodo Contable],TEXT(U$3,"mmm-yyyy")) -> 0 | V33: =SUM(Tabla17[[#This Row],[ene-22]:[dic-22]]) -> 0 | W33: =SUMIFS(Banco[Monto],Banco[CtaCtbl],$C33,Banco[Periodo Contable],TEXT(W$3,"mmm-yyyy")) -> 0 | X33: =SUMIFS(Banco[Monto],Banco[CtaCtbl],$C33,Banco[Periodo Contable],TEXT(X$3,"mmm-yyyy")) -> 0 | Y33: =SUMIFS(Banco[Monto],Banco[CtaCtbl],$C33,Banco[Periodo Contable],TEXT(Y$3,"mmm-yyyy")) -> 0 | Z33: =SUMIFS(Banco[Monto],Banco[CtaCtbl],$C33,Banco[Periodo Contable],TEXT(Z$3,"mmm-yyyy")) -> 0 | AA33: =SUMIFS(Banco[Monto],Banco[CtaCtbl],$C33,Banco[Periodo Contable],TEXT(AA$3,"mmm-yyyy")) -> 0 | AB33: =SUMIFS(Banco[Monto],Banco[CtaCtbl],$C33,Banco[Periodo Contable],TEXT(AB$3,"mmm-yyyy")) -> 0 | AC33: =SUMIFS(Banco[Monto],Banco[CtaCtbl],$C33,Banco[Periodo Contable],TEXT(AC$3,"mmm-yyyy")) -> 0 | AD33: =SUMIFS(Banco[Monto],Banco[CtaCtbl],$C33,Banco[Periodo Contable],TEXT(AD$3,"mmm-yyyy")) -> 0 | ... AH33: =SUMIFS(Banco[Monto],Banco[CtaCtbl],$C33,Banco[Periodo Contable],TEXT(AH$3,"mmm-yyyy")) -> 0 | AI33: =SUM(Tabla17[[#This Row],[ene-23]:[dic-23]]) -> 0 | AJ33: =SUMIFS(Banco[Monto],Banco[CtaCtbl],$C33,Banco[Periodo Contable],TEXT(AJ$3,"mmm-yyyy")) -> 0 | AK33: =SUMIFS(Banco[Monto],Banco[CtaCtbl],$C33,Banco[Periodo Contable],TEXT(AK$3,"mmm-yyyy")) -> 0 | AL33: =SUMIFS(Banco[Monto],Banco[CtaCtbl],$C33,Banco[Periodo Contable],TEXT(AL$3,"mmm-yyyy")) -> 0 | AM33: =SUMIFS(Banco[Monto],Banco[CtaCtbl],$C33,Banco[Periodo Contable],TEXT(AM$3,"mmm-yyyy")) -> 0 | AN33: =SUMIFS(Banco[Monto],Banco[CtaCtbl],$C33,Banco[Periodo Contable],TEXT(AN$3,"mmm-yyyy")) -> 0 | AO33: =SUMIFS(Banco[Monto],Banco[CtaCtbl],$C33,Banco[Periodo Contable],TEXT(AO$3,"mmm-yyyy")) -> 0 | AP33: =SUMIFS(Banco[Monto],Banco[CtaCtbl],$C33,Banco[Periodo Contable],TEXT(AP$3,"mmm-yyyy")) -> 0 | AQ33: =SUMIFS(Banco[Monto],Banco[CtaCtbl],$C33,Banco[Periodo Contable],TEXT(AQ$3,"mmm-yyyy")) -> 0 | ... AU33: =SUMIFS(Banco[Monto],Banco[CtaCtbl],$C33,Banco[Periodo Contable],TEXT(AU$3,"mmm-yyyy")) -> 0 | AV33: =SUM(Tabla17[[#This Row],[ene-24]:[dic-24]]) -> 0 | AW33: =SUMIFS(Banco[Monto],Banco[CtaCtbl],$C33,Banco[Periodo Contable],TEXT(AW$3,"mmm-yyyy")) -> 0 | AX33: =SUMIFS(Banco[Monto],Banco[CtaCtbl],$C33,Banco[Periodo Contable],TEXT(AX$3,"mmm-yyyy")) -> 0 | AY33: =SUMIFS(Banco[Monto],Banco[CtaCtbl],$C33,Banco[Periodo Contable],TEXT(AY$3,"mmm-yyyy")) -> 0 | AZ33: =SUMIFS(Banco[Monto],Banco[CtaCtbl],$C33,Banco[Periodo Contable],TEXT(AZ$3,"mmm-yyyy")) -> 0 | BA33: =SUMIFS(Banco[Monto],Banco[CtaCtbl],$C33,Banco[Periodo Contable],TEXT(BA$3,"mmm-yyyy")) -> 0 | BB33: =SUMIFS(Banco[Monto],Banco[CtaCtbl],$C33,Banco[Periodo Contable],TEXT(BB$3,"mmm-yyyy")) -> 0 | BC33: =SUMIFS(Banco[Monto],Banco[CtaCtbl],$C33,Banco[Periodo Contable],TEXT(BC$3,"mmm-yyyy")) -> 0 | BD33: =SUMIFS(Banco[Monto],Banco[CtaCtbl],$C33,Banco[Periodo Contable],TEXT(BD$3,"mmm-yyyy")) -> 0 | ... BH33: =SUMIFS(Banco[Monto],Banco[CtaCtbl],$C33,Banco[Periodo Contable],TEXT(BH$3,"mmm-yyyy")) -> 0 | BI33: =SUM(Tabla17[[#This Row],[ene-25]:[dic-25]]) -> 8408545 | BJ33: =SUMIFS(Banco[Monto],Banco[CtaCtbl],$C33,Banco[Periodo Contable],TEXT(BJ$3,"mmm-yyyy")) -> 0 | BK33: =SUMIFS(Banco[Monto],Banco[CtaCtbl],$C33,Banco[Periodo Contable],TEXT(BK$3,"mmm-yyyy")) -> 0 | BL33: =SUMIFS(Banco[Monto],Banco[CtaCtbl],$C33,Banco[Periodo Contable],TEXT(BL$3,"mmm-yyyy")) -> 0 | BM33: =SUMIFS(Banco[Monto],Banco[CtaCtbl],$C33,Banco[Periodo Contable],TEXT(BM$3,"mmm-yyyy")) -> 0 | BN33: =SUMIFS(Banco[Monto],Banco[CtaCtbl],$C33,Banco[Periodo Contable],TEXT(BN$3,"mmm-yyyy")) -> 0 | BO33: =SUMIFS(Banco[Monto],Banco[CtaCtbl],$C33,Banco[Periodo Contable],TEXT(BO$3,"mmm-yyyy")) -> 0 | BP33: =SUMIFS(Banco[Monto],Banco[CtaCtbl],$C33,Banco[Periodo Contable],TEXT(BP$3,"mmm-yyyy")) -> 0 | BQ33: =SUMIFS(Banco[Monto],Banco[CtaCtbl],$C33,Banco[Periodo Contable],TEXT(BQ$3,"mmm-yyyy")) -> 0 | ... BU33: =SUMIFS(Banco[Monto],Banco[CtaCtbl],$C33,Banco[Periodo Contable],TEXT(BU$3,"mmm-yyyy")) -> 0 | BV33: =SUM(Tabla17[[#This Row],[ene-26]:[dic-26]]) -> 0 | BW33: =SUMIFS(Banco[Monto],Banco[CtaCtbl],$C33,Banco[Periodo Contable],TEXT(BW$3,"mmm-yyyy")) -> 0
A34: 2.01.02 | B34: Impuestos | C34: =+Tabla17[[#This Row],[Cuenta]]&" - "&Tabla17[[#This Row],[Descripcion Cuenta]] -> 2.01.02 - Impuestos | E34: =SUBTOTAL(9,E35:E36) -> 0 | F34: =SUBTOTAL(9,F35:F36) -> 0 | G34: =SUBTOTAL(9,G35:G36) -> 0 | H34: =SUBTOTAL(9,H35:H36) -> 0 | I34: =SUM(Tabla17[[#This Row],[sept-21]:[dic-21]]) -> 0 | J34: =SUBTOTAL(9,J35:J36) -> 0 | K34: =SUBTOTAL(9,K35:K36) -> 0 | L34: =SUBTOTAL(9,L35:L36) -> 0 | M34: =SUBTOTAL(9,M35:M36) -> 0 | N34: =SUBTOTAL(9,N35:N36) -> 0 | O34: =SUBTOTAL(9,O35:O36) -> 0 | P34: =SUBTOTAL(9,P35:P36) -> 0 | Q34: =SUBTOTAL(9,Q35:Q36) -> 0 | ... BW34: =SUBTOTAL(9,BW35:BW36) -> 0
A35: 2.01.02.01 | B35: Impuestos Bancarios | C35: =+Tabla17[[#This Row],[Cuenta]]&" - "&Tabla17[[#This Row],[Descripcion Cuenta]] -> 2.01.02.01 - Impuestos Bancarios | E35: =SUMIFS(Banco[Monto],Banco[CtaCtbl],$C35,Banco[Periodo Contable],TEXT(E$3,"mmm-yyyy")) -> 0 | F35: =SUMIFS(Banco[Monto],Banco[CtaCtbl],$C35,Banco[Periodo Contable],TEXT(F$3,"mmm-yyyy")) -> 0 | G35: =SUMIFS(Banco[Monto],Banco[CtaCtbl],$C35,Banco[Periodo Contable],TEXT(G$3,"mmm-yyyy")) -> 0 | H35: =SUMIFS(Banco[Monto],Banco[CtaCtbl],$C35,Banco[Periodo Contable],TEXT(H$3,"mmm-yyyy")) -> 0 | I35: =SUM(Tabla17[[#This Row],[sept-21]:[dic-21]]) -> 0 | J35: =SUMIFS(Banco[Monto],Banco[CtaCtbl],$C35,Banco[Periodo Contable],TEXT(J$3,"mmm-yyyy")) -> 0 | K35: =SUMIFS(Banco[Monto],Banco[CtaCtbl],$C35,Banco[Periodo Contable],TEXT(K$3,"mmm-yyyy")) -> 0 | L35: =SUMIFS(Banco[Monto],Banco[CtaCtbl],$C35,Banco[Periodo Contable],TEXT(L$3,"mmm-yyyy")) -> 0 | M35: =SUMIFS(Banco[Monto],Banco[CtaCtbl],$C35,Banco[Periodo Contable],TEXT(M$3,"mmm-yyyy")) -> 0 | N35: =SUMIFS(Banco[Monto],Banco[CtaCtbl],$C35,Banco[Periodo Contable],TEXT(N$3,"mmm-yyyy")) -> 0 | O35: =SUMIFS(Banco[Monto],Banco[CtaCtbl],$C35,Banco[Periodo Contable],TEXT(O$3,"mmm-yyyy")) -> 0 | P35: =SUMIFS(Banco[Monto],Banco[CtaCtbl],$C35,Banco[Periodo Contable],TEXT(P$3,"mmm-yyyy")) -> 0 | Q35: =SUMIFS(Banco[Monto],Banco[CtaCtbl],$C35,Banco[Periodo Contable],TEXT(Q$3,"mmm-yyyy")) -> 0 | ... U35: =SUMIFS(Banco[Monto],Banco[CtaCtbl],$C35,Banco[Periodo Contable],TEXT(U$3,"mmm-yyyy")) -> 0 | V35: =SUM(Tabla17[[#This Row],[ene-22]:[dic-22]]) -> 0 | W35: =SUMIFS(Banco[Monto],Banco[CtaCtbl],$C35,Banco[Periodo Contable],TEXT(W$3,"mmm-yyyy")) -> 0 | X35: =SUMIFS(Banco[Monto],Banco[CtaCtbl],$C35,Banco[Periodo Contable],TEXT(X$3,"mmm-yyyy")) -> 0 | Y35: =SUMIFS(Banco[Monto],Banco[CtaCtbl],$C35,Banco[Periodo Contable],TEXT(Y$3,"mmm-yyyy")) -> 0 | Z35: =SUMIFS(Banco[Monto],Banco[CtaCtbl],$C35,Banco[Periodo Contable],TEXT(Z$3,"mmm-yyyy")) -> 0 | AA35: =SUMIFS(Banco[Monto],Banco[CtaCtbl],$C35,Banco[Periodo Contable],TEXT(AA$3,"mmm-yyyy")) -> 0 | AB35: =SUMIFS(Banco[Monto],Banco[CtaCtbl],$C35,Banco[Periodo Contable],TEXT(AB$3,"mmm-yyyy")) -> 0 | AC35: =SUMIFS(Banco[Monto],Banco[CtaCtbl],$C35,Banco[Periodo Contable],TEXT(AC$3,"mmm-yyyy")) -> 0 | AD35: =SUMIFS(Banco[Monto],Banco[CtaCtbl],$C35,Banco[Periodo Contable],TEXT(AD$3,"mmm-yyyy")) -> 0 | ... AH35: =SUMIFS(Banco[Monto],Banco[CtaCtbl],$C35,Banco[Periodo Contable],TEXT(AH$3,"mmm-yyyy")) -> 0 | AI35: =SUM(Tabla17[[#This Row],[ene-23]:[dic-23]]) -> 0 | AJ35: =SUMIFS(Banco[Monto],Banco[CtaCtbl],$C35,Banco[Periodo Contable],TEXT(AJ$3,"mmm-yyyy")) -> 0 | AK35: =SUMIFS(Banco[Monto],Banco[CtaCtbl],$C35,Banco[Periodo Contable],TEXT(AK$3,"mmm-yyyy")) -> 0 | AL35: =SUMIFS(Banco[Monto],Banco[CtaCtbl],$C35,Banco[Periodo Contable],TEXT(AL$3,"mmm-yyyy")) -> 0 | AM35: =SUMIFS(Banco[Monto],Banco[CtaCtbl],$C35,Banco[Periodo Contable],TEXT(AM$3,"mmm-yyyy")) -> 0 | AN35: =SUMIFS(Banco[Monto],Banco[CtaCtbl],$C35,Banco[Periodo Contable],TEXT(AN$3,"mmm-yyyy")) -> 0 | AO35: =SUMIFS(Banco[Monto],Banco[CtaCtbl],$C35,Banco[Periodo Contable],TEXT(AO$3,"mmm-yyyy")) -> 0 | AP35: =SUMIFS(Banco[Monto],Banco[CtaCtbl],$C35,Banco[Periodo Contable],TEXT(AP$3,"mmm-yyyy")) -> 0 | AQ35: =SUMIFS(Banco[Monto],Banco[CtaCtbl],$C35,Banco[Periodo Contable],TEXT(AQ$3,"mmm-yyyy")) -> 0 | ... AU35: =SUMIFS(Banco[Monto],Banco[CtaCtbl],$C35,Banco[Periodo Contable],TEXT(AU$3,"mmm-yyyy")) -> 0 | AV35: =SUM(Tabla17[[#This Row],[ene-24]:[dic-24]]) -> 0 | AW35: =SUMIFS(Banco[Monto],Banco[CtaCtbl],$C35,Banco[Periodo Contable],TEXT(AW$3,"mmm-yyyy")) -> 0 | AX35: =SUMIFS(Banco[Monto],Banco[CtaCtbl],$C35,Banco[Periodo Contable],TEXT(AX$3,"mmm-yyyy")) -> 0 | AY35: =SUMIFS(Banco[Monto],Banco[CtaCtbl],$C35,Banco[Periodo Contable],TEXT(AY$3,"mmm-yyyy")) -> 0 | AZ35: =SUMIFS(Banco[Monto],Banco[CtaCtbl],$C35,Banco[Periodo Contable],TEXT(AZ$3,"mmm-yyyy")) -> 0 | BA35: =SUMIFS(Banco[Monto],Banco[CtaCtbl],$C35,Banco[Periodo Contable],TEXT(BA$3,"mmm-yyyy")) -> 0 | BB35: =SUMIFS(Banco[Monto],Banco[CtaCtbl],$C35,Banco[Periodo Contable],TEXT(BB$3,"mmm-yyyy")) -> 0 | BC35: =SUMIFS(Banco[Monto],Banco[CtaCtbl],$C35,Banco[Periodo Contable],TEXT(BC$3,"mmm-yyyy")) -> -3537 | BD35: =SUMIFS(Banco[Monto],Banco[CtaCtbl],$C35,Banco[Periodo Contable],TEXT(BD$3,"mmm-yyyy")) -> 0 | ... BH35: =SUMIFS(Banco[Monto],Banco[CtaCtbl],$C35,Banco[Periodo Contable],TEXT(BH$3,"mmm-yyyy")) -> 0 | BI35: =SUM(Tabla17[[#This Row],[ene-25]:[dic-25]]) -> -3537 | BJ35: =SUMIFS(Banco[Monto],Banco[CtaCtbl],$C35,Banco[Periodo Contable],TEXT(BJ$3,"mmm-yyyy")) -> 0 | BK35: =SUMIFS(Banco[Monto],Banco[CtaCtbl],$C35,Banco[Periodo Contable],TEXT(BK$3,"mmm-yyyy")) -> 0 | BL35: =SUMIFS(Banco[Monto],Banco[CtaCtbl],$C35,Banco[Periodo Contable],TEXT(BL$3,"mmm-yyyy")) -> 0 | BM35: =SUMIFS(Banco[Monto],Banco[CtaCtbl],$C35,Banco[Periodo Contable],TEXT(BM$3,"mmm-yyyy")) -> 0 | BN35: =SUMIFS(Banco[Monto],Banco[CtaCtbl],$C35,Banco[Periodo Contable],TEXT(BN$3,"mmm-yyyy")) -> 0 | BO35: =SUMIFS(Banco[Monto],Banco[CtaCtbl],$C35,Banco[Periodo Contable],TEXT(BO$3,"mmm-yyyy")) -> 0 | BP35: =SUMIFS(Banco[Monto],Banco[CtaCtbl],$C35,Banco[Periodo Contable],TEXT(BP$3,"mmm-yyyy")) -> 0 | BQ35: =SUMIFS(Banco[Monto],Banco[CtaCtbl],$C35,Banco[Periodo Contable],TEXT(BQ$3,"mmm-yyyy")) -> 0 | ... BU35: =SUMIFS(Banco[Monto],Banco[CtaCtbl],$C35,Banco[Periodo Contable],TEXT(BU$3,"mmm-yyyy")) -> 0 | BV35: =SUM(Tabla17[[#This Row],[ene-26]:[dic-26]]) -> 0 | BW35: =SUMIFS(Banco[Monto],Banco[CtaCtbl],$C35,Banco[Periodo Contable],TEXT(BW$3,"mmm-yyyy")) -> 0
A36: 2.01.02.02 | B36: Impuestos Tributarios | C36: =+Tabla17[[#This Row],[Cuenta]]&" - "&Tabla17[[#This Row],[Descripcion Cuenta]] -> 2.01.02.02 - Impuestos Tributarios | E36: =SUMIFS(Banco[Monto],Banco[CtaCtbl],$C36,Banco[Periodo Contable],TEXT(E$3,"mmm-yyyy")) -> 0 | F36: =SUMIFS(Banco[Monto],Banco[CtaCtbl],$C36,Banco[Periodo Contable],TEXT(F$3,"mmm-yyyy")) -> 0 | G36: =SUMIFS(Banco[Monto],Banco[CtaCtbl],$C36,Banco[Periodo Contable],TEXT(G$3,"mmm-yyyy")) -> 0 | H36: =SUMIFS(Banco[Monto],Banco[CtaCtbl],$C36,Banco[Periodo Contable],TEXT(H$3,"mmm-yyyy")) -> 0 | I36: =SUM(Tabla17[[#This Row],[sept-21]:[dic-21]]) -> 0 | J36: =SUMIFS(Banco[Monto],Banco[CtaCtbl],$C36,Banco[Periodo Contable],TEXT(J$3,"mmm-yyyy")) -> 0 | K36: =SUMIFS(Banco[Monto],Banco[CtaCtbl],$C36,Banco[Periodo Contable],TEXT(K$3,"mmm-yyyy")) -> 0 | L36: =SUMIFS(Banco[Monto],Banco[CtaCtbl],$C36,Banco[Periodo Contable],TEXT(L$3,"mmm-yyyy")) -> 0 | M36: =SUMIFS(Banco[Monto],Banco[CtaCtbl],$C36,Banco[Periodo Contable],TEXT(M$3,"mmm-yyyy")) -> 0 | N36: =SUMIFS(Banco[Monto],Banco[CtaCtbl],$C36,Banco[Periodo Contable],TEXT(N$3,"mmm-yyyy")) -> 0 | O36: =SUMIFS(Banco[Monto],Banco[CtaCtbl],$C36,Banco[Periodo Contable],TEXT(O$3,"mmm-yyyy")) -> 0 | P36: =SUMIFS(Banco[Monto],Banco[CtaCtbl],$C36,Banco[Periodo Contable],TEXT(P$3,"mmm-yyyy")) -> 0 | Q36: =SUMIFS(Banco[Monto],Banco[CtaCtbl],$C36,Banco[Periodo Contable],TEXT(Q$3,"mmm-yyyy")) -> 0 | ... U36: =SUMIFS(Banco[Monto],Banco[CtaCtbl],$C36,Banco[Periodo Contable],TEXT(U$3,"mmm-yyyy")) -> 0 | V36: =SUM(Tabla17[[#This Row],[ene-22]:[dic-22]]) -> 0 | W36: =SUMIFS(Banco[Monto],Banco[CtaCtbl],$C36,Banco[Periodo Contable],TEXT(W$3,"mmm-yyyy")) -> 0 | X36: =SUMIFS(Banco[Monto],Banco[CtaCtbl],$C36,Banco[Periodo Contable],TEXT(X$3,"mmm-yyyy")) -> 0 | Y36: =SUMIFS(Banco[Monto],Banco[CtaCtbl],$C36,Banco[Periodo Contable],TEXT(Y$3,"mmm-yyyy")) -> 0 | Z36: =SUMIFS(Banco[Monto],Banco[CtaCtbl],$C36,Banco[Periodo Contable],TEXT(Z$3,"mmm-yyyy")) -> 0 | AA36: =SUMIFS(Banco[Monto],Banco[CtaCtbl],$C36,Banco[Periodo Contable],TEXT(AA$3,"mmm-yyyy")) -> 0 | AB36: =SUMIFS(Banco[Monto],Banco[CtaCtbl],$C36,Banco[Periodo Contable],TEXT(AB$3,"mmm-yyyy")) -> 0 | AC36: =SUMIFS(Banco[Monto],Banco[CtaCtbl],$C36,Banco[Periodo Contable],TEXT(AC$3,"mmm-yyyy")) -> 0 | AD36: =SUMIFS(Banco[Monto],Banco[CtaCtbl],$C36,Banco[Periodo Contable],TEXT(AD$3,"mmm-yyyy")) -> 0 | ... AH36: =SUMIFS(Banco[Monto],Banco[CtaCtbl],$C36,Banco[Periodo Contable],TEXT(AH$3,"mmm-yyyy")) -> 0 | AI36: =SUM(Tabla17[[#This Row],[ene-23]:[dic-23]]) -> 0 | AJ36: =SUMIFS(Banco[Monto],Banco[CtaCtbl],$C36,Banco[Periodo Contable],TEXT(AJ$3,"mmm-yyyy")) -> 0 | AK36: =SUMIFS(Banco[Monto],Banco[CtaCtbl],$C36,Banco[Periodo Contable],TEXT(AK$3,"mmm-yyyy")) -> 0 | AL36: =SUMIFS(Banco[Monto],Banco[CtaCtbl],$C36,Banco[Periodo Contable],TEXT(AL$3,"mmm-yyyy")) -> 0 | AM36: =SUMIFS(Banco[Monto],Banco[CtaCtbl],$C36,Banco[Periodo Contable],TEXT(AM$3,"mmm-yyyy")) -> 0 | AN36: =SUMIFS(Banco[Monto],Banco[CtaCtbl],$C36,Banco[Periodo Contable],TEXT(AN$3,"mmm-yyyy")) -> 0 | AO36: =SUMIFS(Banco[Monto],Banco[CtaCtbl],$C36,Banco[Periodo Contable],TEXT(AO$3,"mmm-yyyy")) -> 0 | AP36: =SUMIFS(Banco[Monto],Banco[CtaCtbl],$C36,Banco[Periodo Contable],TEXT(AP$3,"mmm-yyyy")) -> 0 | AQ36: =SUMIFS(Banco[Monto],Banco[CtaCtbl],$C36,Banco[Periodo Contable],TEXT(AQ$3,"mmm-yyyy")) -> 0 | ... AU36: =SUMIFS(Banco[Monto],Banco[CtaCtbl],$C36,Banco[Periodo Contable],TEXT(AU$3,"mmm-yyyy")) -> 0 | AV36: =SUM(Tabla17[[#This Row],[ene-24]:[dic-24]]) -> 0 | AW36: =SUMIFS(Banco[Monto],Banco[CtaCtbl],$C36,Banco[Periodo Contable],TEXT(AW$3,"mmm-yyyy")) -> 0 | AX36: =SUMIFS(Banco[Monto],Banco[CtaCtbl],$C36,Banco[Periodo Contable],TEXT(AX$3,"mmm-yyyy")) -> 0 | AY36: =SUMIFS(Banco[Monto],Banco[CtaCtbl],$C36,Banco[Periodo Contable],TEXT(AY$3,"mmm-yyyy")) -> 0 | AZ36: =SUMIFS(Banco[Monto],Banco[CtaCtbl],$C36,Banco[Periodo Contable],TEXT(AZ$3,"mmm-yyyy")) -> 0 | BA36: =SUMIFS(Banco[Monto],Banco[CtaCtbl],$C36,Banco[Periodo Contable],TEXT(BA$3,"mmm-yyyy")) -> 0 | BB36: =SUMIFS(Banco[Monto],Banco[CtaCtbl],$C36,Banco[Periodo Contable],TEXT(BB$3,"mmm-yyyy")) -> 0 | BC36: =SUMIFS(Banco[Monto],Banco[CtaCtbl],$C36,Banco[Periodo Contable],TEXT(BC$3,"mmm-yyyy")) -> 0 | BD36: =SUMIFS(Banco[Monto],Banco[CtaCtbl],$C36,Banco[Periodo Contable],TEXT(BD$3,"mmm-yyyy")) -> 0 | ... BH36: =SUMIFS(Banco[Monto],Banco[CtaCtbl],$C36,Banco[Periodo Contable],TEXT(BH$3,"mmm-yyyy")) -> 0 | BI36: =SUM(Tabla17[[#This Row],[ene-25]:[dic-25]]) -> 0 | BJ36: =SUMIFS(Banco[Monto],Banco[CtaCtbl],$C36,Banco[Periodo Contable],TEXT(BJ$3,"mmm-yyyy")) -> 0 | BK36: =SUMIFS(Banco[Monto],Banco[CtaCtbl],$C36,Banco[Periodo Contable],TEXT(BK$3,"mmm-yyyy")) -> 0 | BL36: =SUMIFS(Banco[Monto],Banco[CtaCtbl],$C36,Banco[Periodo Contable],TEXT(BL$3,"mmm-yyyy")) -> 0 | BM36: =SUMIFS(Banco[Monto],Banco[CtaCtbl],$C36,Banco[Periodo Contable],TEXT(BM$3,"mmm-yyyy")) -> 0 | BN36: =SUMIFS(Banco[Monto],Banco[CtaCtbl],$C36,Banco[Periodo Contable],TEXT(BN$3,"mmm-yyyy")) -> 0 | BO36: =SUMIFS(Banco[Monto],Banco[CtaCtbl],$C36,Banco[Periodo Contable],TEXT(BO$3,"mmm-yyyy")) -> 0 | BP36: =SUMIFS(Banco[Monto],Banco[CtaCtbl],$C36,Banco[Periodo Contable],TEXT(BP$3,"mmm-yyyy")) -> 0 | BQ36: =SUMIFS(Banco[Monto],Banco[CtaCtbl],$C36,Banco[Periodo Contable],TEXT(BQ$3,"mmm-yyyy")) -> 0 | ... BU36: =SUMIFS(Banco[Monto],Banco[CtaCtbl],$C36,Banco[Periodo Contable],TEXT(BU$3,"mmm-yyyy")) -> 0 | BV36: =SUM(Tabla17[[#This Row],[ene-26]:[dic-26]]) -> 0 | BW36: =SUMIFS(Banco[Monto],Banco[CtaCtbl],$C36,Banco[Periodo Contable],TEXT(BW$3,"mmm-yyyy")) -> 0
A37: 2.01.03 | B37: Servicios | C37: =+Tabla17[[#This Row],[Cuenta]]&" - "&Tabla17[[#This Row],[Descripcion Cuenta]] -> 2.01.03 - Servicios | E37: =SUBTOTAL(9,E38:E58) -> 0 | F37: =SUBTOTAL(9,F38:F58) -> 0 | G37: =SUBTOTAL(9,G38:G58) -> -614571 | H37: =SUBTOTAL(9,H38:H58) -> 0 | I37: =SUM(Tabla17[[#This Row],[sept-21]:[dic-21]]) -> -614571 | J37: =SUBTOTAL(9,J38:J58) -> -233827 | K37: =SUBTOTAL(9,K38:K58) -> -119949 | L37: =SUBTOTAL(9,L38:L58) -> -2300 | M37: =SUBTOTAL(9,M38:M58) -> -380572 | N37: =SUBTOTAL(9,N38:N58) -> -380572 | O37: =SUBTOTAL(9,O38:O58) -> 0 | P37: =SUBTOTAL(9,P38:P58) -> 0 | Q37: =SUBTOTAL(9,Q38:Q58) -> 0 | ... BW37: =SUBTOTAL(9,BW38:BW58) -> 0
A38: 2.01.03.01 | B38: Licencias Software | C38: =+Tabla17[[#This Row],[Cuenta]]&" - "&Tabla17[[#This Row],[Descripcion Cuenta]] -> 2.01.03.01 - Licencias Software | E38: =SUMIFS(Banco[Monto],Banco[CtaCtbl],$C38,Banco[Periodo Contable],TEXT(E$3,"mmm-yyyy")) -> 0 | F38: =SUMIFS(Banco[Monto],Banco[CtaCtbl],$C38,Banco[Periodo Contable],TEXT(F$3,"mmm-yyyy")) -> 0 | G38: =SUMIFS(Banco[Monto],Banco[CtaCtbl],$C38,Banco[Periodo Contable],TEXT(G$3,"mmm-yyyy")) -> 0 | H38: =SUMIFS(Banco[Monto],Banco[CtaCtbl],$C38,Banco[Periodo Contable],TEXT(H$3,"mmm-yyyy")) -> 0 | I38: =SUM(Tabla17[[#This Row],[sept-21]:[dic-21]]) -> 0 | J38: =SUMIFS(Banco[Monto],Banco[CtaCtbl],$C38,Banco[Periodo Contable],TEXT(J$3,"mmm-yyyy")) -> 0 | K38: =SUMIFS(Banco[Monto],Banco[CtaCtbl],$C38,Banco[Periodo Contable],TEXT(K$3,"mmm-yyyy")) -> 0 | L38: =SUMIFS(Banco[Monto],Banco[CtaCtbl],$C38,Banco[Periodo Contable],TEXT(L$3,"mmm-yyyy")) -> 0 | M38: =SUMIFS(Banco[Monto],Banco[CtaCtbl],$C38,Banco[Periodo Contable],TEXT(M$3,"mmm-yyyy")) -> 0 | N38: =SUMIFS(Banco[Monto],Banco[CtaCtbl],$C38,Banco[Periodo Contable],TEXT(N$3,"mmm-yyyy")) -> 0 | O38: =SUMIFS(Banco[Monto],Banco[CtaCtbl],$C38,Banco[Periodo Contable],TEXT(O$3,"mmm-yyyy")) -> 0 | P38: =SUMIFS(Banco[Monto],Banco[CtaCtbl],$C38,Banco[Periodo Contable],TEXT(P$3,"mmm-yyyy")) -> 0 | Q38: =SUMIFS(Banco[Monto],Banco[CtaCtbl],$C38,Banco[Periodo Contable],TEXT(Q$3,"mmm-yyyy")) -> 0 | ... U38: =SUMIFS(Banco[Monto],Banco[CtaCtbl],$C38,Banco[Periodo Contable],TEXT(U$3,"mmm-yyyy")) -> 0 | V38: =SUM(Tabla17[[#This Row],[ene-22]:[dic-22]]) -> 0 | W38: =SUMIFS(Banco[Monto],Banco[CtaCtbl],$C38,Banco[Periodo Contable],TEXT(W$3,"mmm-yyyy")) -> 0 | X38: =SUMIFS(Banco[Monto],Banco[CtaCtbl],$C38,Banco[Periodo Contable],TEXT(X$3,"mmm-yyyy")) -> 0 | Y38: =SUMIFS(Banco[Monto],Banco[CtaCtbl],$C38,Banco[Periodo Contable],TEXT(Y$3,"mmm-yyyy")) -> 0 | Z38: =SUMIFS(Banco[Monto],Banco[CtaCtbl],$C38,Banco[Periodo Contable],TEXT(Z$3,"mmm-yyyy")) -> 0 | AA38: =SUMIFS(Banco[Monto],Banco[CtaCtbl],$C38,Banco[Periodo Contable],TEXT(AA$3,"mmm-yyyy")) -> 0 | AB38: =SUMIFS(Banco[Monto],Banco[CtaCtbl],$C38,Banco[Periodo Contable],TEXT(AB$3,"mmm-yyyy")) -> 0 | AC38: =SUMIFS(Banco[Monto],Banco[CtaCtbl],$C38,Banco[Periodo Contable],TEXT(AC$3,"mmm-yyyy")) -> 0 | AD38: =SUMIFS(Banco[Monto],Banco[CtaCtbl],$C38,Banco[Periodo Contable],TEXT(AD$3,"mmm-yyyy")) -> 0 | ... AH38: =SUMIFS(Banco[Monto],Banco[CtaCtbl],$C38,Banco[Periodo Contable],TEXT(AH$3,"mmm-yyyy")) -> 0 | AI38: =SUM(Tabla17[[#This Row],[ene-23]:[dic-23]]) -> 0 | AJ38: =SUMIFS(Banco[Monto],Banco[CtaCtbl],$C38,Banco[Periodo Contable],TEXT(AJ$3,"mmm-yyyy")) -> 0 | AK38: =SUMIFS(Banco[Monto],Banco[CtaCtbl],$C38,Banco[Periodo Contable],TEXT(AK$3,"mmm-yyyy")) -> 0 | AL38: =SUMIFS(Banco[Monto],Banco[CtaCtbl],$C38,Banco[Periodo Contable],TEXT(AL$3,"mmm-yyyy")) -> 0 | AM38: =SUMIFS(Banco[Monto],Banco[CtaCtbl],$C38,Banco[Periodo Contable],TEXT(AM$3,"mmm-yyyy")) -> 0 | AN38: =SUMIFS(Banco[Monto],Banco[CtaCtbl],$C38,Banco[Periodo Contable],TEXT(AN$3,"mmm-yyyy")) -> 0 | AO38: =SUMIFS(Banco[Monto],Banco[CtaCtbl],$C38,Banco[Periodo Contable],TEXT(AO$3,"mmm-yyyy")) -> 0 | AP38: =SUMIFS(Banco[Monto],Banco[CtaCtbl],$C38,Banco[Periodo Contable],TEXT(AP$3,"mmm-yyyy")) -> 0 | AQ38: =SUMIFS(Banco[Monto],Banco[CtaCtbl],$C38,Banco[Periodo Contable],TEXT(AQ$3,"mmm-yyyy")) -> 0 | ... AU38: =SUMIFS(Banco[Monto],Banco[CtaCtbl],$C38,Banco[Periodo Contable],TEXT(AU$3,"mmm-yyyy")) -> 0 | AV38: =SUM(Tabla17[[#This Row],[ene-24]:[dic-24]]) -> 0 | AW38: =SUMIFS(Banco[Monto],Banco[CtaCtbl],$C38,Banco[Periodo Contable],TEXT(AW$3,"mmm-yyyy")) -> 0 | AX38: =SUMIFS(Banco[Monto],Banco[CtaCtbl],$C38,Banco[Periodo Contable],TEXT(AX$3,"mmm-yyyy")) -> 0 | AY38: =SUMIFS(Banco[Monto],Banco[CtaCtbl],$C38,Banco[Periodo Contable],TEXT(AY$3,"mmm-yyyy")) -> 0 | AZ38: =SUMIFS(Banco[Monto],Banco[CtaCtbl],$C38,Banco[Periodo Contable],TEXT(AZ$3,"mmm-yyyy")) -> 0 | BA38: =SUMIFS(Banco[Monto],Banco[CtaCtbl],$C38,Banco[Periodo Contable],TEXT(BA$3,"mmm-yyyy")) -> 0 | BB38: =SUMIFS(Banco[Monto],Banco[CtaCtbl],$C38,Banco[Periodo Contable],TEXT(BB$3,"mmm-yyyy")) -> 0 | BC38: =SUMIFS(Banco[Monto],Banco[CtaCtbl],$C38,Banco[Periodo Contable],TEXT(BC$3,"mmm-yyyy")) -> 0 | BD38: =SUMIFS(Banco[Monto],Banco[CtaCtbl],$C38,Banco[Periodo Contable],TEXT(BD$3,"mmm-yyyy")) -> 0 | ... BH38: =SUMIFS(Banco[Monto],Banco[CtaCtbl],$C38,Banco[Periodo Contable],TEXT(BH$3,"mmm-yyyy")) -> 0 | BI38: =SUM(Tabla17[[#This Row],[ene-25]:[dic-25]]) -> 0 | BJ38: =SUMIFS(Banco[Monto],Banco[CtaCtbl],$C38,Banco[Periodo Contable],TEXT(BJ$3,"mmm-yyyy")) -> 0 | BK38: =SUMIFS(Banco[Monto],Banco[CtaCtbl],$C38,Banco[Periodo Contable],TEXT(BK$3,"mmm-yyyy")) -> 0 | BL38: =SUMIFS(Banco[Monto],Banco[CtaCtbl],$C38,Banco[Periodo Contable],TEXT(BL$3,"mmm-yyyy")) -> 0 | BM38: =SUMIFS(Banco[Monto],Banco[CtaCtbl],$C38,Banco[Periodo Contable],TEXT(BM$3,"mmm-yyyy")) -> 0 | BN38: =SUMIFS(Banco[Monto],Banco[CtaCtbl],$C38,Banco[Periodo Contable],TEXT(BN$3,"mmm-yyyy")) -> 0 | BO38: =SUMIFS(Banco[Monto],Banco[CtaCtbl],$C38,Banco[Periodo Contable],TEXT(BO$3,"mmm-yyyy")) -> 0 | BP38: =SUMIFS(Banco[Monto],Banco[CtaCtbl],$C38,Banco[Periodo Contable],TEXT(BP$3,"mmm-yyyy")) -> 0 | BQ38: =SUMIFS(Banco[Monto],Banco[CtaCtbl],$C38,Banco[Periodo Contable],TEXT(BQ$3,"mmm-yyyy")) -> 0 | ... BU38: =SUMIFS(Banco[Monto],Banco[CtaCtbl],$C38,Banco[Periodo Contable],TEXT(BU$3,"mmm-yyyy")) -> 0 | BV38: =SUM(Tabla17[[#This Row],[ene-26]:[dic-26]]) -> 0 | BW38: =SUMIFS(Banco[Monto],Banco[CtaCtbl],$C38,Banco[Periodo Contable],TEXT(BW$3,"mmm-yyyy")) -> 0
